Workbook

Sheet README
A1: AI unit economics planning tool (v0.1, thin workbook)
A2: Built 2026-09-20. Status: first build from the approved spec. FICTIONAL WORKED EXAMPLE: every organization input is an assumption (grade D). Only dated primary prices are grade A.
A3: What it is
A4: A planning workbook an enterprise runs before it builds AI. Enter the org shape, teams, users and usage; it returns cost by layer, by team and for the organization, plus payback, sensitivity and the one number that would kill the case. Formulas are visible and there are no macros.
A5: How to use it (about 30 minutes)
A6: 1. Org: set the organization, horizon (up to 60 months), scenario, value case, org shape and allocation rule.
A7: 2. Teams: replace the five fictional teams (one team per business unit in v0.1; Teams 1 and 5 are the same kind of seat-based assistant at two calibrations, on purpose). Blue text on pale yellow is an input.
A8: 3. Params: review every starter value (grade D). Replace any you can with the enterprise's own value; the Summary shows how much cost still rests on starters.
A9: 4. PriceBook: check every price against the provider's page and follow the refresh procedure at the bottom of that sheet.
A10: 5. Read Summary, then Sensitivity (kill number), Scenarios, Allocation (cost-center table) and Tests (all twelve should pass).
A11: Colours
A12: Blue text on pale yellow = input. Black = formula. Green = link to another sheet.
... A24: Evidence base: evidence/. Design: research/ and spec/. Build scripts and the independent reference model used to verify this workbook: model/build/.

Sheet Summary
A1: AI unit economics: summary
A2: FICTIONAL WORKED EXAMPLE. Every input is an assumption (grade D) except dated primary prices (grade A). Not a forecast for any real organization.
A4: Settings (change them on the Org sheet)
A5: Organization | B5: =Org!$B$4 -> Northwind Example Co (fictional)
A6: Scenario | B6: =Org!$B$6 -> Base
A7: Value case | B7: =Org!$B$7 -> Base
A8: Org shape | B8: =Org!$B$8 -> Hub-and-spoke
A9: Allocation rule | B9: =Org!$B$9 -> Usage-proportional
A10: Horizon (months) | B10: =Org!$B$5 -> 36
A11: =IF(Org!$B$6="High-cost","Stress case: every parameter is at its high value at once. Not a likely outcome.","")
A13: Headline (enterprise, over the horizon)
A14: Total cost | B14: =Results!$J$57 -> 18344688
A15: Benefit | B15: =Results!$J$54 -> 26033657
A16: Net value | B16: =Results!$J$58 -> 7688968.4
A17: Payback month | B17: =Results!$J$59 -> 12
A18: Cost per outcome | B18: =Results!$J$60 -> 1.5099503
A19: Benefit per outcome | B19: =Results!$J$62 -> 2.1428289
A20: Cost per active user per month | B20: =Results!$J$61 -> 140.26022
A21: Run-rate at the last horizon month (per month) | B21: =Results!$J$63 -> 458413.6
A23: Cost by layer | B23: =Teams!C$4 -> Corporate knowledge assistant (conservative calibration) | C23: =Teams!D$4 -> Engineering assistant | D23: =Teams!E$4 -> Customer service agent | E23: =Teams!F$4 -> Regulated document review | F23: =Teams!G$4 -> Sales assistant (published-range calibration) | G23: Hub (after shape) | H23: Enterprise
A24: L1 Data readiness | B24: =Results!D36 -> 47681.6 | C24: =Results!E36 -> 39150.56 | D24: =Results!F36 -> 42980 | E24: =Results!G36 -> 141125.63 | F24: =Results!H36 -> 31760.096 | G24: =Results!I36*Results!$D$3 -> 58240 | H24: =Results!J36 -> 360937.89
A25: L2 Setup and infrastructure | B25: =Results!D37 -> 48000 | C25: =Results!E37 -> 48000 | D25: =Results!F37 -> 48000 | E25: =Results!G37 -> 48000 | F25: =Results!H37 -> 48000 | G25: =Results!I37*Results!$D$3 -> 297600 | H25: =Results!J37 -> 537600
A26: L3 Inference and usage | B26: =Results!D38 -> 3024000 | C26: =Results!E38 -> 1043787.8 | D26: =Results!F38 -> 1287000 | E26: =Results!G38 -> 50143.182 | F26: =Results!H38 -> 2016000 | G26: =Results!I38*Results!$D$3 -> 0 | H26: =Results!J38 -> 7420931
A27: L4 Run and maintenance | B27: =Results!D39 -> 263000 | C27: =Results!E39 -> 164480 | D27: =Results!F39 -> 142115 | E27: =Results!G39 -> 141920 | F27: =Results!H39 -> 222800 | G27: =Results!I39*Results!$D$3 -> 3179735.7 | H27: =Results!J39 -> 4114050.7
A28: L5 People and change | B28: =Results!D40 -> 1408120 | C28: =Results!E40 -> 2233862.4 | D28: =Results!F40 -> 330377 | E28: =Results!G40 -> 1000062.4 | F28: =Results!H40 -> 938746.7 | G28: =Results!I40*Results!$D$3 -> 0 | H28: =Results!J40 -> 5911168.5
A30: Teams (cost includes the allocated hub share) | B30: Buying model | C30: Outcomes | D30: Total cost | E30: Cost per outcome | F30: Cost per active user per month | G30: Benefit | H30: Net value | I30: Payback month
A31: =Teams!$C$4 -> Corporate knowledge assistant (conservative calibration) | B31: =Results!D50 -> Seat | C31: =Results!D52 -> 3618000 | D31: =Results!D57 -> 5843686.8 | E31: =Results!D60 -> 1.6151705 | F31: =Results!D61 -> 96.91023 | G31: =Results!D54 -> 2544720.3 | H31: =Results!D58 -> -3298966.5 | I31: =Results!D59 -> None
A32: =Teams!$D$4 -> Engineering assistant | B32: =Results!E50 -> Seat + usage | C32: =Results!E52 -> 4416000 | D32: =Results!E57 -> 4814394.4 | E32: =Results!E60 -> 1.0902161 | F32: =Results!E61 -> 436.08645 | G32: =Results!E54 -> 13763200 | H32: =Results!E58 -> 8948805.6 | I32: =Results!E59 -> 3
A33: =Teams!$E$4 -> Customer service agent | B33: =Results!F50 -> Per-unit | C33: =Results!F52 -> 1300000 | D33: =Results!F57 -> 2228789 | E33: =Results!F60 -> 1.714453 | F33: =Results!F61 -> n/a | G33: =Results!F54 -> 2590672.5 | H33: =Results!F58 -> 361883.54 | I33: =Results!F59 -> 14
A34: =Teams!$F$4 -> Regulated document review | B34: =Results!G50 -> Per-unit | C34: =Results!G52 -> 403200 | D34: =Results!G57 -> 1498587.7 | E34: =Results!G60 -> 3.7167353 | F34: =Results!G61 -> 446.00824 | G34: =Results!G54 -> 1197383 | H34: =Results!G58 -> -301204.63 | I34: =Results!G59 -> None
A35: =Teams!$G$4 -> Sales assistant (published-range calibration) | B35: =Results!H50 -> Seat | C35: =Results!H52 -> 2412000 | D35: =Results!H57 -> 3959230.3 | E35: =Results!H60 -> 1.6414719 | F35: =Results!H61 -> 98.488315 | G35: =Results!H54 -> 5937680.7 | H35: =Results!H58 -> 1978450.4 | I35: =Results!H59 -> 13
A37: How much of the cost rests on what evidence | B37: Cost | C37: Share
A38: Dated primary prices (A) | B38: =Results!D43 -> 7494384.6 | C38: =Results!E43 -> 0.40853159
A39: Ranges with a warning (B*/C) | B39: =Results!D44 -> 4619616.5 | C39: =Results!E44 -> 0.25182312
A40: Starter values (D) | B40: =Results!D45 -> 6230687 | C40: =Results!E45 -> 0.33964529
A41: Enterprise-entered, off until entered | B41: =Results!D46 -> 0 | C41: =Results!E46 -> 0
A43: Cost lines that are OFF (they understate cost until entered)
A44: =Lines!$A$17&" "&Lines!$B$17&": "&Lines!$H$17 -> CL-14 Environments and base cloud infrastructure: OFF
A45: =Lines!$A$18&" "&Lines!$B$18&": "&Lines!$H$18 -> CL-15 Committed capacity (provisioned cloud or self-hosted GPUs): OFF
A46: =Lines!$A$34&" "&Lines!$B$34&": "&Lines!$H$34 -> CL-31 Compliance audit and governance: OFF
A47: =Lines!$A$35&" "&Lines!$B$35&": "&Lines!$H$35 -> CL-32 Platform and vendor licences: OFF
A49: Acceptance tests (Tests sheet) | B49: =Tests!$C$16 -> ALL 12 PASS
A51: The number that would kill the case
A52: Smallest margin of safety | B52: =Sensitivity!$B$23 -> Realisation share of self-reported time saved
A53: How far it can move before net value reaches zero | B53: =Sensitivity!$B$24 -> can fall by 30% before net value reaches zero (break-even multiplier 0.70x)
A54: Top three drivers by swing in net value | B54: =Sensitivity!$B$27 -> Realisation share of self-reported time saved (swing $26,033,657) | C54: =Sensitivity!$B$28 -> Minutes saved per outcome (swing $26,033,657) | D54: =Sensitivity!$B$29 -> Adoption and volume (active share, outcomes) (swing $11,947,865)

Sheet Org
A1: Organization inputs
A2: Blue text on pale yellow = input. Everything here is a fictional assumption (grade D) unless stated.
A3: Field | B3: Value | C3: Unit / options | D3: Label | E3: Source | F3: Grade
A4: Organization name | B4: Northwind Example Co (fictional) | C4: text | D4: assumed | E4: Fictional worked example (Claude, 2026-09-20) | F4: D
A5: Horizon | B5: 36 | C5: months (max 60) | D5: assumed | E5: Project owner's choice, 2026-09-20 | F5: D
A6: Scenario shown on Summary | B6: Base | C6: Low-cost / Base / High-cost (High-cost is a stress case: every parameter at its high value at once) | D6: assumed | E6: User choice | F6: D
A7: Value case (realisation share) | B7: Base | C7: Low / Base / High | D7: assumed | E7: User choice | F7: D
A8: Org shape | B8: Hub-and-spoke | C8: Centralized / Federated / Hub-and-spoke | D8: assumed | E8: User choice; definitions in research/enterprise-structure.md | F8: D
A9: Allocation rule | B9: Usage-proportional | C9: Usage-proportional / Headcount proxy / Even split / Central budget | D9: assumed | E9: Default per shape (D), research/enterprise-structure.md | F9: D
A10: Person-day rate | B10: 800 | C10: USD per person-day | D10: assumed | E10: spec/starter-values.md (Claude, 2026-09-20); cross-check BLS LAB-02 (S41, S42) | F10: D
A11: Hours per person-day | B11: 8 | C11: hours | D11: assumed | E11: spec/starter-values.md (Claude, 2026-09-20) | F11: D
A12: Working days per year | B12: 220 | C12: days | D12: assumed | E12: spec/starter-values.md (Claude, 2026-09-20) | F12: D
A13: Monitoring units per outcome | B13: 5 | C13: units | D13: assumed | E13: Fictional worked example (Claude, 2026-09-20) | F13: D
A15: Derived
A16: Scenario index (1 low-cost, 2 base, 3 high-cost) | B16: =MATCH($B$6,{"Low-cost","Base","High-cost"},0) -> 2
A17: Value-case index (1 low, 2 base, 3 high) | B17: =MATCH($B$7,{"Low","Base","High"},0) -> 2
A18: Number of active teams | B18: =SUM(Teams!C5:G5) -> 5
A19: Number of business units (v0.1: one team per unit) | B19: =B18 -> 5

Sheet Teams
A1: Teams (worked example: fictional)
A2: One team per business unit in v0.1. Blue text on pale yellow = input. IDs refer to the PriceBook.
A3: Field | B3: Unit / options | C3: Team 1 | D3: Team 2 | E3: Team 3 | F3: Team 4 | G3: Team 5 | H3: Label | I3: Source | J3: Grade
A4: Team name | B4: text | C4: Corporate knowledge assistant (conservative calibration) | D4: Engineering assistant | E4: Customer service agent | F4: Regulated document review | G4: Sales assistant (published-range calibration) | H4: assumed | I4: Fictional worked example (Claude, 2026-09-20); prices come from PriceBook (A) | J4: D
A5: Team is active (1 = counted, 0 = ignored) | B5: 1 / 0 | C5: 1 | D5: 1 | E5: 1 | F5: 1 | G5: 1 | H5: assumed | I5: Fictional worked example (Claude, 2026-09-20); prices come from PriceBook (A) | J5: D
A6: Archetype | B6: text | C6: A1 Knowledge-worker assistant | D6: A2 Developer productivity and agents | E6: A3 High-volume service operations | F6: A4 Regulated document and decision work | G6: A1 Knowledge-worker assistant | H6: assumed | I6: Fictional worked example (Claude, 2026-09-20); prices come from PriceBook (A) | J6: D
A7: Business unit and cost center | B7: text | C7: Corporate functions | D7: Engineering | E7: Customer operations | F7: Risk and legal | G7: Sales and marketing | H7: assumed | I7: Fictional worked example (Claude, 2026-09-20); prices come from PriceBook (A) | J7: D
A8: Buying model | B8: Seat / Seat + usage / Per-unit / Committed capacity | C8: Seat | D8: Seat + usage | E8: Per-unit | F8: Per-unit | G8: Seat | H8: assumed | I8: Fictional worked example (Claude, 2026-09-20); prices come from PriceBook (A) | J8: D
A9: Seat price (price book ID) | B9: ID | C9: SEAT_TEAM_STD | D9: SEAT_ENT | E9: SEAT_TEAM_STD | F9: SEAT_TEAM_STD | G9: SEAT_TEAM_STD | H9: assumed | I9: Fictional worked example (Claude, 2026-09-20); prices come from PriceBook (A) | J9: D
A10: Premium seat price (price book ID) | B10: ID | C10: SEAT_TEAM_PREM | D10: SEAT_TEAM_PREM | E10: SEAT_TEAM_PREM | F10: SEAT_TEAM_PREM | G10: SEAT_TEAM_PREM | H10: assumed | I10: Fictional worked example (Claude, 2026-09-20); prices come from PriceBook (A) | J10: D
A11: Share of licensed users on premium seats | B11: share | C11: 0.1 | D11: 0 | E11: 0 | F11: 0 | G11: 0.1 | H11: assumed | I11: Fictional worked example (Claude, 2026-09-20); prices come from PriceBook (A) | J11: D
A12: Usage included per seat per month (hybrid) | B12: USD | C12: 0 | D12: 0 | E12: 0 | F12: 0 | G12: 0 | H12: assumed | I12: Fictional worked example (Claude, 2026-09-20); prices come from PriceBook (A) | J12: D
A13: Top segment share of active users | B13: share | C13: 0.1 | D13: 0.1 | E13: 0.1 | F13: 0.1 | G13: 0.1 | H13: assumed | I13: Fictional worked example (Claude, 2026-09-20); prices come from PriceBook (A) | J13: D
A14: Top segment intensity vs the rest | B14: multiple | C14: 5 | D14: 5 | E14: 5 | F14: 5 | G14: 5 | H14: assumed | I14: Fictional worked example (Claude, 2026-09-20); prices come from PriceBook (A) | J14: D
A15: Vendor per-outcome price (price book ID, or none) | B15: ID | E15: OUT_FIN | H15: assumed | I15: Fictional worked example (Claude, 2026-09-20); prices come from PriceBook (A) | J15: D
A16: Committed capacity cost | B16: USD per month | C16: 0 | D16: 0 | E16: 0 | F16: 0 | G16: 0 | H16: assumed | I16: Fictional worked example (Claude, 2026-09-20); prices come from PriceBook (A) | J16: D
A17: Committed capacity outcomes per month | B17: outcomes | C17: 0 | D17: 0 | E17: 0 | F17: 0 | G17: 0 | H17: assumed | I17: Fictional worked example (Claude, 2026-09-20); prices come from PriceBook (A) | J17: D
A18: Licensed users | B18: users | C18: 3000 | D18: 400 | E18: 60 | F18: 150 | G18: 2000 | H18: assumed | I18: Fictional worked example (Claude, 2026-09-20); prices come from PriceBook (A) | J18: D
A19: Active share of licensed users at plateau | B19: share | C19: 0.6 | D19: 0.8 | E19: 0.85 | F19: 0.7 | G19: 0.6 | H19: assumed | I19: Fictional worked example (Claude, 2026-09-20); prices come from PriceBook (A) | J19: D
A20: Launch month | B20: month | C20: 1 | D20: 1 | E20: 2 | F20: 3 | G20: 1 | H20: assumed | I20: Fictional worked example (Claude, 2026-09-20); prices come from PriceBook (A) | J20: D
A21: Months to plateau | B21: months | C21: 6 | D21: 4 | E21: 6 | F21: 5 | G21: 6 | H21: assumed | I21: Fictional worked example (Claude, 2026-09-20); prices come from PriceBook (A) | J21: D
A22: Ramp curve | B22: Linear / S | C22: S | D22: Linear | E22: S | F22: S | G22: S | H22: assumed | I22: Fictional worked example (Claude, 2026-09-20); prices come from PriceBook (A) | J22: D
A23: Outcome basis | B23: per user / direct volume | C23: per user | D23: per user | E23: direct volume | F23: per user | G23: per user | H23: assumed | I23: Fictional worked example (Claude, 2026-09-20); prices come from PriceBook (A) | J23: D
A24: Outcomes per active user per month | B24: outcomes | C24: 60 | D24: 400 | E24: 0 | F24: 120 | G24: 60 | H24: assumed | I24: Fictional worked example (Claude, 2026-09-20); prices come from PriceBook (A) | J24: D
A25: Direct volume at plateau | B25: outcomes per month | C25: 0 | D25: 0 | E25: 40000 | F25: 0 | G25: 0 | H25: assumed | I25: Fictional worked example (Claude, 2026-09-20); prices come from PriceBook (A) | J25: D
A26: Main model (price book ID) | B26: ID | C26: M_SONNET5 | D26: M_SONNET5 | E26: M_SONNET5 | F26: M_OPUS5 | G26: M_SONNET5 | H26: assumed | I26: Fictional worked example (Claude, 2026-09-20); prices come from PriceBook (A) | J26: D
A27: Cheaper model (price book ID) | B27: ID | C27: M_HAIKU45 | D27: M_HAIKU45 | E27: M_HAIKU45 | F27: M_SONNET5 | G27: M_HAIKU45 | H27: assumed | I27: Fictional worked example (Claude, 2026-09-20); prices come from PriceBook (A) | J27: D
A28: Share routed to cheaper model | B28: share | C28: 0 | D28: 0 | E28: 0 | F28: 0.5 | G28: 0 | H28: assumed | I28: Fictional worked example (Claude, 2026-09-20); prices come from PriceBook (A) | J28: D
A29: Input tokens per outcome | B29: tokens | C29: 2000 | D29: 8000 | E29: 0 | F29: 30000 | G29: 2000 | H29: assumed | I29: Fictional worked example (Claude, 2026-09-20); prices come from PriceBook (A) | J29: D
A30: Output tokens per outcome | B30: tokens | C30: 500 | D30: 2000 | E30: 0 | F30: 1500 | G30: 500 | H30: assumed | I30: Fictional worked example (Claude, 2026-09-20); prices come from PriceBook (A) | J30: D
A31: Context-management reduction | B31: share | C31: 0 | D31: 0.1 | E31: 0 | F31: 0 | G31: 0 | H31: assumed | I31: Fictional worked example (Claude, 2026-09-20); prices come from PriceBook (A) | J31: D
A32: Cached share of input | B32: share | C32: 0.3 | D32: 0.6 | E32: 0 | F32: 0.3 | G32: 0.3 | H32: assumed | I32: Fictional worked example (Claude, 2026-09-20); prices come from PriceBook (A) | J32: D
A33: Cache-write share of input | B33: share | C33: 0.05 | D33: 0.05 | E33: 0 | F33: 0.05 | G33: 0.05 | H33: assumed | I33: Fictional worked example (Claude, 2026-09-20); prices come from PriceBook (A) | J33: D
A34: Asynchronous (batch) share | B34: share | C34: 0 | D34: 0 | E34: 0 | F34: 0.4 | G34: 0 | H34: assumed | I34: Fictional worked example (Claude, 2026-09-20); prices come from PriceBook (A) | J34: D
A35: Residency multiplier | B35: multiplier | C35: 1 | D35: 1 | E35: 1 | F35: 1.1 | G35: 1 | H35: assumed | I35: Fictional worked example (Claude, 2026-09-20); prices come from PriceBook (A) | J35: D
A36: Agentic workflow | B36: Yes / No | C36: No | D36: Yes | E36: No | F36: No | G36: No | H36: assumed | I36: Fictional worked example (Claude, 2026-09-20); prices come from PriceBook (A) | J36: D
A37: Tool calls per outcome | B37: calls | C37: 0 | D37: 0 | E37: 0 | F37: 0 | G37: 0 | H37: assumed | I37: Fictional worked example (Claude, 2026-09-20); prices come from PriceBook (A) | J37: D
A38: Tool price (price book ID) | B38: ID | C38: U_TOOL_SEARCH | D38: U_TOOL_SEARCH | E38: U_TOOL_SEARCH | F38: U_TOOL_SEARCH | G38: U_TOOL_SEARCH | H38: assumed | I38: Fictional worked example (Claude, 2026-09-20); prices come from PriceBook (A) | J38: D
A39: Guardrail text units per outcome | B39: units | C39: 0 | D39: 0 | E39: 0 | F39: 126 | G39: 0 | H39: assumed | I39: Fictional worked example (Claude, 2026-09-20); prices come from PriceBook (A) | J39: D
A40: Guardrail price (price book ID) | B40: ID | C40: U_GUARD_CF | D40: U_GUARD_CF | E40: U_GUARD_CF | F40: U_GUARD_CF | G40: U_GUARD_CF | H40: assumed | I40: Fictional worked example (Claude, 2026-09-20); prices come from PriceBook (A) | J40: D
A41: Human review share of outputs | B41: share | C41: 0.05 | D41: 0.2 | E41: 0.1 | F41: 1 | G41: 0.05 | H41: assumed | I41: Fictional worked example (Claude, 2026-09-20); prices come from PriceBook (A) | J41: D
A42: Reviewer loaded rate | B42: USD per hour | C42: 46.89 | D42: 46.89 | E42: 46.89 | F42: 46.89 | G42: 46.89 | H42: assumed | I42: Fictional worked example (Claude, 2026-09-20); prices come from PriceBook (A) | J42: D
A43: Source systems | B43: count | C43: 3 | D43: 2 | E43: 3 | F43: 4 | G43: 2 | H43: assumed | I43: Fictional worked example (Claude, 2026-09-20); prices come from PriceBook (A) | J43: D
A44: Documents | B44: count | C44: 20000 | D44: 50000 | E44: 8000 | F44: 200000 | G44: 10000 | H44: assumed | I44: Fictional worked example (Claude, 2026-09-20); prices come from PriceBook (A) | J44: D
A45: Pages per document | B45: pages | C45: 5 | D45: 3 | E45: 4 | F45: 8 | G45: 5 | H45: assumed | I45: Fictional worked example (Claude, 2026-09-20); prices come from PriceBook (A) | J45: D
A46: Parsing price (price book ID) | B46: ID | C46: U_TEXTRACT_TXT | D46: U_TEXTRACT_TXT | E46: U_TEXTRACT_TXT | F46: U_TEXTRACT_TBL | G46: U_TEXTRACT_TXT | H46: assumed | I46: Fictional worked example (Claude, 2026-09-20); prices come from PriceBook (A) | J46: D
A47: Embedding tokens per document | B47: tokens | C47: 3000 | D47: 4000 | E47: 0 | F47: 6000 | G47: 3000 | H47: assumed | I47: Fictional worked example (Claude, 2026-09-20); prices come from PriceBook (A) | J47: D
A48: Embedding price (price book ID) | B48: ID | C48: U_EMB_3L | D48: U_EMB_3L | E48: U_EMB_3L | F48: U_EMB_3L | G48: U_EMB_3L | H48: assumed | I48: Fictional worked example (Claude, 2026-09-20); prices come from PriceBook (A) | J48: D
A49: Team runs its own index | B49: 1 / 0 | C49: 1 | D49: 1 | E49: 0 | F49: 1 | G49: 1 | H49: assumed | I49: Fictional worked example (Claude, 2026-09-20); prices come from PriceBook (A) | J49: D
A50: Index storage | B50: GB | C50: 20 | D50: 40 | E50: 0 | F50: 300 | G50: 10 | H50: assumed | I50: Fictional worked example (Claude, 2026-09-20); prices come from PriceBook (A) | J50: D
A51: Read units per outcome | B51: units | C51: 2 | D51: 5 | E51: 0 | F51: 10 | G51: 2 | H51: assumed | I51: Fictional worked example (Claude, 2026-09-20); prices come from PriceBook (A) | J51: D
A52: Index plan minimum (price book ID) | B52: ID | C52: PL_PINE_STD | D52: PL_PINE_STD | E52: PL_PINE_STD | F52: PL_PINE_STD | G52: PL_PINE_STD | H52: assumed | I52: Fictional worked example (Claude, 2026-09-20); prices come from PriceBook (A) | J52: D
A53: Storage price (price book ID) | B53: ID | C53: U_PINE_STORE | D53: U_PINE_STORE | E53: U_PINE_STORE | F53: U_PINE_STORE | G53: U_PINE_STORE | H53: assumed | I53: Fictional worked example (Claude, 2026-09-20); prices come from PriceBook (A) | J53: D
A54: Read price (price book ID) | B54: ID | C54: U_PINE_READ | D54: U_PINE_READ | E54: U_PINE_READ | F54: U_PINE_READ | G54: U_PINE_READ | H54: assumed | I54: Fictional worked example (Claude, 2026-09-20); prices come from PriceBook (A) | J54: D
A55: Minutes saved per outcome | B55: minutes | C55: 2 | D55: 4 | E55: 6 | F55: 8 | G55: 7 | H55: assumed | I55: Fictional worked example (Claude, 2026-09-20); prices come from PriceBook (A) | J55: D
A56: Loaded hourly rate of time saved | B56: USD per hour | C56: 46.89 | D56: 110 | E56: 46.89 | F56: 46.89 | G56: 46.89 | H56: assumed | I56: Fictional worked example (Claude, 2026-09-20); prices come from PriceBook (A) | J56: D
A57: Quality or acceptance rate | B57: share | C57: 0.9 | D57: 0.85 | E57: 0.85 | F57: 0.95 | G57: 0.9 | H57: assumed | I57: Fictional worked example (Claude, 2026-09-20); prices come from PriceBook (A) | J57: D
A59: Derived from inputs and the PriceBook (formulas)
A60: Seat billed (1/0) | C60: =IF(OR(C8="Seat",C8="Seat + usage"),1,0) -> 1 | D60: =IF(OR(D8="Seat",D8="Seat + usage"),1,0) -> 1 | E60: =IF(OR(E8="Seat",E8="Seat + usage"),1,0) -> 0 | F60: =IF(OR(F8="Seat",F8="Seat + usage"),1,0) -> 0 | G60: =IF(OR(G8="Seat",G8="Seat + usage"),1,0) -> 1
A61: Seat + usage (1/0) | C61: =IF(C8="Seat + usage",1,0) -> 0 | D61: =IF(D8="Seat + usage",1,0) -> 1 | E61: =IF(E8="Seat + usage",1,0) -> 0 | F61: =IF(F8="Seat + usage",1,0) -> 0 | G61: =IF(G8="Seat + usage",1,0) -> 0
A62: Per-unit, token-billed (1/0) | C62: =IF(AND(C8="Per-unit",C15=""),1,0) -> 0 | D62: =IF(AND(D8="Per-unit",D15=""),1,0) -> 0 | E62: =IF(AND(E8="Per-unit",E15=""),1,0) -> 0 | F62: =IF(AND(F8="Per-unit",F15=""),1,0) -> 1 | G62: =IF(AND(G8="Per-unit",G15=""),1,0) -> 0
A63: Per-unit, vendor outcome price (1/0) | C63: =IF(AND(C8="Per-unit",C15<>""),1,0) -> 0 | D63: =IF(AND(D8="Per-unit",D15<>""),1,0) -> 0 | E63: =IF(AND(E8="Per-unit",E15<>""),1,0) -> 1 | F63: =IF(AND(F8="Per-unit",F15<>""),1,0) -> 0 | G63: =IF(AND(G8="Per-unit",G15<>""),1,0) -> 0
A64: Committed capacity (1/0) | C64: =IF(C8="Committed capacity",1,0) -> 0 | D64: =IF(D8="Committed capacity",1,0) -> 0 | E64: =IF(E8="Committed capacity",1,0) -> 0 | F64: =IF(F8="Committed capacity",1,0) -> 0 | G64: =IF(G8="Committed capacity",1,0) -> 0
A65: API-billed extras apply (1/0) | C65: =IF(C61+C62+C64>0,1,0) -> 0 | D65: =IF(D61+D62+D64>0,1,0) -> 1 | E65: =IF(E61+E62+E64>0,1,0) -> 0 | F65: =IF(F61+F62+F64>0,1,0) -> 1 | G65: =IF(G61+G62+G64>0,1,0) -> 0
A66: Blended seat price (USD per licensed user per month) | C66: =(1-C11)*IFERROR(INDEX(PriceBook!$E$4:$E$203,MATCH(C9,PriceBook!$A$4:$A$203,0)),0)+C11*IFERROR(INDEX(PriceBook!$E$4:$E$203,MATCH(C10,PriceBook!$A$4:$A$203,0)),0) -> 28 | D66: =(1-D11)*IFERROR(INDEX(PriceBook!$E$4:$E$203,MATCH(D9,PriceBook!$A$4:$A$203,0)),0)+D11*IFERROR(INDEX(PriceBook!$E$4:$E$203,MATCH(D10,PriceBook!$A$4:$A$203,0)),0) -> 20 | E66: =(1-E11)*IFERROR(INDEX(PriceBook!$E$4:$E$203,MATCH(E9,PriceBook!$A$4:$A$203,0)),0)+E11*IFERROR(INDEX(PriceBook!$E$4:$E$203,MATCH(E10,PriceBook!$A$4:$A$203,0)),0) -> 20 | F66: =(1-F11)*IFERROR(INDEX(PriceBook!$E$4:$E$203,MATCH(F9,PriceBook!$A$4:$A$203,0)),0)+F11*IFERROR(INDEX(PriceBook!$E$4:$E$203,MATCH(F10,PriceBook!$A$4:$A$203,0)),0) -> 20 | G66: =(1-G11)*IFERROR(INDEX(PriceBook!$E$4:$E$203,MATCH(G9,PriceBook!$A$4:$A$203,0)),0)+G11*IFERROR(INDEX(PriceBook!$E$4:$E$203,MATCH(G10,PriceBook!$A$4:$A$203,0)),0) -> 28
A67: Vendor per-outcome price (USD) | C67: =IFERROR(INDEX(PriceBook!$E$4:$E$203,MATCH(C15,PriceBook!$A$4:$A$203,0)),0) -> 0 | D67: =IFERROR(INDEX(PriceBook!$E$4:$E$203,MATCH(D15,PriceBook!$A$4:$A$203,0)),0) -> 0 | E67: =IFERROR(INDEX(PriceBook!$E$4:$E$203,MATCH(E15,PriceBook!$A$4:$A$203,0)),0) -> 0.99 | F67: =IFERROR(INDEX(PriceBook!$E$4:$E$203,MATCH(F15,PriceBook!$A$4:$A$203,0)),0) -> 0 | G67: =IFERROR(INDEX(PriceBook!$E$4:$E$203,MATCH(G15,PriceBook!$A$4:$A$203,0)),0) -> 0
A68: Blended input price (USD per million tokens) | C68: =(1-C28)*IFERROR(INDEX(PriceBook!$E$4:$E$203,MATCH(C26,PriceBook!$A$4:$A$203,0)),0)+C28*IFERROR(INDEX(PriceBook!$E$4:$E$203,MATCH(C27,PriceBook!$A$4:$A$203,0)),0) -> 2 | D68: =(1-D28)*IFERROR(INDEX(PriceBook!$E$4:$E$203,MATCH(D26,PriceBook!$A$4:$A$203,0)),0)+D28*IFERROR(INDEX(PriceBook!$E$4:$E$203,MATCH(D27,PriceBook!$A$4:$A$203,0)),0) -> 2 | E68: =(1-E28)*IFERROR(INDEX(PriceBook!$E$4:$E$203,MATCH(E26,PriceBook!$A$4:$A$203,0)),0)+E28*IFERROR(INDEX(PriceBook!$E$4:$E$203,MATCH(E27,PriceBook!$A$4:$A$203,0)),0) -> 2 | F68: =(1-F28)*IFERROR(INDEX(PriceBook!$E$4:$E$203,MATCH(F26,PriceBook!$A$4:$A$203,0)),0)+F28*IFERROR(INDEX(PriceBook!$E$4:$E$203,MATCH(F27,PriceBook!$A$4:$A$203,0)),0) -> 3.5 | G68: =(1-G28)*IFERROR(INDEX(PriceBook!$E$4:$E$203,MATCH(G26,PriceBook!$A$4:$A$203,0)),0)+G28*IFERROR(INDEX(PriceBook!$E$4:$E$203,MATCH(G27,PriceBook!$A$4:$A$203,0)),0) -> 2
A69: Blended output price (USD per million tokens) | C69: =(1-C28)*IFERROR(INDEX(PriceBook!$F$4:$F$203,MATCH(C26,PriceBook!$A$4:$A$203,0)),0)+C28*IFERROR(INDEX(PriceBook!$F$4:$F$203,MATCH(C27,PriceBook!$A$4:$A$203,0)),0) -> 10 | D69: =(1-D28)*IFERROR(INDEX(PriceBook!$F$4:$F$203,MATCH(D26,PriceBook!$A$4:$A$203,0)),0)+D28*IFERROR(INDEX(PriceBook!$F$4:$F$203,MATCH(D27,PriceBook!$A$4:$A$203,0)),0) -> 10 | E69: =(1-E28)*IFERROR(INDEX(PriceBook!$F$4:$F$203,MATCH(E26,PriceBook!$A$4:$A$203,0)),0)+E28*IFERROR(INDEX(PriceBook!$F$4:$F$203,MATCH(E27,PriceBook!$A$4:$A$203,0)),0) -> 10 | F69: =(1-F28)*IFERROR(INDEX(PriceBook!$F$4:$F$203,MATCH(F26,PriceBook!$A$4:$A$203,0)),0)+F28*IFERROR(INDEX(PriceBook!$F$4:$F$203,MATCH(F27,PriceBook!$A$4:$A$203,0)),0) -> 17.5 | G69: =(1-G28)*IFERROR(INDEX(PriceBook!$F$4:$F$203,MATCH(G26,PriceBook!$A$4:$A$203,0)),0)+G28*IFERROR(INDEX(PriceBook!$F$4:$F$203,MATCH(G27,PriceBook!$A$4:$A$203,0)),0) -> 10
A70: Input price factor after caching | C70: =(1-C32-C33)+C32*IFERROR(INDEX(PriceBook!$G$4:$G$203,MATCH(C26,PriceBook!$A$4:$A$203,0)),0)+C33*IFERROR(INDEX(PriceBook!$H$4:$H$203,MATCH(C26,PriceBook!$A$4:$A$203,0)),0) -> 0.7425 | D70: =(1-D32-D33)+D32*IFERROR(INDEX(PriceBook!$G$4:$G$203,MATCH(D26,PriceBook!$A$4:$A$203,0)),0)+D33*IFERROR(INDEX(PriceBook!$H$4:$H$203,MATCH(D26,PriceBook!$A$4:$A$203,0)),0) -> 0.4725 | E70: =(1-E32-E33)+E32*IFERROR(INDEX(PriceBook!$G$4:$G$203,MATCH(E26,PriceBook!$A$4:$A$203,0)),0)+E33*IFERROR(INDEX(PriceBook!$H$4:$H$203,MATCH(E26,PriceBook!$A$4:$A$203,0)),0) -> 1 | F70: =(1-F32-F33)+F32*IFERROR(INDEX(PriceBook!$G$4:$G$203,MATCH(F26,PriceBook!$A$4:$A$203,0)),0)+F33*IFERROR(INDEX(PriceBook!$H$4:$H$203,MATCH(F26,PriceBook!$A$4:$A$203,0)),0) -> 0.7425 | G70: =(1-G32-G33)+G32*IFERROR(INDEX(PriceBook!$G$4:$G$203,MATCH(G26,PriceBook!$A$4:$A$203,0)),0)+G33*IFERROR(INDEX(PriceBook!$H$4:$H$203,MATCH(G26,PriceBook!$A$4:$A$203,0)),0) -> 0.7425
A71: Price factor after batch share | C71: =1-C34*(1-IFERROR(INDEX(PriceBook!$I$4:$I$203,MATCH(C26,PriceBook!$A$4:$A$203,0)),0)) -> 1 | D71: =1-D34*(1-IFERROR(INDEX(PriceBook!$I$4:$I$203,MATCH(D26,PriceBook!$A$4:$A$203,0)),0)) -> 1 | E71: =1-E34*(1-IFERROR(INDEX(PriceBook!$I$4:$I$203,MATCH(E26,PriceBook!$A$4:$A$203,0)),0)) -> 1 | F71: =1-F34*(1-IFERROR(INDEX(PriceBook!$I$4:$I$203,MATCH(F26,PriceBook!$A$4:$A$203,0)),0)) -> 0.8 | G71: =1-G34*(1-IFERROR(INDEX(PriceBook!$I$4:$I$203,MATCH(G26,PriceBook!$A$4:$A$203,0)),0)) -> 1
A72: Outcomes per user, non-top segment | C72: =IF(C23="per user",C24/((1-C13)+C13*C14),0) -> 42.857143 | D72: =IF(D23="per user",D24/((1-D13)+D13*D14),0) -> 285.71429 | E72: =IF(E23="per user",E24/((1-E13)+E13*E14),0) -> 0 | F72: =IF(F23="per user",F24/((1-F13)+F13*F14),0) -> 85.714286 | G72: =IF(G23="per user",G24/((1-G13)+G13*G14),0) -> 42.857143
A73: Outcomes per user, top segment | C73: =C14*C72 -> 214.28571 | D73: =D14*D72 -> 1428.5714 | E73: =E14*E72 -> 0 | F73: =F14*F72 -> 428.57143 | G73: =G14*G72 -> 214.28571
A74: Tool and guardrail cost per outcome (USD) | C74: =C37*IFERROR(INDEX(PriceBook!$E$4:$E$203,MATCH(C38,PriceBook!$A$4:$A$203,0)),0)/1000+C39*IFERROR(INDEX(PriceBook!$E$4:$E$203,MATCH(C40,PriceBook!$A$4:$A$203,0)),0)/1000 -> 0 | D74: =D37*IFERROR(INDEX(PriceBook!$E$4:$E$203,MATCH(D38,PriceBook!$A$4:$A$203,0)),0)/1000+D39*IFERROR(INDEX(PriceBook!$E$4:$E$203,MATCH(D40,PriceBook!$A$4:$A$203,0)),0)/1000 -> 0 | E74: =E37*IFERROR(INDEX(PriceBook!$E$4:$E$203,MATCH(E38,PriceBook!$A$4:$A$203,0)),0)/1000+E39*IFERROR(INDEX(PriceBook!$E$4:$E$203,MATCH(E40,PriceBook!$A$4:$A$203,0)),0)/1000 -> 0 | F74: =F37*IFERROR(INDEX(PriceBook!$E$4:$E$203,MATCH(F38,PriceBook!$A$4:$A$203,0)),0)/1000+F39*IFERROR(INDEX(PriceBook!$E$4:$E$203,MATCH(F40,PriceBook!$A$4:$A$203,0)),0)/1000 -> 0.0189 | G74: =G37*IFERROR(INDEX(PriceBook!$E$4:$E$203,MATCH(G38,PriceBook!$A$4:$A$203,0)),0)/1000+G39*IFERROR(INDEX(PriceBook!$E$4:$E$203,MATCH(G40,PriceBook!$A$4:$A$203,0)),0)/1000 -> 0
A75: Parsing price (USD per page) | C75: =IFERROR(INDEX(PriceBook!$E$4:$E$203,MATCH(C46,PriceBook!$A$4:$A$203,0)),0) -> 0.0015 | D75: =IFERROR(INDEX(PriceBook!$E$4:$E$203,MATCH(D46,PriceBook!$A$4:$A$203,0)),0) -> 0.0015 | E75: =IFERROR(INDEX(PriceBook!$E$4:$E$203,MATCH(E46,PriceBook!$A$4:$A$203,0)),0) -> 0.0015 | F75: =IFERROR(INDEX(PriceBook!$E$4:$E$203,MATCH(F46,PriceBook!$A$4:$A$203,0)),0) -> 0.015 | G75: =IFERROR(INDEX(PriceBook!$E$4:$E$203,MATCH(G46,PriceBook!$A$4:$A$203,0)),0) -> 0.0015
A76: Embedding price (USD per million tokens) | C76: =IFERROR(INDEX(PriceBook!$E$4:$E$203,MATCH(C48,PriceBook!$A$4:$A$203,0)),0) -> 0.13 | D76: =IFERROR(INDEX(PriceBook!$E$4:$E$203,MATCH(D48,PriceBook!$A$4:$A$203,0)),0) -> 0.13 | E76: =IFERROR(INDEX(PriceBook!$E$4:$E$203,MATCH(E48,PriceBook!$A$4:$A$203,0)),0) -> 0.13 | F76: =IFERROR(INDEX(PriceBook!$E$4:$E$203,MATCH(F48,PriceBook!$A$4:$A$203,0)),0) -> 0.13 | G76: =IFERROR(INDEX(PriceBook!$E$4:$E$203,MATCH(G48,PriceBook!$A$4:$A$203,0)),0) -> 0.13
A77: Index plan minimum (USD per month) | C77: =IFERROR(INDEX(PriceBook!$E$4:$E$203,MATCH(C52,PriceBook!$A$4:$A$203,0)),0) -> 50 | D77: =IFERROR(INDEX(PriceBook!$E$4:$E$203,MATCH(D52,PriceBook!$A$4:$A$203,0)),0) -> 50 | E77: =IFERROR(INDEX(PriceBook!$E$4:$E$203,MATCH(E52,PriceBook!$A$4:$A$203,0)),0) -> 50 | F77: =IFERROR(INDEX(PriceBook!$E$4:$E$203,MATCH(F52,PriceBook!$A$4:$A$203,0)),0) -> 50 | G77: =IFERROR(INDEX(PriceBook!$E$4:$E$203,MATCH(G52,PriceBook!$A$4:$A$203,0)),0) -> 50
A78: Storage price (USD per GB per month) | C78: =IFERROR(INDEX(PriceBook!$E$4:$E$203,MATCH(C53,PriceBook!$A$4:$A$203,0)),0) -> 0.33 | D78: =IFERROR(INDEX(PriceBook!$E$4:$E$203,MATCH(D53,PriceBook!$A$4:$A$203,0)),0) -> 0.33 | E78: =IFERROR(INDEX(PriceBook!$E$4:$E$203,MATCH(E53,PriceBook!$A$4:$A$203,0)),0) -> 0.33 | F78: =IFERROR(INDEX(PriceBook!$E$4:$E$203,MATCH(F53,PriceBook!$A$4:$A$203,0)),0) -> 0.33 | G78: =IFERROR(INDEX(PriceBook!$E$4:$E$203,MATCH(G53,PriceBook!$A$4:$A$203,0)),0) -> 0.33
A79: Read price (USD per million read units) | C79: =IFERROR(INDEX(PriceBook!$E$4:$E$203,MATCH(C54,PriceBook!$A$4:$A$203,0)),0) -> 16 | D79: =IFERROR(INDEX(PriceBook!$E$4:$E$203,MATCH(D54,PriceBook!$A$4:$A$203,0)),0) -> 16 | E79: =IFERROR(INDEX(PriceBook!$E$4:$E$203,MATCH(E54,PriceBook!$A$4:$A$203,0)),0) -> 16 | F79: =IFERROR(INDEX(PriceBook!$E$4:$E$203,MATCH(F54,PriceBook!$A$4:$A$203,0)),0) -> 16 | G79: =IFERROR(INDEX(PriceBook!$E$4:$E$203,MATCH(G54,PriceBook!$A$4:$A$203,0)),0) -> 16
A80: Effective launch month (9999 when the team is not active) | C80: =IF(C5=1,C20,9999) -> 1 | D80: =IF(D5=1,D20,9999) -> 1 | E80: =IF(E5=1,E20,9999) -> 2 | F80: =IF(F5=1,F20,9999) -> 3 | G80: =IF(G5=1,G20,9999) -> 1
A81: Licensed users counted (0 when the team is not active) | C81: =C5*C18 -> 3000 | D81: =D5*D18 -> 400 | E81: =E5*E18 -> 60 | F81: =F5*F18 -> 150 | G81: =G5*G18 -> 2000
A83: Calibration note: Team 1 assumes 2 minutes saved per interaction, about 5.5 minutes per working day, far below published self-reported figures. Team 5 is the same kind of team calibrated to the low published figure (7 minutes per interaction, about 19 minutes per working day, grade C*). Both are shown on purpose.

Sheet Params
A1: Scenario parameters (starter values)
A2: Grade D unless stated. Low, Base and High are the low-cost, base and high-cost values. Source: spec/starter-values.md. Every value is editable.
A3: Key | B3: Parameter | C3: Unit | D3: Low-cost | E3: Base | F3: High-cost (stress) | G3: Taxonomy line | H3: How it was built | I3: Label | J3: Source | K3: Grade
A4: src_pd | B4: Assess one source system | C4: person-days | D4: 1 | E4: 3 | F4: 8 | G4: CL-01 | H4: Owner interview, access check, sample review | I4: assumed | J4: spec/starter-values.md (Claude, 2026-09-20) | K4: D
A5: clean_pd | B5: Clean and label 100,000 documents | C5: person-days | D5: 5 | E5: 20 | F5: 60 | G5: CL-02 | H5: Pipeline plus sampled review; range wide because published shares conflict (CST-07) | I5: assumed | J5: spec/starter-values.md (Claude, 2026-09-20) | K5: D
A6: conn_pd | B6: Build one connector | C6: person-days | D6: 5 | E6: 10 | F6: 25 | G6: CL-03 | H6: Standard vs custom source | I6: assumed | J6: spec/starter-values.md (Claude, 2026-09-20) | K6: D
A7: conn_up | B7: Connector upkeep per year | C7: share of build | D7: 0.1 | E7: 0.15 | F7: 0.25 | G7: CL-03 | H7: Yearly upkeep share | I7: assumed | J7: spec/starter-values.md (Claude, 2026-09-20) | K7: D
A8: perm_pd | B8: Map permissions for one source | C8: person-days | D8: 2 | E8: 4 | F8: 10 | G8: CL-04 | H8: Map groups once, revise on org change | I8: assumed | J8: spec/starter-values.md (Claude, 2026-09-20) | K8: D
A9: perm_up | B9: Permission upkeep per year | C9: share of build | D9: 0.05 | E9: 0.1 | F9: 0.2 | G9: CL-04 | H9: Org change rate | I9: assumed | J9: spec/starter-values.md (Claude, 2026-09-20) | K9: D
A10: change_rate | B10: Share of documents changing per month | C10: share | D10: 0.01 | E10: 0.03 | F10: 0.1 | G10: CL-08 | H10: Slow policy content vs fast tickets | I10: assumed | J10: spec/starter-values.md (Claude, 2026-09-20) | K10: D
A11: plat_pd | B11: Platform or gateway, one-time | C11: person-days | D11: 60 | E11: 120 | F11: 300 | G11: CL-09 | H11: Configure or build gateway with logging and access control; base x rate = $96,000 vs ENV-01 (B*, 2024) | I11: assumed | J11: spec/starter-values.md (Claude, 2026-09-20) | K11: D
A12: plat_run | B12: Platform run per year | C12: share of one-time | D12: 0.1 | E12: 0.2 | F12: 0.3 | G12: CL-09 | H12: Yearly run share | I12: assumed | J12: spec/starter-values.md (Claude, 2026-09-20) | K12: D
A13: int_pd | B13: Integrate one use case | C13: person-days | D13: 15 | E13: 40 | F13: 120 | G13: CL-10 | H13: Connect one workflow and its systems | I13: assumed | J13: spec/starter-values.md (Claude, 2026-09-20) | K13: D
A14: rev_uc_pd | B14: Security, privacy, legal review per use case | C14: person-days | D14: 5 | E14: 10 | F14: 30 | G14: CL-11 | H14: A few days each from three reviewers | I14: assumed | J14: spec/starter-values.md (Claude, 2026-09-20) | K14: D
A15: rev_once_pd | B15: Platform-level review, once | C15: person-days | D15: 15 | E15: 30 | F15: 60 | G15: CL-11 | H15: One-time platform review | I15: assumed | J15: spec/starter-values.md (Claude, 2026-09-20) | K15: D
... A41: realise | B41: Realisation share of self-reported time saved | C41: share | D41: 0.25 | E41: 0.5 | F41: 0.75 | G41: value | H41: No evidence converts self-reported time saved to cash (G5) | I41: assumed | J41: spec/starter-values.md (Claude, 2026-09-20) | K41: D

Sheet PriceBook
A1: Price book (dated primary prices, grade A)
A2: Fetched 2026-09-20 from each provider's own page (see evidence/source-register.md). 'Effective from' is the first date the price was seen. Confirm on the page before use. Model names are as extracted. Refresh: add a new row with a NEW unique ID, keep the old row, never overwrite (adoption/price-book-refresh.md). Dates and status are recorded, not applied in calculations.
A3: ID | B3: Provider | C3: Product | D3: Kind | E3: Price / input | F3: Output | G3: Cache read x | H3: Cache write x | I3: Batch factor | J3: Unit | K3: Effective from | L3: Effective to | M3: Status | N3: Source | O3: Date fetched | P3: Grade | Q3: Label | R3: Included units
A4: M_HAIKU45 | B4: Anthropic | C4: Claude Haiku 4.5 | D4: Model | E4: 1 | F4: 5 | G4: 0.1 | H4: 1.25 | I4: 0.5 | J4: USD per million tokens | K4: 46285 | M4: standard | N4: S09 | O4: 46285 | P4: A | Q4: quoted
A5: M_SONNET5 | B5: Anthropic | C5: Claude Sonnet 5 | D5: Model | E5: 2 | F5: 10 | G5: 0.1 | H5: 1.25 | I5: 0.5 | J5: USD per million tokens | K5: 46285 | M5: standard | N5: S09 | O5: 46285 | P5: A | Q5: quoted
A6: M_OPUS5 | B6: Anthropic | C6: Claude Opus 5 | D6: Model | E6: 5 | F6: 25 | G6: 0.1 | H6: 1.25 | I6: 0.5 | J6: USD per million tokens | K6: 46285 | M6: standard | N6: S09 | O6: 46285 | P6: A | Q6: quoted
A7: M_GPT54MINI | B7: OpenAI | C7: GPT-5.4 Mini (name as extracted) | D7: Model | E7: 0.75 | F7: 4.5 | G7: 0.1 | H7: 1 | I7: 0.5 | J7: USD per million tokens | K7: 46285 | M7: standard | N7: S12 | O7: 46285 | P7: A | Q7: quoted
A8: M_GEM38FLASH | B8: Google | C8: Gemini 3.8 Flash (name as extracted) | D8: Model | E8: 0.75 | F8: 3.75 | G8: 0.1 | H8: 1 | I8: 0.5 | J8: USD per million tokens | K8: 46285 | L8: 46387 | M8: promotional | N8: S11 | O8: 46285 | P8: A | Q8: quoted
A9: SEAT_TEAM_STD | B9: Anthropic | C9: Claude Team standard seat (annual billing) | D9: Seat | E9: 20 | J9: USD per user per month | K9: 46285 | M9: standard | N9: S33 | O9: 46285 | P9: A | Q9: quoted
A10: SEAT_TEAM_PREM | B10: Anthropic | C10: Claude Team premium seat (annual billing) | D10: Seat | E10: 100 | J10: USD per user per month | K10: 46285 | M10: standard | N10: S33 | O10: 46285 | P10: A | Q10: quoted
A11: SEAT_ENT | B11: Anthropic | C11: Claude Enterprise seat (annual); usage billed at API rates | D11: Seat | E11: 20 | J11: USD per user per month | K11: 46285 | M11: standard | N11: S33 | O11: 46285 | P11: A | Q11: quoted
A12: SEAT_M365_BUS | B12: Microsoft | C12: Microsoft 365 Copilot Business (annual, promotional) | D12: Seat | E12: 18 | J12: USD per user per month | K12: 46285 | L12: 46387 | M12: promotional | N12: S08 | O12: 46285 | P12: A | Q12: quoted
A13: SEAT_M365 | B13: Microsoft | C13: Microsoft 365 Copilot (paid yearly) | D13: Seat | E13: 30 | J13: USD per user per month | K13: 46285 | M13: standard | N13: S35 | O13: 46285 | P13: A | Q13: quoted
A14: OUT_FIN | B14: Intercom | C14: Fin AI agent, per outcome (outcome definition in BUY-06) | D14: Outcome | E14: 0.99 | J14: USD per outcome | K14: 46285 | M14: standard | N14: S37 | O14: 46285 | P14: A | Q14: quoted
A15: U_TEXTRACT_TXT | B15: AWS | C15: Textract detect text, first 1M pages | D15: Unit | E15: 0.0015 | J15: USD per page | K15: 46285 | M15: standard | N15: S45 | O15: 46285 | P15: A | Q15: quoted
A16: U_TEXTRACT_TBL | B16: AWS | C16: Textract tables, first 1M pages | D16: Unit | E16: 0.015 | J16: USD per page | K16: 46285 | M16: standard | N16: S45 | O16: 46285 | P16: A | Q16: quoted
A17: U_EMB_3L | B17: OpenAI | C17: text-embedding-3-large | D17: Unit | E17: 0.13 | J17: USD per million tokens | K17: 46285 | M17: standard | N17: S12 | O17: 46285 | P17: A | Q17: quoted
A18: U_PINE_READ | B18: Pinecone | C18: Read units (low end of range) | D18: Unit | E18: 16 | J18: USD per million read units | K18: 46285 | M18: standard | N18: S43 | O18: 46285 | P18: A | Q18: quoted
A19: U_PINE_STORE | B19: Pinecone | C19: Storage, Standard plan | D19: Unit | E19: 0.33 | J19: USD per GB per month | K19: 46285 | M19: standard | N19: S43 | O19: 46285 | P19: A | Q19: quoted
A20: PL_PINE_STD | B20: Pinecone | C20: Standard plan minimum | D20: Plan | E20: 50 | J20: USD per month | K20: 46285 | M20: standard | N20: S43 | O20: 46285 | P20: A | Q20: quoted
A21: U_GUARD_CF | B21: AWS | C21: Bedrock Guardrails content filters | D21: Unit | E21: 0.15 | J21: USD per 1,000 text units | K21: 46285 | M21: standard | N21: S46 | O21: 46285 | P21: A | Q21: quoted
A22: U_TOOL_SEARCH | B22: Anthropic/OpenAI | C22: Web search tool | D22: Unit | E22: 10 | J22: USD per 1,000 calls | K22: 46285 | M22: standard | N22: S09 | O22: 46285 | P22: A | Q22: quoted
A23: PL_LANGFUSE_PRO | B23: Langfuse | C23: Pro plan (100k units included) | D23: Plan | E23: 199 | J23: USD per month | K23: 46285 | M23: standard | N23: S44 | O23: 46285 | P23: A | Q23: quoted | R23: 100000
A24: U_LANGFUSE_OVER | B24: Langfuse | C24: Overage per 100k units | D24: Unit | E24: 8 | J24: USD per 100k units | K24: 46285 | M24: standard | N24: S44 | O24: 46285 | P24: A | Q24: quoted

Sheet Lines
A1: The 35 cost lines (taxonomy index)
A2: Source: research/cost-taxonomy.md. Policy: P dated primary price, R range with warning, E enterprise-entered (starter value unless off).
A3: ID | B3: Line | C3: Layer | D3: Type | E3: Owner (hub-and-spoke) | F3: Policy | G3: Evidence | H3: Status | I3: Where it is computed
A4: CL-01 | B4: Source inventory and assessment | C4: L1 | D4: One-time | E4: H+S | F4: E | G4: none (G1) | H4: ON | I4: Team: one-time assess, clean, connect
A5: CL-02 | B5: Cleaning, deduplication, labelling | C5: L1 | D5: One-time, then refresh | E5: S | F5: E | G5: CST-07 (C), CST-08 | H5: ON | I5: Team: one-time assess, clean, connect
A6: CL-03 | B6: Connectors to source systems | C6: L1 | D6: One-time plus upkeep | E6: H+S | F6: E | G6: none (G1) | H6: ON | I6: Team: one-time row and connector upkeep
A7: CL-04 | B7: Permission and access mapping | C7: L1 | D7: One-time, then on org change | E7: H | F7: E | G7: ORG-03 | H7: ON | I7: Hub: permission mapping and upkeep
A8: CL-05 | B8: Document parsing and OCR | C8: L1 | D8: Variable | E8: S | F8: P | G8: COMP-01 | H8: ON | I8: Team: parsing, embeddings, index row and initial load
A9: CL-06 | B9: Embeddings | C9: L1 | D9: Variable | E9: S | F9: P | G9: COMP-02 | H9: ON | I9: Team: parsing, embeddings, index row and initial load
A10: CL-07 | B10: Index and retrieval infrastructure | C10: L1 | D10: Recurring fixed plus variable | E10: H+S | F10: P | G10: COMP-03 | H10: ON | I10: Team: parsing, embeddings, index row
A11: CL-08 | B11: Refresh and sync | C11: L1 | D11: Recurring | E11: S | F11: E | G11: none | H11: ON | I11: Team: parsing, embeddings, index row (change rate)
A12: CL-09 | B12: Platform or gateway, build or buy | C12: L2 | D12: One-time plus recurring | E12: H | F12: E | G12: ENV-01 (B*) | H12: ON | I12: Hub: platform one-time and run
A13: CL-10 | B13: Workflow and application integration | C13: L2 | D13: One-time | E13: S | F13: E | G13: none (G11) | H13: ON | I13: Team: one-time integrate, evaluation harness
A14: CL-11 | B14: Security, privacy and legal review | C14: L2 | D14: One-time, and on material change | E14: H | F14: E | G14: none (G11) | H14: ON | I14: Hub: review one-time
... A16: CL-13 | B16: Red-teaming and adversarial testing | C16: L2 | D16: One-time, then periodic | E16: H | F16: E | G16: none (G11) | H16: ON | I16: Hub: red-team one-time and repeat
A17: CL-14 | B17: Environments and base cloud infrastructure | C17: L2 | D17: Recurring fixed | E17: H | F17: E | G17: none | H17: =IF(Params!$E$20=0,"OFF","ON") -> OFF | I17: Hub: environments
A18: CL-15 | B18: Committed capacity (provisioned cloud or self-hosted GPUs) | C18: L2 | D18: Recurring fixed | E18: H or S | F18: E | G18: BUY-05, CST-09 (C) | H18: =IF(SUM(Teams!$C$16:$G$16)=0,"OFF","ON") -> OFF | I18: Team: committed capacity row
A19: CL-16 | B19: Model tokens | C19: L3 | D19: Variable | E19: S | F19: P | G19: PRC-01 to PRC-04 | H19: ON | I19: Team: model tokens row
A20: CL-17 | B20: Retries, failed calls, agent steps | C20: L3 | D20: Variable | E20: S | F20: E | G20: none (G8) | H20: ON | I20: Multiplier inside the model tokens row
A21: CL-18 | B21: Tool and retrieval calls | C21: L3 | D21: Variable | E21: S | F21: P | G21: COMP-03, COMP-04 | H21: ON | I21: Team: tool and guardrail row
A22: CL-19 | B22: Guardrails and moderation | C22: L3 | D22: Variable | E22: H+S | F22: P | G22: COMP-05, COMP-02 | H22: ON | I22: Team: tool and guardrail row
A23: CL-20 | B23: Voice and image | C23: L3 | D23: Variable | E23: S | F23: P | G23: COMP-04 | H23: n/a (not used in this example) | I23: Not used in the worked example
A24: CL-21 | B24: Seats | C24: L3 | D24: Recurring fixed | E24: S | F24: P | G24: BUY-02, BUY-03 | H24: ON | I24: Team: seats row
A25: CL-22 | B25: Credits and outcomes | C25: L3 | D25: Variable | E25: S | F25: P | G25: BUY-04, BUY-06 | H25: ON | I25: Team: vendor per-outcome row
A26: CL-23 | B26: Residency and regional premium | C26: L3 | D26: Multiplier | E26: S | F26: P | G26: PRC-01, PRC-02, BUY-05 | H26: ON | I26: Residency multiplier inside the model tokens row
A27: CL-24 | B27: Monitoring and observability | C27: L4 | D27: Recurring fixed plus variable | E27: H | F27: P | G27: COMP-06 | H27: ON | I27: Hub: monitoring
A28: CL-25 | B28: Ongoing evaluation and quality review | C28: L4 | D28: Recurring | E28: H+S | F28: E | G28: none | H28: ON | I28: Team: quality review, maintenance, support row
A29: CL-26 | B29: Model migration events | C29: L4 | D29: Recurring event | E29: S | F29: R | G29: PRC-06 (cadence, one provider) | H29: ON | I29: Team: migration row
A30: CL-27 | B30: Prompt and workflow maintenance | C30: L4 | D30: Recurring | E30: S | F30: E | G30: none | H30: ON | I30: Team: quality review, maintenance, support row
... A33: CL-30 | B33: Cost governance (FinOps) | C33: L4 | D33: Recurring fixed | E33: H | F33: R | G33: ORG-07 (B) | H33: ON | I33: Hub: cost governance
A34: CL-31 | B34: Compliance audit and governance | C34: L4 | D34: Recurring | E34: H | F34: E | G34: none (G7) | H34: =IF(Params!$E$32=0,"OFF","ON") -> OFF | I34: Hub: compliance audit
A35: CL-32 | B35: Platform and vendor licences | C35: L4 | D35: Recurring fixed | E35: H | F35: E | G35: none | H35: =IF(Params!$E$33=0,"OFF","ON") -> OFF | I35: Hub: licences
A36: CL-33 | B36: Training and enablement | C36: L5 | D36: One-time, plus new joiners | E36: S | F36: E | G36: none | H36: ON | I36: Team: one-time training
A37: CL-34 | B37: Human review of output | C37: L5 | D37: Variable | E37: S | F37: R | G37: ORG-06 (B*), LAB-01 | H37: ON | I37: Team: human review row
A38: CL-35 | B38: Change management and champions | C38: L5 | D38: Recurring | E38: H+S | F38: E | G38: none | H38: ON | I38: Team: change champions row
A40: Tally by policy
A41: P | B41: =COUNTIF($F$4:$F$38,A41) -> 11
A42: R | B42: =COUNTIF($F$4:$F$38,A42) -> 3
A43: E | B43: =COUNTIF($F$4:$F$38,A43) -> 21
A44: Lines with no starter value are OFF and understate cost until the enterprise enters a value (CL-14, CL-15, CL-31, CL-32).

Sheet Levers
A1: Levers in their fixed order (Base scenario)
A2: Order: context and scenario scale, routing, caching, batch, residency. Below: two hand-calculated fixtures used by acceptance test 5.
A3: Step | B3: =Teams!$C$4 -> Corporate knowledge assistant (conservative calibration) | C3: =Teams!$D$4 -> Engineering assistant | D3: =Teams!$E$4 -> Customer service agent | E3: =Teams!$F$4 -> Regulated document review | F3: =Teams!$G$4 -> Sales assistant (published-range calibration)
A4: Input tokens per outcome (entered) | B4: =Teams!$C$29 -> 2000 | C4: =Teams!$D$29 -> 8000 | D4: =Teams!$E$29 -> 0 | E4: =Teams!$F$29 -> 30000 | F4: =Teams!$G$29 -> 2000
A5: Output tokens per outcome (entered) | B5: =Teams!$C$30 -> 500 | C5: =Teams!$D$30 -> 2000 | D5: =Teams!$E$30 -> 0 | E5: =Teams!$F$30 -> 1500 | F5: =Teams!$G$30 -> 500
A6: Scale: (1 - context) x scenario x retries x steps | B6: =(1-Teams!$C$31)*Params!$E$39*Params!$E$21*IF(Teams!$C$36="Yes",Params!$E$22,1) -> 1.15 | C6: =(1-Teams!$D$31)*Params!$E$39*Params!$E$21*IF(Teams!$D$36="Yes",Params!$E$22,1) -> 6.21 | D6: =(1-Teams!$E$31)*Params!$E$39*Params!$E$21*IF(Teams!$E$36="Yes",Params!$E$22,1) -> 1.15 | E6: =(1-Teams!$F$31)*Params!$E$39*Params!$E$21*IF(Teams!$F$36="Yes",Params!$E$22,1) -> 1.15 | F6: =(1-Teams!$G$31)*Params!$E$39*Params!$E$21*IF(Teams!$G$36="Yes",Params!$E$22,1) -> 1.15
A7: Input tokens after scale | B7: =B4*B6 -> 2300 | C7: =C4*C6 -> 49680 | D7: =D4*D6 -> 0 | E7: =E4*E6 -> 34500 | F7: =F4*F6 -> 2300
A8: Output tokens after scale | B8: =B5*B6 -> 575 | C8: =C5*C6 -> 12420 | D8: =D5*D6 -> 0 | E8: =E5*E6 -> 1725 | F8: =F5*F6 -> 575
A9: Blended input price after routing (USD per million) | B9: =Teams!$C$68 -> 2 | C9: =Teams!$D$68 -> 2 | D9: =Teams!$E$68 -> 2 | E9: =Teams!$F$68 -> 3.5 | F9: =Teams!$G$68 -> 2
A10: Blended output price after routing (USD per million) | B10: =Teams!$C$69 -> 10 | C10: =Teams!$D$69 -> 10 | D10: =Teams!$E$69 -> 10 | E10: =Teams!$F$69 -> 17.5 | F10: =Teams!$G$69 -> 10
A11: Input price factor after caching | B11: =Teams!$C$70 -> 0.7425 | C11: =Teams!$D$70 -> 0.4725 | D11: =Teams!$E$70 -> 1 | E11: =Teams!$F$70 -> 0.7425 | F11: =Teams!$G$70 -> 0.7425
A12: Price factor after batch share | B12: =Teams!$C$71 -> 1 | C12: =Teams!$D$71 -> 1 | D12: =Teams!$E$71 -> 1 | E12: =Teams!$F$71 -> 0.8 | F12: =Teams!$G$71 -> 1
A13: Residency multiplier | B13: =Teams!$C$35 -> 1 | C13: =Teams!$D$35 -> 1 | D13: =Teams!$E$35 -> 1 | E13: =Teams!$F$35 -> 1.1 | F13: =Teams!$G$35 -> 1
A14: Token cost per outcome (this sheet) | B14: =(B7*B9*B11+B8*B10)/1000000*B12*B13 -> 0.0091655 | C14: =(C7*C9*C11+C8*C10)/1000000*C12*C13 -> 0.1711476 | D14: =(D7*D9*D11+D8*D10)/1000000*D12*D13 -> 0 | E14: =(E7*E9*E11+E8*E10)/1000000*E12*E13 -> 0.10546305 | F14: =(F7*F9*F11+F8*F10)/1000000*F12*F13 -> 0.0091655
A15: Token cost per outcome (Calc_Base) | B15: =Calc_Base!$C$8 -> 0.0091655 | C15: =Calc_Base!$C$35 -> 0.1711476 | D15: =Calc_Base!$C$62 -> 0 | E15: =Calc_Base!$C$89 -> 0.10546305 | F15: =Calc_Base!$C$116 -> 0.0091655
A16: Difference | B16: =B14-B15 -> 0 | C16: =C14-C15 -> 0 | D16: =D14-D15 -> 0 | E16: =E14-E15 -> 0 | F16: =F14-F15 -> 0
A19: Fixtures (typed inputs; expected values hand-calculated, see build/build_out_c.py) | B19: Fixture 1 | C19: Fixture 2 | D19: Fixture 3 (provider example, no cache) | E19: Fixture 4 (provider example, 80% cached)
A20: Input tokens per outcome | B20: 10000 | C20: 20000 | D20: 50000 | E20: 50000
A21: Output tokens per outcome | B21: 1000 | C21: 2000 | D21: 15000 | E21: 15000
A22: Context-management reduction | B22: 0 | C22: 0.2 | D22: 0 | E22: 0
A23: Tokens scenario multiplier | B23: 1 | C23: 1 | D23: 1 | E23: 1
A24: Retry multiplier | B24: 1 | C24: 1.2 | D24: 1 | E24: 1
A25: Agent steps | B25: 1 | C25: 2 | D25: 1 | E25: 1
A26: Main model input price | B26: 2 | C26: 5 | D26: 5 | E26: 5
A27: Main model output price | B27: 10 | C27: 25 | D27: 25 | E27: 25
A28: Cheaper model input price | B28: 1 | C28: 1 | D28: 1 | E28: 1
A29: Cheaper model output price | B29: 5 | C29: 5 | D29: 5 | E29: 5
A30: Share routed to cheaper model | B30: 0 | C30: 0.5 | D30: 0 | E30: 0
A31: Cached share of input | B31: 0.5 | C31: 0.4 | D31: 0 | E31: 0.8
... A37: Residency multiplier | B37: 1 | C37: 1.1 | D37: 1 | E37: 1
A38: Computed cost per outcome | B38: =(B20*((1-B22)*B23*B24*B25)*((1-B30)*B26+B30*B28)*((1-B31-B32)+B31*B33+B32*B34)+B21*((1-B22)*B23*B24*B25)*((1-B30)*B27+B30*B29))/1000000*(1-B35*(1-B36))*B37 -> 0.021 | C38: =(C20*((1-C22)*C23*C24*C25)*((1-C30)*C26+C30*C28)*((1-C31-C32)+C31*C33+C32*C34)+C21*((1-C22)*C23*C24*C25)*((1-C30)*C27+C30*C29))/1000000*(1-C35*(1-C36))*C37 -> 0.12548448 | D38: =(D20*((1-D22)*D23*D24*D25)*((1-D30)*D26+D30*D28)*((1-D31-D32)+D31*D33+D32*D34)+D21*((1-D22)*D23*D24*D25)*((1-D30)*D27+D30*D29))/1000000*(1-D35*(1-D36))*D37 -> 0.625 | E38: =(E20*((1-E22)*E23*E24*E25)*((1-E30)*E26+E30*E28)*((1-E31-E32)+E31*E33+E32*E34)+E21*((1-E22)*E23*E24*E25)*((1-E30)*E27+E30*E29))/1000000*(1-E35*(1-E36))*E37 -> 0.445
A39: Expected (fixtures 1 and 2 hand-calculated; 3 and 4 from the provider's published example) | B39: 0.021 | C39: 0.12548448 | D39: 0.625 | E39: 0.445
A40: Difference | B40: =B38-B39 -> 0 | C40: =C38-C39 -> 0 | D40: =D38-D39 -> 0 | E40: =E38-E39 -> 0
A42: Fixtures 3 and 4 reproduce the worked example on Anthropic's pricing page (evidence S09, read 2026-09-20): Opus 5, 50,000 input and 15,000 output tokens. The page's totals, $0.705 without caching and $0.525 with 40,000 tokens read from cache, include $0.08 of session runtime, which is not a token cost.

Sheet Results
A1: Results for the selected scenario
A2: Every cell picks the Low-cost, Base or High-cost Calc sheet using the scenario chosen on Org.
A3: Shape factor on raw hub cost | D3: =CHOOSE(Org!$B$16,Calc_Low!$B$170,Calc_Base!$B$170,Calc_High!$B$170) -> 1
A4: Cost group | B4: Evidence | C4: Layer | D4: =Teams!C$4 -> Corporate knowledge assistant (conservative calibration) | E4: =Teams!D$4 -> Engineering assistant | F4: =Teams!E$4 -> Customer service agent | G4: =Teams!F$4 -> Regulated document review | H4: =Teams!G$4 -> Sales assistant (published-range calibration) | I4: Hub (raw) | J4: Enterprise
A5: Seats (CL-21) | B5: A | C5: 3 | D5: =CHOOSE(Org!$B$16,Calc_Low!$C$13,Calc_Base!$C$13,Calc_High!$C$13) -> 3024000 | E5: =CHOOSE(Org!$B$16,Calc_Low!$C$40,Calc_Base!$C$40,Calc_High!$C$40) -> 288000 | F5: =CHOOSE(Org!$B$16,Calc_Low!$C$67,Calc_Base!$C$67,Calc_High!$C$67) -> 0 | G5: =CHOOSE(Org!$B$16,Calc_Low!$C$94,Calc_Base!$C$94,Calc_High!$C$94) -> 0 | H5: =CHOOSE(Org!$B$16,Calc_Low!$C$121,Calc_Base!$C$121,Calc_High!$C$121) -> 2016000 | J5: =SUM(D5:H5) -> 5328000
A6: Model tokens incl. retries and agent steps (CL-16, CL-17) | B6: A | C6: 3 | D6: =CHOOSE(Org!$B$16,Calc_Low!$C$14,Calc_Base!$C$14,Calc_High!$C$14) -> 0 | E6: =CHOOSE(Org!$B$16,Calc_Low!$C$41,Calc_Base!$C$41,Calc_High!$C$41) -> 755787.8 | F6: =CHOOSE(Org!$B$16,Calc_Low!$C$68,Calc_Base!$C$68,Calc_High!$C$68) -> 0 | G6: =CHOOSE(Org!$B$16,Calc_Low!$C$95,Calc_Base!$C$95,Calc_High!$C$95) -> 42522.702 | H6: =CHOOSE(Org!$B$16,Calc_Low!$C$122,Calc_Base!$C$122,Calc_High!$C$122) -> 0 | J6: =SUM(D6:H6) -> 798310.5
A7: Vendor per-outcome price (CL-22) | B7: A | C7: 3 | D7: =CHOOSE(Org!$B$16,Calc_Low!$C$15,Calc_Base!$C$15,Calc_High!$C$15) -> 0 | E7: =CHOOSE(Org!$B$16,Calc_Low!$C$42,Calc_Base!$C$42,Calc_High!$C$42) -> 0 | F7: =CHOOSE(Org!$B$16,Calc_Low!$C$69,Calc_Base!$C$69,Calc_High!$C$69) -> 1287000 | G7: =CHOOSE(Org!$B$16,Calc_Low!$C$96,Calc_Base!$C$96,Calc_High!$C$96) -> 0 | H7: =CHOOSE(Org!$B$16,Calc_Low!$C$123,Calc_Base!$C$123,Calc_High!$C$123) -> 0 | J7: =SUM(D7:H7) -> 1287000
A8: Tool and guardrail calls (CL-18, CL-19) | B8: A | C8: 3 | D8: =CHOOSE(Org!$B$16,Calc_Low!$C$16,Calc_Base!$C$16,Calc_High!$C$16) -> 0 | E8: =CHOOSE(Org!$B$16,Calc_Low!$C$43,Calc_Base!$C$43,Calc_High!$C$43) -> 0 | F8: =CHOOSE(Org!$B$16,Calc_Low!$C$70,Calc_Base!$C$70,Calc_High!$C$70) -> 0 | G8: =CHOOSE(Org!$B$16,Calc_Low!$C$97,Calc_Base!$C$97,Calc_High!$C$97) -> 7620.48 | H8: =CHOOSE(Org!$B$16,Calc_Low!$C$124,Calc_Base!$C$124,Calc_High!$C$124) -> 0 | J8: =SUM(D8:H8) -> 7620.48
A9: Committed capacity (CL-15) | B9: E | C9: 2 | D9: =CHOOSE(Org!$B$16,Calc_Low!$C$17,Calc_Base!$C$17,Calc_High!$C$17) -> 0 | E9: =CHOOSE(Org!$B$16,Calc_Low!$C$44,Calc_Base!$C$44,Calc_High!$C$44) -> 0 | F9: =CHOOSE(Org!$B$16,Calc_Low!$C$71,Calc_Base!$C$71,Calc_High!$C$71) -> 0 | G9: =CHOOSE(Org!$B$16,Calc_Low!$C$98,Calc_Base!$C$98,Calc_High!$C$98) -> 0 | H9: =CHOOSE(Org!$B$16,Calc_Low!$C$125,Calc_Base!$C$125,Calc_High!$C$125) -> 0 | J9: =SUM(D9:H9) -> 0
A10: Parsing, embeddings, index, retrieval (CL-05 to CL-08) | B10: A | C10: 1 | D10: =CHOOSE(Org!$B$16,Calc_Low!$C$18,Calc_Base!$C$18,Calc_High!$C$18) -> 2323.8 | E10: =CHOOSE(Org!$B$16,Calc_Low!$C$45,Calc_Base!$C$45,Calc_High!$C$45) -> 2899.56 | F10: =CHOOSE(Org!$B$16,Calc_Low!$C$72,Calc_Base!$C$72,Calc_High!$C$72) -> 0 | G10: =CHOOSE(Org!$B$16,Calc_Low!$C$99,Calc_Base!$C$99,Calc_High!$C$99) -> 29769.632 | H10: =CHOOSE(Org!$B$16,Calc_Low!$C$126,Calc_Base!$C$126,Calc_High!$C$126) -> 2081.196 | J10: =SUM(D10:H10) -> 37074.188
A11: Connector upkeep (CL-03) | B11: S | C11: 1 | D11: =CHOOSE(Org!$B$16,Calc_Low!$C$19,Calc_Base!$C$19,Calc_High!$C$19) -> 10800 | E11: =CHOOSE(Org!$B$16,Calc_Low!$C$46,Calc_Base!$C$46,Calc_High!$C$46) -> 7200 | F11: =CHOOSE(Org!$B$16,Calc_Low!$C$73,Calc_Base!$C$73,Calc_High!$C$73) -> 10500 | G11: =CHOOSE(Org!$B$16,Calc_Low!$C$100,Calc_Base!$C$100,Calc_High!$C$100) -> 13600 | H11: =CHOOSE(Org!$B$16,Calc_Low!$C$127,Calc_Base!$C$127,Calc_High!$C$127) -> 7200 | J11: =SUM(D11:H11) -> 49300
A12: Quality review, maintenance, support (CL-25, CL-27, CL-28) | B12: S | C12: 4 | D12: =CHOOSE(Org!$B$16,Calc_Low!$C$20,Calc_Base!$C$20,Calc_High!$C$20) -> 250200 | E12: =CHOOSE(Org!$B$16,Calc_Low!$C$47,Calc_Base!$C$47,Calc_High!$C$47) -> 151680 | F12: =CHOOSE(Org!$B$16,Calc_Low!$C$74,Calc_Base!$C$74,Calc_High!$C$74) -> 129315 | G12: =CHOOSE(Org!$B$16,Calc_Low!$C$101,Calc_Base!$C$101,Calc_High!$C$101) -> 129120 | H12: =CHOOSE(Org!$B$16,Calc_Low!$C$128,Calc_Base!$C$128,Calc_High!$C$128) -> 210000 | J12: =SUM(D12:H12) -> 870315
A13: Model migration events (CL-26) | B13: R | C13: 4 | D13: =CHOOSE(Org!$B$16,Calc_Low!$C$21,Calc_Base!$C$21,Calc_High!$C$21) -> 12800 | E13: =CHOOSE(Org!$B$16,Calc_Low!$C$48,Calc_Base!$C$48,Calc_High!$C$48) -> 12800 | F13: =CHOOSE(Org!$B$16,Calc_Low!$C$75,Calc_Base!$C$75,Calc_High!$C$75) -> 12800 | G13: =CHOOSE(Org!$B$16,Calc_Low!$C$102,Calc_Base!$C$102,Calc_High!$C$102) -> 12800 | H13: =CHOOSE(Org!$B$16,Calc_Low!$C$129,Calc_Base!$C$129,Calc_High!$C$129) -> 12800 | J13: =SUM(D13:H13) -> 64000
A14: Human review of output (CL-34) | B14: R | C14: 5 | D14: =CHOOSE(Org!$B$16,Calc_Low!$C$22,Calc_Base!$C$22,Calc_High!$C$22) -> 424120.05 | E14: =CHOOSE(Org!$B$16,Calc_Low!$C$49,Calc_Base!$C$49,Calc_High!$C$49) -> 2070662.4 | F14: =CHOOSE(Org!$B$16,Calc_Low!$C$76,Calc_Base!$C$76,Calc_High!$C$76) -> 304785 | G14: =CHOOSE(Org!$B$16,Calc_Low!$C$103,Calc_Base!$C$103,Calc_High!$C$103) -> 945302.4 | H14: =CHOOSE(Org!$B$16,Calc_Low!$C$130,Calc_Base!$C$130,Calc_High!$C$130) -> 282746.7 | J14: =SUM(D14:H14) -> 4027616.5
A15: Change champions (CL-35) | B15: S | C15: 5 | D15: =CHOOSE(Org!$B$16,Calc_Low!$C$23,Calc_Base!$C$23,Calc_High!$C$23) -> 264000 | E15: =CHOOSE(Org!$B$16,Calc_Low!$C$50,Calc_Base!$C$50,Calc_High!$C$50) -> 35200 | F15: =CHOOSE(Org!$B$16,Calc_Low!$C$77,Calc_Base!$C$77,Calc_High!$C$77) -> 5192 | G15: =CHOOSE(Org!$B$16,Calc_Low!$C$104,Calc_Base!$C$104,Calc_High!$C$104) -> 12760 | H15: =CHOOSE(Org!$B$16,Calc_Low!$C$131,Calc_Base!$C$131,Calc_High!$C$131) -> 176000 | J15: =SUM(D15:H15) -> 493152
A16: One-time: assess, clean, connect (CL-01 to CL-03) | B16: S | C16: 1 | D16: =CHOOSE(Org!$B$16,Calc_Low!$C$24,Calc_Base!$C$24,Calc_High!$C$24) -> 34400 | E16: =CHOOSE(Org!$B$16,Calc_Low!$C$51,Calc_Base!$C$51,Calc_High!$C$51) -> 28800 | F16: =CHOOSE(Org!$B$16,Calc_Low!$C$78,Calc_Base!$C$78,Calc_High!$C$78) -> 32480 | G16: =CHOOSE(Org!$B$16,Calc_Low!$C$105,Calc_Base!$C$105,Calc_High!$C$105) -> 73600 | H16: =CHOOSE(Org!$B$16,Calc_Low!$C$132,Calc_Base!$C$132,Calc_High!$C$132) -> 22400 | J16: =SUM(D16:H16) -> 191680
A17: One-time: initial parse and embed (CL-05, CL-06) | B17: A | C17: 1 | D17: =CHOOSE(Org!$B$16,Calc_Low!$C$25,Calc_Base!$C$25,Calc_High!$C$25) -> 157.8 | E17: =CHOOSE(Org!$B$16,Calc_Low!$C$52,Calc_Base!$C$52,Calc_High!$C$52) -> 251 | F17: =CHOOSE(Org!$B$16,Calc_Low!$C$79,Calc_Base!$C$79,Calc_High!$C$79) -> 0 | G17: =CHOOSE(Org!$B$16,Calc_Low!$C$106,Calc_Base!$C$106,Calc_High!$C$106) -> 24156 | H17: =CHOOSE(Org!$B$16,Calc_Low!$C$133,Calc_Base!$C$133,Calc_High!$C$133) -> 78.9 | J17: =SUM(D17:H17) -> 24643.7
A18: One-time: integrate, evaluation harness (CL-10, CL-12) | B18: S | C18: 2 | D18: =CHOOSE(Org!$B$16,Calc_Low!$C$26,Calc_Base!$C$26,Calc_High!$C$26) -> 48000 | E18: =CHOOSE(Org!$B$16,Calc_Low!$C$53,Calc_Base!$C$53,Calc_High!$C$53) -> 48000 | F18: =CHOOSE(Org!$B$16,Calc_Low!$C$80,Calc_Base!$C$80,Calc_High!$C$80) -> 48000 | G18: =CHOOSE(Org!$B$16,Calc_Low!$C$107,Calc_Base!$C$107,Calc_High!$C$107) -> 48000 | H18: =CHOOSE(Org!$B$16,Calc_Low!$C$134,Calc_Base!$C$134,Calc_High!$C$134) -> 48000 | J18: =SUM(D18:H18) -> 240000
A19: One-time: training (CL-33) | B19: S | C19: 5 | D19: =CHOOSE(Org!$B$16,Calc_Low!$C$27,Calc_Base!$C$27,Calc_High!$C$27) -> 720000 | E19: =CHOOSE(Org!$B$16,Calc_Low!$C$54,Calc_Base!$C$54,Calc_High!$C$54) -> 128000 | F19: =CHOOSE(Org!$B$16,Calc_Low!$C$81,Calc_Base!$C$81,Calc_High!$C$81) -> 20400 | G19: =CHOOSE(Org!$B$16,Calc_Low!$C$108,Calc_Base!$C$108,Calc_High!$C$108) -> 42000 | H19: =CHOOSE(Org!$B$16,Calc_Low!$C$135,Calc_Base!$C$135,Calc_High!$C$135) -> 480000 | J19: =SUM(D19:H19) -> 1390400
A20: Hub: One-time: platform or gateway (CL-09) | B20: S | C20: 2 | I20: =CHOOSE(Org!$B$16,Calc_Low!$C$145,Calc_Base!$C$145,Calc_High!$C$145) -> 96000 | J20: =I20*$D$3 -> 96000
A21: Hub: One-time: permission mapping (CL-04) | B21: S | C21: 1 | I21: =CHOOSE(Org!$B$16,Calc_Low!$C$146,Calc_Base!$C$146,Calc_High!$C$146) -> 44800 | J21: =I21*$D$3 -> 44800
A22: Hub: One-time: security, privacy, legal review (CL-11) | B22: S | C22: 2 | I22: =CHOOSE(Org!$B$16,Calc_Low!$C$147,Calc_Base!$C$147,Calc_High!$C$147) -> 64000 | J22: =I22*$D$3 -> 64000
A23: Hub: One-time: red-teaming (CL-13) | B23: S | C23: 2 | I23: =CHOOSE(Org!$B$16,Calc_Low!$C$148,Calc_Base!$C$148,Calc_High!$C$148) -> 32000 | J23: =I23*$D$3 -> 32000
A24: Hub: Platform run (CL-09) | B24: S | C24: 2 | I24: =CHOOSE(Org!$B$16,Calc_Low!$C$149,Calc_Base!$C$149,Calc_High!$C$149) -> 57600 | J24: =I24*$D$3 -> 57600
A25: Hub: Permission upkeep (CL-04) | B25: S | C25: 1 | I25: =CHOOSE(Org!$B$16,Calc_Low!$C$150,Calc_Base!$C$150,Calc_High!$C$150) -> 13440 | J25: =I25*$D$3 -> 13440
A26: Hub: Red-team repeat (CL-13) | B26: S | C26: 2 | I26: =CHOOSE(Org!$B$16,Calc_Low!$C$151,Calc_Base!$C$151,Calc_High!$C$151) -> 48000 | J26: =I26*$D$3 -> 48000
A27: Hub: Environments (CL-14) | B27: E | C27: 2 | I27: =CHOOSE(Org!$B$16,Calc_Low!$C$152,Calc_Base!$C$152,Calc_High!$C$152) -> 0 | J27: =I27*$D$3 -> 0
A28: Hub: Monitoring and observability (CL-24) | B28: A | C28: 4 | I28: =CHOOSE(Org!$B$16,Calc_Low!$C$153,Calc_Base!$C$153,Calc_High!$C$153) -> 11735.68 | J28: =I28*$D$3 -> 11735.68
A29: Hub: Platform team (CL-29) | B29: S | C29: 4 | I29: =CHOOSE(Org!$B$16,Calc_Low!$C$154,Calc_Base!$C$154,Calc_High!$C$154) -> 2640000 | J29: =I29*$D$3 -> 2640000
A30: Hub: Cost governance (CL-30) | B30: R | C30: 4 | I30: =CHOOSE(Org!$B$16,Calc_Low!$C$155,Calc_Base!$C$155,Calc_High!$C$155) -> 528000 | J30: =I30*$D$3 -> 528000
A31: Hub: Compliance audit (CL-31) | B31: E | C31: 4 | I31: =CHOOSE(Org!$B$16,Calc_Low!$C$156,Calc_Base!$C$156,Calc_High!$C$156) -> 0 | J31: =I31*$D$3 -> 0
A32: Hub: Platform and vendor licences (CL-32) | B32: E | C32: 4 | I32: =CHOOSE(Org!$B$16,Calc_Low!$C$157,Calc_Base!$C$157,Calc_High!$C$157) -> 0 | J32: =I32*$D$3 -> 0
A33: Total cost over the horizon | D33: =SUM(D5:D32) -> 4790801.6 | E33: =SUM(E5:E32) -> 3529280.8 | F33: =SUM(F5:F32) -> 1850472 | G33: =SUM(G5:G32) -> 1381251.2 | H33: =SUM(H5:H32) -> 3257306.8 | I33: =SUM(I5:I32) -> 3535575.7 | J33: =SUM(J5:J32) -> 18344688
A35: By layer
A36: L1 Data readiness | D36: =SUMIF($C$5:$C$32,1,D$5:D$32) -> 47681.6 | E36: =SUMIF($C$5:$C$32,1,E$5:E$32) -> 39150.56 | F36: =SUMIF($C$5:$C$32,1,F$5:F$32) -> 42980 | G36: =SUMIF($C$5:$C$32,1,G$5:G$32) -> 141125.63 | H36: =SUMIF($C$5:$C$32,1,H$5:H$32) -> 31760.096 | I36: =SUMIF($C$5:$C$32,1,I$5:I$32) -> 58240 | J36: =SUMIF($C$5:$C$32,1,J$5:J$32) -> 360937.89
A37: L2 Setup and infrastructure | D37: =SUMIF($C$5:$C$32,2,D$5:D$32) -> 48000 | E37: =SUMIF($C$5:$C$32,2,E$5:E$32) -> 48000 | F37: =SUMIF($C$5:$C$32,2,F$5:F$32) -> 48000 | G37: =SUMIF($C$5:$C$32,2,G$5:G$32) -> 48000 | H37: =SUMIF($C$5:$C$32,2,H$5:H$32) -> 48000 | I37: =SUMIF($C$5:$C$32,2,I$5:I$32) -> 297600 | J37: =SUMIF($C$5:$C$32,2,J$5:J$32) -> 537600
A38: L3 Inference and usage | D38: =SUMIF($C$5:$C$32,3,D$5:D$32) -> 3024000 | E38: =SUMIF($C$5:$C$32,3,E$5:E$32) -> 1043787.8 | F38: =SUMIF($C$5:$C$32,3,F$5:F$32) -> 1287000 | G38: =SUMIF($C$5:$C$32,3,G$5:G$32) -> 50143.182 | H38: =SUMIF($C$5:$C$32,3,H$5:H$32) -> 2016000 | I38: =SUMIF($C$5:$C$32,3,I$5:I$32) -> 0 | J38: =SUMIF($C$5:$C$32,3,J$5:J$32) -> 7420931
A39: L4 Run and maintenance | D39: =SUMIF($C$5:$C$32,4,D$5:D$32) -> 263000 | E39: =SUMIF($C$5:$C$32,4,E$5:E$32) -> 164480 | F39: =SUMIF($C$5:$C$32,4,F$5:F$32) -> 142115 | G39: =SUMIF($C$5:$C$32,4,G$5:G$32) -> 141920 | H39: =SUMIF($C$5:$C$32,4,H$5:H$32) -> 222800 | I39: =SUMIF($C$5:$C$32,4,I$5:I$32) -> 3179735.7 | J39: =SUMIF($C$5:$C$32,4,J$5:J$32) -> 4114050.7
A40: L5 People and change | D40: =SUMIF($C$5:$C$32,5,D$5:D$32) -> 1408120 | E40: =SUMIF($C$5:$C$32,5,E$5:E$32) -> 2233862.4 | F40: =SUMIF($C$5:$C$32,5,F$5:F$32) -> 330377 | G40: =SUMIF($C$5:$C$32,5,G$5:G$32) -> 1000062.4 | H40: =SUMIF($C$5:$C$32,5,H$5:H$32) -> 938746.7 | I40: =SUMIF($C$5:$C$32,5,I$5:I$32) -> 0 | J40: =SUMIF($C$5:$C$32,5,J$5:J$32) -> 5911168.5
A42: By evidence category | D42: Cost | E42: Share
A43: Dated primary prices (A) | B43: A | D43: =SUMIF($B$5:$B$32,B43,$J$5:$J$32) -> 7494384.6 | E43: =IF($J$33=0,0,D43/$J$33) -> 0.40853159
A44: Ranges with a warning (B*/C) | B44: R | D44: =SUMIF($B$5:$B$32,B44,$J$5:$J$32) -> 4619616.5 | E44: =IF($J$33=0,0,D44/$J$33) -> 0.25182312
A45: Starter values (D) | B45: S | D45: =SUMIF($B$5:$B$32,B45,$J$5:$J$32) -> 6230687 | E45: =IF($J$33=0,0,D45/$J$33) -> 0.33964529
A46: Enterprise-entered, off until entered | B46: E | D46: =SUMIF($B$5:$B$32,B46,$J$5:$J$32) -> 0 | E46: =IF($J$33=0,0,D46/$J$33) -> 0
A47: Sum of shares | E47: =SUM(E43:E46) -> 1
A49: Team and enterprise metrics
A50: Buying model | D50: =Teams!$C$8 -> Seat | E50: =Teams!$D$8 -> Seat + usage | F50: =Teams!$E$8 -> Per-unit | G50: =Teams!$F$8 -> Per-unit | H50: =Teams!$G$8 -> Seat
A51: Licensed users (active teams) | D51: =Teams!$C$81 -> 3000 | E51: =Teams!$D$81 -> 400 | F51: =Teams!$E$81 -> 60 | G51: =Teams!$F$81 -> 150 | H51: =Teams!$G$81 -> 2000 | J51: =SUM(D51:H51) -> 5610
A52: Outcomes over the horizon | D52: =CHOOSE(Org!$B$16,Calc_Low!$C$12,Calc_Base!$C$12,Calc_High!$C$12) -> 3618000 | E52: =CHOOSE(Org!$B$16,Calc_Low!$C$39,Calc_Base!$C$39,Calc_High!$C$39) -> 4416000 | F52: =CHOOSE(Org!$B$16,Calc_Low!$C$66,Calc_Base!$C$66,Calc_High!$C$66) -> 1300000 | G52: =CHOOSE(Org!$B$16,Calc_Low!$C$93,Calc_Base!$C$93,Calc_High!$C$93) -> 403200 | H52: =CHOOSE(Org!$B$16,Calc_Low!$C$120,Calc_Base!$C$120,Calc_High!$C$120) -> 2412000 | J52: =SUM(D52:H52) -> 12149200
A53: Active user-months | D53: =CHOOSE(Org!$B$16,Calc_Low!$C$11,Calc_Base!$C$11,Calc_High!$C$11) -> 60300 | E53: =CHOOSE(Org!$B$16,Calc_Low!$C$38,Calc_Base!$C$38,Calc_High!$C$38) -> 11040 | F53: =CHOOSE(Org!$B$16,Calc_Low!$C$65,Calc_Base!$C$65,Calc_High!$C$65) -> 1657.5 | G53: =CHOOSE(Org!$B$16,Calc_Low!$C$92,Calc_Base!$C$92,Calc_High!$C$92) -> 3360 | H53: =CHOOSE(Org!$B$16,Calc_Low!$C$119,Calc_Base!$C$119,Calc_High!$C$119) -> 40200 | J53: =SUM(D53:H53) -> 116557.5
A54: Benefit | D54: =CHOOSE(Org!$B$16,Calc_Low!$C$28,Calc_Base!$C$28,Calc_High!$C$28) -> 2544720.3 | E54: =CHOOSE(Org!$B$16,Calc_Low!$C$55,Calc_Base!$C$55,Calc_High!$C$55) -> 13763200 | F54: =CHOOSE(Org!$B$16,Calc_Low!$C$82,Calc_Base!$C$82,Calc_High!$C$82) -> 2590672.5 | G54: =CHOOSE(Org!$B$16,Calc_Low!$C$109,Calc_Base!$C$109,Calc_High!$C$109) -> 1197383 | H54: =CHOOSE(Org!$B$16,Calc_Low!$C$136,Calc_Base!$C$136,Calc_High!$C$136) -> 5937680.7 | J54: =SUM(D54:H54) -> 26033657
A55: Direct cost | D55: =D33 -> 4790801.6 | E55: =E33 -> 3529280.8 | F55: =F33 -> 1850472 | G55: =G33 -> 1381251.2 | H55: =H33 -> 3257306.8
A56: Allocated hub cost | D56: =CHOOSE(Org!$B$16,Calc_Low!$B$167,Calc_Base!$B$167,Calc_High!$B$167) -> 1052885.2 | E56: =CHOOSE(Org!$B$16,Calc_Low!$C$167,Calc_Base!$C$167,Calc_High!$C$167) -> 1285113.6 | F56: =CHOOSE(Org!$B$16,Calc_Low!$D$167,Calc_Base!$D$167,Calc_High!$D$167) -> 378316.96 | G56: =CHOOSE(Org!$B$16,Calc_Low!$E$167,Calc_Base!$E$167,Calc_High!$E$167) -> 117336.46 | H56: =CHOOSE(Org!$B$16,Calc_Low!$F$167,Calc_Base!$F$167,Calc_High!$F$167) -> 701923.46 | J56: =CHOOSE(Org!$B$16,Calc_Low!$H$167,Calc_Base!$H$167,Calc_High!$H$167) -> 3535575.7
A57: Total cost including allocation | D57: =D55+D56 -> 5843686.8 | E57: =E55+E56 -> 4814394.4 | F57: =F55+F56 -> 2228789 | G57: =G55+G56 -> 1498587.7 | H57: =H55+H56 -> 3959230.3 | J57: =J33 -> 18344688
A58: Net value (benefit minus cost) | D58: =D54-D57 -> -3298966.5 | E58: =E54-E57 -> 8948805.6 | F58: =F54-F57 -> 361883.54 | G58: =G54-G57 -> -301204.63 | H58: =H54-H57 -> 1978450.4 | J58: =J54-J57 -> 7688968.4
A59: Payback month | D59: =IF(Teams!$C$5=0,"n/a",CHOOSE(Org!$B$16,Calc_Low!$C$33,Calc_Base!$C$33,Calc_High!$C$33)) -> None | E59: =IF(Teams!$D$5=0,"n/a",CHOOSE(Org!$B$16,Calc_Low!$C$60,Calc_Base!$C$60,Calc_High!$C$60)) -> 3 | F59: =IF(Teams!$E$5=0,"n/a",CHOOSE(Org!$B$16,Calc_Low!$C$87,Calc_Base!$C$87,Calc_High!$C$87)) -> 14 | G59: =IF(Teams!$F$5=0,"n/a",CHOOSE(Org!$B$16,Calc_Low!$C$114,Calc_Base!$C$114,Calc_High!$C$114)) -> None | H59: =IF(Teams!$G$5=0,"n/a",CHOOSE(Org!$B$16,Calc_Low!$C$141,Calc_Base!$C$141,Calc_High!$C$141)) -> 13 | J59: =CHOOSE(Org!$B$16,Calc_Low!$C$179,Calc_Base!$C$179,Calc_High!$C$179) -> 12
A60: Cost per outcome | D60: =IF(D52=0,0,D57/D52) -> 1.6151705 | E60: =IF(E52=0,0,E57/E52) -> 1.0902161 | F60: =IF(F52=0,0,F57/F52) -> 1.714453 | G60: =IF(G52=0,0,G57/G52) -> 3.7167353 | H60: =IF(H52=0,0,H57/H52) -> 1.6414719 | J60: =IF(J52=0,0,J57/J52) -> 1.5099503
A61: Cost per active user per month (teams with per-user outcomes; n/a for direct-volume teams) | D61: =IF(Teams!$C$23="direct volume","n/a",IF(D53=0,0,D57/D53)) -> 96.91023 | E61: =IF(Teams!$D$23="direct volume","n/a",IF(E53=0,0,E57/E53)) -> 436.08645 | F61: =IF(Teams!$E$23="direct volume","n/a",IF(F53=0,0,F57/F53)) -> n/a | G61: =IF(Teams!$F$23="direct volume","n/a",IF(G53=0,0,G57/G53)) -> 446.00824 | H61: =IF(Teams!$G$23="direct volume","n/a",IF(H53=0,0,H57/H53)) -> 98.488315 | J61: =IF(SUMPRODUCT((Teams!$C$23:$G$23="per user")*D53:H53)=0,0,SUMPRODUCT((Teams!$C$23:$G$23="per user")*D57:H57)/SUMPRODUCT((Teams!$C$23:$G$23="per user")*D53:H53)) -> 140.26022
A62: Benefit per outcome | D62: =IF(D52=0,0,D54/D52) -> 0.70335 | E62: =IF(E52=0,0,E54/E52) -> 3.1166667 | F62: =IF(F52=0,0,F54/F52) -> 1.992825 | G62: =IF(G52=0,0,G54/G52) -> 2.9697 | H62: =IF(H52=0,0,H54/H52) -> 2.461725 | J62: =IF(J52=0,0,J54/J52) -> 2.1428289
A63: Run-rate at the last horizon month (team direct + hub) | J63: =CHOOSE(Org!$B$16,Calc_Low!$C$180,Calc_Base!$C$180,Calc_High!$C$180) -> 458413.6
A64: Unallocated hub cost (central budget) | J64: =CHOOSE(Org!$B$16,Calc_Low!$G$167,Calc_Base!$G$167,Calc_High!$G$167) -> 0

Sheet Scenarios
A1: Scenarios side by side
A2: Low-cost, Base and High-cost, each from its own Calc sheet. Value case follows the Org selection.
A3: Enterprise, over the horizon | B3: Low-cost | C3: Base | D3: High-cost (stress case) | E3: Low <= Base <= High
A4: L1 Data readiness | B4: =Calc_Low!$C$18+Calc_Low!$C$19+Calc_Low!$C$24+Calc_Low!$C$25+Calc_Low!$C$45+Calc_Low!$C$46+Calc_Low!$C$51+Calc_Low!$C$52+Calc_Low!$C$72+Calc_Low!$C$73+Calc_Low!$C$78+Calc_Low!$C$79+Calc_Low!$C$99+Calc_Low!$C$100+Calc_Low!$C$105+Calc_Low!$C$106+Calc_Low!$C$126+Calc_Low!$C$127+Calc_Low!$C$132+Calc_Low!$C$133+Calc_Low!$B$170*(Calc_Low!$C$146+Calc_Low!$C$150) -> 165854 | C4: =Calc_Base!$C$18+Calc_Base!$C$19+Calc_Base!$C$24+Calc_Base!$C$25+Calc_Base!$C$45+Calc_Base!$C$46+Calc_Base!$C$51+Calc_Base!$C$52+Calc_Base!$C$72+Calc_Base!$C$73+Calc_Base!$C$78+Calc_Base!$C$79+Calc_Base!$C$99+Calc_Base!$C$100+Calc_Base!$C$105+Calc_Base!$C$106+Calc_Base!$C$126+Calc_Base!$C$127+Calc_Base!$C$132+Calc_Base!$C$133+Calc_Base!$B$170*(Calc_Base!$C$146+Calc_Base!$C$150) -> 360937.89 | D4: =Calc_High!$C$18+Calc_High!$C$19+Calc_High!$C$24+Calc_High!$C$25+Calc_High!$C$45+Calc_High!$C$46+Calc_High!$C$51+Calc_High!$C$52+Calc_High!$C$72+Calc_High!$C$73+Calc_High!$C$78+Calc_High!$C$79+Calc_High!$C$99+Calc_High!$C$100+Calc_High!$C$105+Calc_High!$C$106+Calc_High!$C$126+Calc_High!$C$127+Calc_High!$C$132+Calc_High!$C$133+Calc_High!$B$170*(Calc_High!$C$146+Calc_High!$C$150) -> 1012894.8 | E4: =IF(AND(B4<=C4,C4<=D4),"OK","CHECK") -> OK
A5: L2 Setup and infrastructure | B5: =Calc_Low!$C$17+Calc_Low!$C$26+Calc_Low!$C$44+Calc_Low!$C$53+Calc_Low!$C$71+Calc_Low!$C$80+Calc_Low!$C$98+Calc_Low!$C$107+Calc_Low!$C$125+Calc_Low!$C$134+Calc_Low!$B$170*(Calc_Low!$C$145+Calc_Low!$C$147+Calc_Low!$C$148+Calc_Low!$C$149+Calc_Low!$C$151+Calc_Low!$C$152) -> 207400 | C5: =Calc_Base!$C$17+Calc_Base!$C$26+Calc_Base!$C$44+Calc_Base!$C$53+Calc_Base!$C$71+Calc_Base!$C$80+Calc_Base!$C$98+Calc_Base!$C$107+Calc_Base!$C$125+Calc_Base!$C$134+Calc_Base!$B$170*(Calc_Base!$C$145+Calc_Base!$C$147+Calc_Base!$C$148+Calc_Base!$C$149+Calc_Base!$C$151+Calc_Base!$C$152) -> 537600 | D5: =Calc_High!$C$17+Calc_High!$C$26+Calc_High!$C$44+Calc_High!$C$53+Calc_High!$C$71+Calc_High!$C$80+Calc_High!$C$98+Calc_High!$C$107+Calc_High!$C$125+Calc_High!$C$134+Calc_High!$B$170*(Calc_High!$C$145+Calc_High!$C$147+Calc_High!$C$148+Calc_High!$C$149+Calc_High!$C$151+Calc_High!$C$152) -> 1744000 | E5: =IF(AND(B5<=C5,C5<=D5),"OK","CHECK") -> OK
A6: L3 Inference and usage | B6: =Calc_Low!$C$13+Calc_Low!$C$14+Calc_Low!$C$15+Calc_Low!$C$16+Calc_Low!$C$40+Calc_Low!$C$41+Calc_Low!$C$42+Calc_Low!$C$43+Calc_Low!$C$67+Calc_Low!$C$68+Calc_Low!$C$69+Calc_Low!$C$70+Calc_Low!$C$94+Calc_Low!$C$95+Calc_Low!$C$96+Calc_Low!$C$97+Calc_Low!$C$121+Calc_Low!$C$122+Calc_Low!$C$123+Calc_Low!$C$124 -> 6891321.5 | C6: =Calc_Base!$C$13+Calc_Base!$C$14+Calc_Base!$C$15+Calc_Base!$C$16+Calc_Base!$C$40+Calc_Base!$C$41+Calc_Base!$C$42+Calc_Base!$C$43+Calc_Base!$C$67+Calc_Base!$C$68+Calc_Base!$C$69+Calc_Base!$C$70+Calc_Base!$C$94+Calc_Base!$C$95+Calc_Base!$C$96+Calc_Base!$C$97+Calc_Base!$C$121+Calc_Base!$C$122+Calc_Base!$C$123+Calc_Base!$C$124 -> 7420931 | D6: =Calc_High!$C$13+Calc_High!$C$14+Calc_High!$C$15+Calc_High!$C$16+Calc_High!$C$40+Calc_High!$C$41+Calc_High!$C$42+Calc_High!$C$43+Calc_High!$C$67+Calc_High!$C$68+Calc_High!$C$69+Calc_High!$C$70+Calc_High!$C$94+Calc_High!$C$95+Calc_High!$C$96+Calc_High!$C$97+Calc_High!$C$121+Calc_High!$C$122+Calc_High!$C$123+Calc_High!$C$124 -> 11634868 | E6: =IF(AND(B6<=C6,C6<=D6),"OK","CHECK") -> OK
A7: L4 Run and maintenance | B7: =Calc_Low!$C$20+Calc_Low!$C$21+Calc_Low!$C$47+Calc_Low!$C$48+Calc_Low!$C$74+Calc_Low!$C$75+Calc_Low!$C$101+Calc_Low!$C$102+Calc_Low!$C$128+Calc_Low!$C$129+Calc_Low!$B$170*(Calc_Low!$C$153+Calc_Low!$C$154+Calc_Low!$C$155+Calc_Low!$C$156+Calc_Low!$C$157) -> 1980275.1 | C7: =Calc_Base!$C$20+Calc_Base!$C$21+Calc_Base!$C$47+Calc_Base!$C$48+Calc_Base!$C$74+Calc_Base!$C$75+Calc_Base!$C$101+Calc_Base!$C$102+Calc_Base!$C$128+Calc_Base!$C$129+Calc_Base!$B$170*(Calc_Base!$C$153+Calc_Base!$C$154+Calc_Base!$C$155+Calc_Base!$C$156+Calc_Base!$C$157) -> 4114050.7 | D7: =Calc_High!$C$20+Calc_High!$C$21+Calc_High!$C$47+Calc_High!$C$48+Calc_High!$C$74+Calc_High!$C$75+Calc_High!$C$101+Calc_High!$C$102+Calc_High!$C$128+Calc_High!$C$129+Calc_High!$B$170*(Calc_High!$C$153+Calc_High!$C$154+Calc_High!$C$155+Calc_High!$C$156+Calc_High!$C$157) -> 15856426 | E7: =IF(AND(B7<=C7,C7<=D7),"OK","CHECK") -> OK
A8: L5 People and change | B8: =Calc_Low!$C$22+Calc_Low!$C$23+Calc_Low!$C$27+Calc_Low!$C$49+Calc_Low!$C$50+Calc_Low!$C$54+Calc_Low!$C$76+Calc_Low!$C$77+Calc_Low!$C$81+Calc_Low!$C$103+Calc_Low!$C$104+Calc_Low!$C$108+Calc_Low!$C$130+Calc_Low!$C$131+Calc_Low!$C$135 -> 2284314.9 | C8: =Calc_Base!$C$22+Calc_Base!$C$23+Calc_Base!$C$27+Calc_Base!$C$49+Calc_Base!$C$50+Calc_Base!$C$54+Calc_Base!$C$76+Calc_Base!$C$77+Calc_Base!$C$81+Calc_Base!$C$103+Calc_Base!$C$104+Calc_Base!$C$108+Calc_Base!$C$130+Calc_Base!$C$131+Calc_Base!$C$135 -> 5911168.5 | D8: =Calc_High!$C$22+Calc_High!$C$23+Calc_High!$C$27+Calc_High!$C$49+Calc_High!$C$50+Calc_High!$C$54+Calc_High!$C$76+Calc_High!$C$77+Calc_High!$C$81+Calc_High!$C$103+Calc_High!$C$104+Calc_High!$C$108+Calc_High!$C$130+Calc_High!$C$131+Calc_High!$C$135 -> 19377365 | E8: =IF(AND(B8<=C8,C8<=D8),"OK","CHECK") -> OK
A9: Total cost | B9: =SUM(B4:B8) -> 11529165 | C9: =SUM(C4:C8) -> 18344688 | D9: =SUM(D4:D8) -> 49625554 | E9: =IF(AND(B9<=C9,C9<=D9),"OK","CHECK") -> OK
A10: Benefit | B10: =Calc_Low!$C$174 -> 26033657 | C10: =Calc_Base!$C$174 -> 26033657 | D10: =Calc_High!$C$174 -> 26033657
A11: Net value | B11: =B10-B9 -> 14504491 | C11: =C10-C9 -> 7688968.4 | D11: =D10-D9 -> -23591897
A12: Payback month | B12: =Calc_Low!$C$179 -> 6 | C12: =Calc_Base!$C$179 -> 12 | D12: =Calc_High!$C$179 -> None
A13: Cost per outcome | B13: =IF((Calc_Low!$C$12+Calc_Low!$C$39+Calc_Low!$C$66+Calc_Low!$C$93+Calc_Low!$C$120)=0,0,B9/(Calc_Low!$C$12+Calc_Low!$C$39+Calc_Low!$C$66+Calc_Low!$C$93+Calc_Low!$C$120)) -> 0.94896499 | C13: =IF((Calc_Base!$C$12+Calc_Base!$C$39+Calc_Base!$C$66+Calc_Base!$C$93+Calc_Base!$C$120)=0,0,C9/(Calc_Base!$C$12+Calc_Base!$C$39+Calc_Base!$C$66+Calc_Base!$C$93+Calc_Base!$C$120)) -> 1.5099503 | D13: =IF((Calc_High!$C$12+Calc_High!$C$39+Calc_High!$C$66+Calc_High!$C$93+Calc_High!$C$120)=0,0,D9/(Calc_High!$C$12+Calc_High!$C$39+Calc_High!$C$66+Calc_High!$C$93+Calc_High!$C$120)) -> 4.0846767
A15: High-cost is a stress case: every parameter at its high value at once. It is not a likely outcome. Published forecast-miss rates (FCS-01, grade C) are much narrower.

Sheet Sensitivity
A1: Sensitivity and the kill number
A2: One-at-a-time, linear scaling of the selected scenario's components. Checked in Phase 5 by full recalculation: exact for realisation, minutes saved, acceptance, tokens, review minutes and effort; approximate for adoption and volume (about 8% of that driver's swing at x0.7). Multipliers are grade D inputs.
A4: Benefit (B) | B4: =Results!$J$54 -> 26033657
A5: Total cost | B5: =Results!$J$57 -> 18344688
A6: Net value (N0 = B minus cost) | B6: =B4-B5 -> 7688968.4
A7: Model token cost | B7: =SUM(Results!D6:H6) -> 798310.5
A8: Human review cost | B8: =SUM(Results!D14:H14) -> 4027616.5
A9: Volume-driven cost (tokens, vendor, tools, review) | B9: =SUM(Results!D6:H6)+SUM(Results!D7:H7)+SUM(Results!D8:H8)+SUM(Results!D14:H14) -> 6120547.5
A10: Person-day-rate-driven effort cost (starter effort lines, migration, cost governance; hub after shape) | B10: =Results!D45+SUM(Results!D13:H13)+Results!J30 -> 6822687
A12: Driver | B12: Effect on net value per +100% (USD) | C12: Low multiplier | D12: High multiplier | E12: Net value at low | F12: Net value at high | G12: Swing | H12: Rank | I12: Break-even multiplier | J12: Margin of safety | K12: Direction | L12: Break-even value (where a single scalar exists)
A13: Realisation share of self-reported time saved | B13: =$B$4 -> 26033657 | C13: 0.5 | D13: 1.5 | E13: =$B$6+(C13-1)*B13 -> -5327859.8 | F13: =$B$6+(D13-1)*B13 -> 20705797 | G13: =ABS(F13-E13) -> 26033657 | H13: =RANK(G13,$G$13:$G$19)+COUNTIF($G$13:G13,G13)-1 -> 1 | I13: =IF(B13=0,"n/a",1-$B$6/B13) -> 0.70465277 | J13: =IF(B13=0,1000000000,$B$6/ABS(B13)) -> 0.29534723 | K13: =IF(B13>0,"can fall by","can rise by") -> can fall by | L13: =I13*INDEX(Params!$D$41:$F$41,Org!$B$17) -> 0.35232638
A14: Minutes saved per outcome | B14: =$B$4 -> 26033657 | C14: 0.5 | D14: 1.5 | E14: =$B$6+(C14-1)*B14 -> -5327859.8 | F14: =$B$6+(D14-1)*B14 -> 20705797 | G14: =ABS(F14-E14) -> 26033657 | H14: =RANK(G14,$G$13:$G$19)+COUNTIF($G$13:G14,G14)-1 -> 2 | I14: =IF(B14=0,"n/a",1-$B$6/B14) -> 0.70465277 | J14: =IF(B14=0,1000000000,$B$6/ABS(B14)) -> 0.29534723 | K14: =IF(B14>0,"can fall by","can rise by") -> can fall by
A15: Quality or acceptance rate | B15: =$B$4 -> 26033657 | C15: 0.8 | D15: 1.1 | E15: =$B$6+(C15-1)*B15 -> 2482237.1 | F15: =$B$6+(D15-1)*B15 -> 10292334 | G15: =ABS(F15-E15) -> 7810097 | H15: =RANK(G15,$G$13:$G$19)+COUNTIF($G$13:G15,G15)-1 -> 5 | I15: =IF(B15=0,"n/a",1-$B$6/B15) -> 0.70465277 | J15: =IF(B15=0,1000000000,$B$6/ABS(B15)) -> 0.29534723 | K15: =IF(B15>0,"can fall by","can rise by") -> can fall by
A16: Adoption and volume (active share, outcomes) | B16: =$B$4-$B$9 -> 19913109 | C16: 0.7 | D16: 1.3 | E16: =$B$6+(C16-1)*B16 -> 1715035.7 | F16: =$B$6+(D16-1)*B16 -> 13662901 | G16: =ABS(F16-E16) -> 11947865 | H16: =RANK(G16,$G$13:$G$19)+COUNTIF($G$13:G16,G16)-1 -> 3 | I16: =IF(B16=0,"n/a",1-$B$6/B16) -> 0.61387403 | J16: =IF(B16=0,1000000000,$B$6/ABS(B16)) -> 0.38612597 | K16: =IF(B16>0,"can fall by","can rise by") -> can fall by
A17: Tokens per outcome | B17: =-$B$7 -> -798310.5 | C17: 0.7 | D17: 1.5 | E17: =$B$6+(C17-1)*B17 -> 7928461.6 | F17: =$B$6+(D17-1)*B17 -> 7289813.2 | G17: =ABS(F17-E17) -> 638648.4 | H17: =RANK(G17,$G$13:$G$19)+COUNTIF($G$13:G17,G17)-1 -> 7 | I17: =IF(B17=0,"n/a",1-$B$6/B17) -> 10.631551 | J17: =IF(B17=0,1000000000,$B$6/ABS(B17)) -> 9.6315511 | K17: =IF(B17>0,"can fall by","can rise by") -> can rise by
A18: Human review minutes | B18: =-$B$8 -> -4027616.5 | C18: 0.66666667 | D18: 2 | E18: =$B$6+(C18-1)*B18 -> 9031507.3 | F18: =$B$6+(D18-1)*B18 -> 3661351.9 | G18: =ABS(F18-E18) -> 5370155.4 | H18: =RANK(G18,$G$13:$G$19)+COUNTIF($G$13:G18,G18)-1 -> 6 | I18: =IF(B18=0,"n/a",1-$B$6/B18) -> 2.9090617 | J18: =IF(B18=0,1000000000,$B$6/ABS(B18)) -> 1.9090617 | K18: =IF(B18>0,"can fall by","can rise by") -> can rise by
A19: Effort (person-day-rate-driven lines) | B19: =-$B$10 -> -6822687 | C19: 0.5 | D19: 2 | E19: =$B$6+(C19-1)*B19 -> 11100312 | F19: =$B$6+(D19-1)*B19 -> 866281.44 | G19: =ABS(F19-E19) -> 10234030 | H19: =RANK(G19,$G$13:$G$19)+COUNTIF($G$13:G19,G19)-1 -> 4 | I19: =IF(B19=0,"n/a",1-$B$6/B19) -> 2.1269707 | J19: =IF(B19=0,1000000000,$B$6/ABS(B19)) -> 1.1269707 | K19: =IF(B19>0,"can fall by","can rise by") -> can rise by
A22: The number that would kill the case (smallest margin of safety)
A23: Driver | B23: =IF($B$6<=0,"Net value is already zero or negative",INDEX($A$13:$A$19,MATCH(MIN($J$13:$J$19),$J$13:$J$19,0))) -> Realisation share of self-reported time saved
A24: How far it can move | B24: =IF($B$6<=0,"Nothing to erode in this scenario",INDEX($K$13:$K$19,MATCH(MIN($J$13:$J$19),$J$13:$J$19,0))&" "&TEXT(MIN($J$13:$J$19),"0%")&" before net value reaches zero (break-even multiplier "&TEXT(INDEX($I$13:$I$19,MATCH(MIN($J$13:$J$19),$J$13:$J$19,0)),"0.00")&"x)") -> can fall by 30% before net value reaches zero (break-even multiplier 0.70x)
A26: Top three drivers by swing
A27: Rank 1 | B27: =INDEX($A$13:$A$19,MATCH(1,$H$13:$H$19,0))&" (swing "&TEXT(INDEX($G$13:$G$19,MATCH(1,$H$13:$H$19,0)),"$#,##0")&")" -> Realisation share of self-reported time saved (swing $26,033,657)
A28: Rank 2 | B28: =INDEX($A$13:$A$19,MATCH(2,$H$13:$H$19,0))&" (swing "&TEXT(INDEX($G$13:$G$19,MATCH(2,$H$13:$H$19,0)),"$#,##0")&")" -> Minutes saved per outcome (swing $26,033,657)
A29: Rank 3 | B29: =INDEX($A$13:$A$19,MATCH(3,$H$13:$H$19,0))&" (swing "&TEXT(INDEX($G$13:$G$19,MATCH(3,$H$13:$H$19,0)),"$#,##0")&")" -> Adoption and volume (active share, outcomes) (swing $11,947,865)

Sheet Allocation
A1: Cost-center table (showback)
A2: CSV-ready: each row is one cost center. Direct cost plus the allocated hub share. Fictional cost centers.
A3: Cost center | B3: Business unit | C3: Team | D3: Direct cost | E3: Allocated hub cost | F3: Total cost | G3: Share of total
A4: CC-1001 | B4: =Teams!$C$7 -> Corporate functions | C4: =Teams!$C$4 -> Corporate knowledge assistant (conservative calibration) | D4: =Results!D55 -> 4790801.6 | E4: =Results!D56 -> 1052885.2 | F4: =D4+E4 -> 5843686.8 | G4: =IF($F$10=0,0,F4/$F$10) -> 0.31854926
A5: CC-1002 | B5: =Teams!$D$7 -> Engineering | C5: =Teams!$D$4 -> Engineering assistant | D5: =Results!E55 -> 3529280.8 | E5: =Results!E56 -> 1285113.6 | F5: =D5+E5 -> 4814394.4 | G5: =IF($F$10=0,0,F5/$F$10) -> 0.26244079
A6: CC-1003 | B6: =Teams!$E$7 -> Customer operations | C6: =Teams!$E$4 -> Customer service agent | D6: =Results!F55 -> 1850472 | E6: =Results!F56 -> 378316.96 | F6: =D6+E6 -> 2228789 | G6: =IF($F$10=0,0,F6/$F$10) -> 0.12149506
A7: CC-1004 | B7: =Teams!$F$7 -> Risk and legal | C7: =Teams!$F$4 -> Regulated document review | D7: =Results!G55 -> 1381251.2 | E7: =Results!G56 -> 117336.46 | F7: =D7+E7 -> 1498587.7 | G7: =IF($F$10=0,0,F7/$F$10) -> 0.081690551
A8: CC-1005 | B8: =Teams!$G$7 -> Sales and marketing | C8: =Teams!$G$4 -> Sales assistant (published-range calibration) | D8: =Results!H55 -> 3257306.8 | E8: =Results!H56 -> 701923.46 | F8: =D8+E8 -> 3959230.3 | G8: =IF($F$10=0,0,F8/$F$10) -> 0.21582434
A9: HUB-UNALLOC | B9: Hub (central budget) | C9: Unallocated shared cost | D9: 0 | E9: =Results!$J$64 -> 0 | F9: =D9+E9 -> 0 | G9: =IF($F$10=0,0,F9/$F$10) -> 0
A10: Total | D10: =SUM(D4:D9) -> 14809112 | E10: =SUM(E4:E9) -> 3535575.7 | F10: =SUM(F4:F9) -> 18344688 | G10: =SUM(G4:G9) -> 1

Sheet Evidence
A1: Assumptions register
A2: Every input with its label, source, date, grade, owner and review date. Values link to the input cells.
A3: Input ID | B3: Name | C3: Value (base) | D3: Unit | E3: Label | F3: Source | G3: Date | H3: Grade | I3: Owner | J3: Last reviewed
A4: ORG.name | B4: Organization name | C4: =Org!$B$4 -> Northwind Example Co (fictional) | D4: text | E4: assumed | F4: Fictional worked example (Claude, 2026-09-20) | G4: 46285 | H4: D | I4: AI program lead (fictional) | J4: 46285
A5: ORG.horizon | B5: Horizon | C5: =Org!$B$5 -> 36 | D5: months (max 60) | E5: assumed | F5: Project owner's choice, 2026-09-20 | G5: 46285 | H5: D | I5: AI program lead (fictional) | J5: 46285
A6: ORG.scenario | B6: Scenario shown on Summary | C6: =Org!$B$6 -> Base | D6: Low-cost / Base / High-cost (High-cost is a stress case: every parameter at its high value at once) | E6: assumed | F6: User choice | G6: 46285 | H6: D | I6: AI program lead (fictional) | J6: 46285
A7: ORG.value_case | B7: Value case (realisation share) | C7: =Org!$B$7 -> Base | D7: Low / Base / High | E7: assumed | F7: User choice | G7: 46285 | H7: D | I7: AI program lead (fictional) | J7: 46285
A8: ORG.shape | B8: Org shape | C8: =Org!$B$8 -> Hub-and-spoke | D8: Centralized / Federated / Hub-and-spoke | E8: assumed | F8: User choice; definitions in research/enterprise-structure.md | G8: 46285 | H8: D | I8: AI program lead (fictional) | J8: 46285
A9: ORG.alloc | B9: Allocation rule | C9: =Org!$B$9 -> Usage-proportional | D9: Usage-proportional / Headcount proxy / Even split / Central budget | E9: assumed | F9: Default per shape (D), research/enterprise-structure.md | G9: 46285 | H9: D | I9: AI program lead (fictional) | J9: 46285
A10: ORG.pd_rate | B10: Person-day rate | C10: =Org!$B$10 -> 800 | D10: USD per person-day | E10: assumed | F10: spec/starter-values.md (Claude, 2026-09-20); cross-check BLS LAB-02 (S41, S42) | G10: 46285 | H10: D | I10: AI program lead (fictional) | J10: 46285
A11: ORG.hours_day | B11: Hours per person-day | C11: =Org!$B$11 -> 8 | D11: hours | E11: assumed | F11: spec/starter-values.md (Claude, 2026-09-20) | G11: 46285 | H11: D | I11: AI program lead (fictional) | J11: 46285
A12: ORG.work_days | B12: Working days per year | C12: =Org!$B$12 -> 220 | D12: days | E12: assumed | F12: spec/starter-values.md (Claude, 2026-09-20) | G12: 46285 | H12: D | I12: AI program lead (fictional) | J12: 46285
A13: ORG.obs_per_out | B13: Monitoring units per outcome | C13: =Org!$B$13 -> 5 | D13: units | E13: assumed | F13: Fictional worked example (Claude, 2026-09-20) | G13: 46285 | H13: D | I13: AI program lead (fictional) | J13: 46285
A14: PARAM.src_pd | B14: Assess one source system | C14: =Params!$E$4 -> 3 | D14: person-days | E14: assumed | F14: spec/starter-values.md (CL-01); Owner interview, access check, sample review | G14: 46285 | H14: D | I14: AI program lead (fictional) | J14: 46285
A15: PARAM.clean_pd | B15: Clean and label 100,000 documents | C15: =Params!$E$5 -> 20 | D15: person-days | E15: assumed | F15: spec/starter-values.md (CL-02); Pipeline plus sampled review; range wide because published shares conflict (CST-07) | G15: 46285 | H15: D | I15: AI program lead (fictional) | J15: 46285
A16: PARAM.conn_pd | B16: Build one connector | C16: =Params!$E$6 -> 10 | D16: person-days | E16: assumed | F16: spec/starter-values.md (CL-03); Standard vs custom source | G16: 46285 | H16: D | I16: AI program lead (fictional) | J16: 46285
A17: PARAM.conn_up | B17: Connector upkeep per year | C17: =Params!$E$7 -> 0.15 | D17: share of build | E17: assumed | F17: spec/starter-values.md (CL-03); Yearly upkeep share | G17: 46285 | H17: D | I17: AI program lead (fictional) | J17: 46285
A18: PARAM.perm_pd | B18: Map permissions for one source | C18: =Params!$E$8 -> 4 | D18: person-days | E18: assumed | F18: spec/starter-values.md (CL-04); Map groups once, revise on org change | G18: 46285 | H18: D | I18: AI program lead (fictional) | J18: 46285
A19: PARAM.perm_up | B19: Permission upkeep per year | C19: =Params!$E$9 -> 0.1 | D19: share of build | E19: assumed | F19: spec/starter-values.md (CL-04); Org change rate | G19: 46285 | H19: D | I19: AI program lead (fictional) | J19: 46285
A20: PARAM.change_rate | B20: Share of documents changing per month | C20: =Params!$E$10 -> 0.03 | D20: share | E20: assumed | F20: spec/starter-values.md (CL-08); Slow policy content vs fast tickets | G20: 46285 | H20: D | I20: AI program lead (fictional) | J20: 46285
A21: PARAM.plat_pd | B21: Platform or gateway, one-time | C21: =Params!$E$11 -> 120 | D21: person-days | E21: assumed | F21: spec/starter-values.md (CL-09); Configure or build gateway with logging and access control; base x rate = $96,000 vs ENV-01 (B*, 2024) | G21: 46285 | H21: D | I21: AI program lead (fictional) | J21: 46285
A22: PARAM.plat_run | B22: Platform run per year | C22: =Params!$E$12 -> 0.2 | D22: share of one-time | E22: assumed | F22: spec/starter-values.md (CL-09); Yearly run share | G22: 46285 | H22: D | I22: AI program lead (fictional) | J22: 46285
A23: PARAM.int_pd | B23: Integrate one use case | C23: =Params!$E$13 -> 40 | D23: person-days | E23: assumed | F23: spec/starter-values.md (CL-10); Connect one workflow and its systems | G23: 46285 | H23: D | I23: AI program lead (fictional) | J23: 46285
A24: PARAM.rev_uc_pd | B24: Security, privacy, legal review per use case | C24: =Params!$E$14 -> 10 | D24: person-days | E24: assumed | F24: spec/starter-values.md (CL-11); A few days each from three reviewers | G24: 46285 | H24: D | I24: AI program lead (fictional) | J24: 46285
A25: PARAM.rev_once_pd | B25: Platform-level review, once | C25: =Params!$E$15 -> 30 | D25: person-days | E25: assumed | F25: spec/starter-values.md (CL-11); One-time platform review | G25: 46285 | H25: D | I25: AI program lead (fictional) | J25: 46285
A26: PARAM.eval_pd | B26: Evaluation harness per use case | C26: =Params!$E$16 -> 20 | D26: person-days | E26: assumed | F26: spec/starter-values.md (CL-12); Build a test set and scoring | G26: 46285 | H26: D | I26: AI program lead (fictional) | J26: 46285
A27: PARAM.eval_rerun | B27: Share of harness re-done per model change | C27: =Params!$E$17 -> 0.25 | D27: share | E27: assumed | F27: spec/starter-values.md (CL-12); Re-run when the model changes | G27: 46285 | H27: D | I27: AI program lead (fictional) | J27: 46285
A28: PARAM.rt_pd | B28: Red-team one use case | C28: =Params!$E$18 -> 8 | D28: person-days | E28: assumed | F28: spec/starter-values.md (CL-13); Adversarial testing before launch | G28: 46285 | H28: D | I28: AI program lead (fictional) | J28: 46285
A29: PARAM.rt_rep | B29: Red-team repeat per year | C29: =Params!$E$19 -> 0.5 | D29: share of one-time | E29: assumed | F29: spec/starter-values.md (CL-13); Periodic repeat | G29: 46285 | H29: D | I29: AI program lead (fictional) | J29: 46285
A30: PARAM.env_month | B30: Environments and base infrastructure | C30: =Params!$E$20 -> 0 | D30: USD per month | E30: assumed | F30: spec/starter-values.md (CL-14); No starter: off until entered (approved 2026-09-20) | G30: 46285 | H30: D | I30: AI program lead (fictional) | J30: 46285
A31: PARAM.retry | B31: Retry and failure multiplier on tokens | C31: =Params!$E$21 -> 1.15 | D31: multiplier | E31: assumed | F31: spec/starter-values.md (CL-17); Minority of calls retried (G8) | G31: 46285 | H31: D | I31: AI program lead (fictional) | J31: 46285
A32: PARAM.steps | B32: Agent steps per outcome (agentic teams) | C32: =Params!$E$22 -> 6 | D32: count | E32: assumed | F32: spec/starter-values.md (CL-17); Plan, tool calls, check (G8) | G32: 46285 | H32: D | I32: AI program lead (fictional) | J32: 46285
A33: PARAM.evalcases | B33: Quality-review cases per month per use case | C33: =Params!$E$23 -> 200 | D33: cases | E33: assumed | F33: spec/starter-values.md (CL-25); Sample outputs and score them | G33: 46285 | H33: D | I33: AI program lead (fictional) | J33: 46285
A34: PARAM.eval_min | B34: Minutes per quality-review case | C34: =Params!$E$24 -> 10 | D34: minutes | E34: assumed | F34: spec/starter-values.md (CL-25); Read and score one output | G34: 46285 | H34: D | I34: AI program lead (fictional) | J34: 46285
A35: PARAM.mig_int | B35: Months between model migration events | C35: =Params!$E$25 -> 15 | D35: months | E35: assumed | F35: spec/starter-values.md (CL-26); Derived from retirement data: min 12, median 14.5, max 25.4 (PRC-06, one provider) | G35: 46285 | H35: C | I35: AI program lead (fictional) | J35: 46285
A36: PARAM.mig_pd | B36: Re-evaluate one workflow per migration event | C36: =Params!$E$26 -> 3 | D36: person-days | E36: assumed | F36: spec/starter-values.md (CL-26); Effort per workflow (G12) | G36: 46285 | H36: D | I36: AI program lead (fictional) | J36: 46285
A37: PARAM.maint | B37: Workflow maintenance per year | C37: =Params!$E$27 -> 0.1 | D37: share of integration | E37: assumed | F37: spec/starter-values.md (CL-27); Prompt changes and fixes | G37: 46285 | H37: D | I37: AI program lead (fictional) | J37: 46285
A38: PARAM.tickets | B38: Support tickets per 1,000 active users per month | C38: =Params!$E$28 -> 20 | D38: tickets | E38: assumed | F38: spec/starter-values.md (CL-28); Questions and incidents | G38: 46285 | H38: D | I38: AI program lead (fictional) | J38: 46285
A39: PARAM.tkt_hours | B39: Hours per support ticket | C39: =Params!$E$29 -> 1 | D39: hours | E39: assumed | F39: spec/starter-values.md (CL-28); Handle one ticket | G39: 46285 | H39: D | I39: AI program lead (fictional) | J39: 46285
A40: PARAM.plat_fte | B40: Hub platform team | C40: =Params!$E$30 -> 5 | D40: FTE | E40: assumed | F40: spec/starter-values.md (CL-29); Product owner, two engineers, data engineer, governance lead | G40: 46285 | H40: D | I40: AI program lead (fictional) | J40: 46285
A41: PARAM.gov_fte | B41: AI cost governance | C41: =Params!$E$31 -> 1 | D41: FTE | E41: assumed | F41: spec/starter-values.md (CL-30); AI share of a FinOps function; ORG-07 covers the whole function (B) | G41: 46285 | H41: C | I41: AI program lead (fictional) | J41: 46285
A42: PARAM.comp_year | B42: Compliance audit and governance | C42: =Params!$E$32 -> 0 | D42: USD per year | E42: assumed | F42: spec/starter-values.md (CL-31); No starter: off until entered (approved 2026-09-20) | G42: 46285 | H42: D | I42: AI program lead (fictional) | J42: 46285
A43: PARAM.lic_year | B43: Platform and vendor licences | C43: =Params!$E$33 -> 0 | D43: USD per year | E43: assumed | F43: spec/starter-values.md (CL-32); No starter: enter quotes | G43: 46285 | H43: D | I43: AI program lead (fictional) | J43: 46285
A44: PARAM.train_hours | B44: Training per active user, one-time | C44: =Params!$E$34 -> 4 | D44: hours | E44: assumed | F44: spec/starter-values.md (CL-33); Short course plus practice | G44: 46285 | H44: D | I44: AI program lead (fictional) | J44: 46285
A45: PARAM.rev_mult | B45: Human review share multiplier | C45: =Params!$E$35 -> 1 | D45: multiplier (capped at 100%) | E45: assumed | F45: spec/starter-values.md (CL-34); Low is base x 0.5; high is base x 2 | G45: 46285 | H45: C | I45: AI program lead (fictional) | J45: 46285
A46: PARAM.rev_min | B46: Minutes per human review | C46: =Params!$E$36 -> 3 | D46: minutes | E46: assumed | F46: spec/starter-values.md (CL-34); Review one output; ORG-06 review shares (B*). Range narrowed from 1/3/10 at Phase 5 approval | G46: 46285 | H46: C | I46: AI program lead (fictional) | J46: 46285
A47: PARAM.cm_ramp | B47: Change champions during first 6 months | C47: =Params!$E$37 -> 0.5 | D47: FTE per 1,000 licensed | E47: assumed | F47: spec/starter-values.md (CL-35); Champions and communications during ramp | G47: 46285 | H47: D | I47: AI program lead (fictional) | J47: 46285
A48: PARAM.cm_after | B48: Change champions after ramp | C48: =Params!$E$38 -> 0.1 | D48: FTE per 1,000 licensed | E48: assumed | F48: spec/starter-values.md (CL-35); Sustaining communications | G48: 46285 | H48: D | I48: AI program lead (fictional) | J48: 46285
A49: PARAM.tok_mult | B49: Tokens-per-outcome scenario multiplier | C49: =Params!$E$39 -> 1 | D49: multiplier | E49: assumed | F49: spec/starter-values.md (CL-16); Wide band by design (FCS-01, C) | G49: 46285 | H49: D | I49: AI program lead (fictional) | J49: 46285
A50: PARAM.fed_dup | B50: Federated: each unit's platform as share of a full hub platform | C50: =Params!$E$40 -> 0.5 | D50: share | E50: assumed | F50: spec/starter-values.md (org shape); No evidence on duplication (G4) | G50: 46285 | H50: D | I50: AI program lead (fictional) | J50: 46285
A51: PARAM.realise | B51: Realisation share of self-reported time saved | C51: =Params!$E$41 -> 0.5 | D51: share | E51: assumed | F51: spec/starter-values.md (value); No evidence converts self-reported time saved to cash (G5) | G51: 46285 | H51: D | I51: AI program lead (fictional) | J51: 46285
A52: TEAM.name | B52: Team name | C52: see Teams sheet (one value per team) | D52: text | E52: assumed | F52: Fictional worked example (Claude, 2026-09-20) | G52: 46285 | H52: D | I52: Team product owner (fictional) | J52: 46285
A53: TEAM.active | B53: Team is active (1 = counted, 0 = ignored) | C53: see Teams sheet (one value per team) | D53: 1 / 0 | E53: assumed | F53: Fictional worked example (Claude, 2026-09-20) | G53: 46285 | H53: D | I53: Team product owner (fictional) | J53: 46285
A54: TEAM.archetype | B54: Archetype | C54: see Teams sheet (one value per team) | D54: text | E54: assumed | F54: Fictional worked example (Claude, 2026-09-20) | G54: 46285 | H54: D | I54: Team product owner (fictional) | J54: 46285
A55: TEAM.bu | B55: Business unit and cost center | C55: see Teams sheet (one value per team) | D55: text | E55: assumed | F55: Fictional worked example (Claude, 2026-09-20) | G55: 46285 | H55: D | I55: Team product owner (fictional) | J55: 46285
A56: TEAM.buy | B56: Buying model | C56: see Teams sheet (one value per team) | D56: Seat / Seat + usage / Per-unit / Committed capacity | E56: assumed | F56: Fictional worked example (Claude, 2026-09-20) | G56: 46285 | H56: D | I56: Team product owner (fictional) | J56: 46285
A57: TEAM.seat_std | B57: Seat price (price book ID) | C57: see Teams sheet (one value per team) | D57: ID | E57: assumed | F57: Fictional worked example (Claude, 2026-09-20) | G57: 46285 | H57: D | I57: Team product owner (fictional) | J57: 46285
A58: TEAM.seat_prem | B58: Premium seat price (price book ID) | C58: see Teams sheet (one value per team) | D58: ID | E58: assumed | F58: Fictional worked example (Claude, 2026-09-20) | G58: 46285 | H58: D | I58: Team product owner (fictional) | J58: 46285
A59: TEAM.prem_share | B59: Share of licensed users on premium seats | C59: see Teams sheet (one value per team) | D59: share | E59: assumed | F59: Fictional worked example (Claude, 2026-09-20) | G59: 46285 | H59: D | I59: Team product owner (fictional) | J59: 46285
A60: TEAM.allow | B60: Usage included per seat per month (hybrid) | C60: see Teams sheet (one value per team) | D60: USD | E60: assumed | F60: Fictional worked example (Claude, 2026-09-20) | G60: 46285 | H60: D | I60: Team product owner (fictional) | J60: 46285
A61: TEAM.top_share | B61: Top segment share of active users | C61: see Teams sheet (one value per team) | D61: share | E61: assumed | F61: Fictional worked example (Claude, 2026-09-20) | G61: 46285 | H61: D | I61: Team product owner (fictional) | J61: 46285
A62: TEAM.top_mult | B62: Top segment intensity vs the rest | C62: see Teams sheet (one value per team) | D62: multiple | E62: assumed | F62: Fictional worked example (Claude, 2026-09-20) | G62: 46285 | H62: D | I62: Team product owner (fictional) | J62: 46285
A63: TEAM.unit_price | B63: Vendor per-outcome price (price book ID, or none) | C63: see Teams sheet (one value per team) | D63: ID | E63: assumed | F63: Fictional worked example (Claude, 2026-09-20) | G63: 46285 | H63: D | I63: Team product owner (fictional) | J63: 46285
... A105: TEAM.accept | B105: Quality or acceptance rate | C105: see Teams sheet (one value per team) | D105: share | E105: assumed | F105: Fictional worked example (Claude, 2026-09-20) | G105: 46285 | H105: D | I105: Team product owner (fictional) | J105: 46285
A106: PB.M_HAIKU45 | B106: Claude Haiku 4.5 | C106: =PriceBook!$E$4 -> 1 | D106: USD per million tokens | E106: quoted | F106: S09 in evidence/source-register.md; Anthropic pricing page, fetched 2026-09-20 | G106: 46285 | H106: A | I106: AI program lead (fictional) | J106: 46285
A107: PB.M_SONNET5 | B107: Claude Sonnet 5 | C107: =PriceBook!$E$5 -> 2 | D107: USD per million tokens | E107: quoted | F107: S09 in evidence/source-register.md; Anthropic pricing page, fetched 2026-09-20 | G107: 46285 | H107: A | I107: AI program lead (fictional) | J107: 46285
A108: PB.M_OPUS5 | B108: Claude Opus 5 | C108: =PriceBook!$E$6 -> 5 | D108: USD per million tokens | E108: quoted | F108: S09 in evidence/source-register.md; Anthropic pricing page, fetched 2026-09-20 | G108: 46285 | H108: A | I108: AI program lead (fictional) | J108: 46285
A109: PB.M_GPT54MINI | B109: GPT-5.4 Mini (name as extracted) | C109: =PriceBook!$E$7 -> 0.75 | D109: USD per million tokens | E109: quoted | F109: S12 in evidence/source-register.md; OpenAI pricing page, fetched 2026-09-20 | G109: 46285 | H109: A | I109: AI program lead (fictional) | J109: 46285
A110: PB.M_GEM38FLASH | B110: Gemini 3.8 Flash (name as extracted) | C110: =PriceBook!$E$8 -> 0.75 | D110: USD per million tokens | E110: quoted | F110: S11 in evidence/source-register.md; Google pricing page, fetched 2026-09-20 | G110: 46285 | H110: A | I110: AI program lead (fictional) | J110: 46285
A111: PB.SEAT_TEAM_STD | B111: Claude Team standard seat (annual billing) | C111: =PriceBook!$E$9 -> 20 | D111: USD per user per month | E111: quoted | F111: S33 in evidence/source-register.md; Anthropic pricing page, fetched 2026-09-20 | G111: 46285 | H111: A | I111: AI program lead (fictional) | J111: 46285
A112: PB.SEAT_TEAM_PREM | B112: Claude Team premium seat (annual billing) | C112: =PriceBook!$E$10 -> 100 | D112: USD per user per month | E112: quoted | F112: S33 in evidence/source-register.md; Anthropic pricing page, fetched 2026-09-20 | G112: 46285 | H112: A | I112: AI program lead (fictional) | J112: 46285
A113: PB.SEAT_ENT | B113: Claude Enterprise seat (annual); usage billed at API rates | C113: =PriceBook!$E$11 -> 20 | D113: USD per user per month | E113: quoted | F113: S33 in evidence/source-register.md; Anthropic pricing page, fetched 2026-09-20 | G113: 46285 | H113: A | I113: AI program lead (fictional) | J113: 46285
A114: PB.SEAT_M365_BUS | B114: Microsoft 365 Copilot Business (annual, promotional) | C114: =PriceBook!$E$12 -> 18 | D114: USD per user per month | E114: quoted | F114: S08 in evidence/source-register.md; Microsoft pricing page, fetched 2026-09-20 | G114: 46285 | H114: A | I114: AI program lead (fictional) | J114: 46285
A115: PB.SEAT_M365 | B115: Microsoft 365 Copilot (paid yearly) | C115: =PriceBook!$E$13 -> 30 | D115: USD per user per month | E115: quoted | F115: S35 in evidence/source-register.md; Microsoft pricing page, fetched 2026-09-20 | G115: 46285 | H115: A | I115: AI program lead (fictional) | J115: 46285
A116: PB.OUT_FIN | B116: Fin AI agent, per outcome (outcome definition in BUY-06) | C116: =PriceBook!$E$14 -> 0.99 | D116: USD per outcome | E116: quoted | F116: S37 in evidence/source-register.md; Intercom pricing page, fetched 2026-09-20 | G116: 46285 | H116: A | I116: AI program lead (fictional) | J116: 46285
A117: PB.U_TEXTRACT_TXT | B117: Textract detect text, first 1M pages | C117: =PriceBook!$E$15 -> 0.0015 | D117: USD per page | E117: quoted | F117: S45 in evidence/source-register.md; AWS pricing page, fetched 2026-09-20 | G117: 46285 | H117: A | I117: AI program lead (fictional) | J117: 46285
A118: PB.U_TEXTRACT_TBL | B118: Textract tables, first 1M pages | C118: =PriceBook!$E$16 -> 0.015 | D118: USD per page | E118: quoted | F118: S45 in evidence/source-register.md; AWS pricing page, fetched 2026-09-20 | G118: 46285 | H118: A | I118: AI program lead (fictional) | J118: 46285
A119: PB.U_EMB_3L | B119: text-embedding-3-large | C119: =PriceBook!$E$17 -> 0.13 | D119: USD per million tokens | E119: quoted | F119: S12 in evidence/source-register.md; OpenAI pricing page, fetched 2026-09-20 | G119: 46285 | H119: A | I119: AI program lead (fictional) | J119: 46285
A120: PB.U_PINE_READ | B120: Read units (low end of range) | C120: =PriceBook!$E$18 -> 16 | D120: USD per million read units | E120: quoted | F120: S43 in evidence/source-register.md; Pinecone pricing page, fetched 2026-09-20 | G120: 46285 | H120: A | I120: AI program lead (fictional) | J120: 46285
A121: PB.U_PINE_STORE | B121: Storage, Standard plan | C121: =PriceBook!$E$19 -> 0.33 | D121: USD per GB per month | E121: quoted | F121: S43 in evidence/source-register.md; Pinecone pricing page, fetched 2026-09-20 | G121: 46285 | H121: A | I121: AI program lead (fictional) | J121: 46285
A122: PB.PL_PINE_STD | B122: Standard plan minimum | C122: =PriceBook!$E$20 -> 50 | D122: USD per month | E122: quoted | F122: S43 in evidence/source-register.md; Pinecone pricing page, fetched 2026-09-20 | G122: 46285 | H122: A | I122: AI program lead (fictional) | J122: 46285
A123: PB.U_GUARD_CF | B123: Bedrock Guardrails content filters | C123: =PriceBook!$E$21 -> 0.15 | D123: USD per 1,000 text units | E123: quoted | F123: S46 in evidence/source-register.md; AWS pricing page, fetched 2026-09-20 | G123: 46285 | H123: A | I123: AI program lead (fictional) | J123: 46285
A124: PB.U_TOOL_SEARCH | B124: Web search tool | C124: =PriceBook!$E$22 -> 10 | D124: USD per 1,000 calls | E124: quoted | F124: S09 in evidence/source-register.md; Anthropic/OpenAI pricing page, fetched 2026-09-20 | G124: 46285 | H124: A | I124: AI program lead (fictional) | J124: 46285
A125: PB.PL_LANGFUSE_PRO | B125: Pro plan (100k units included) | C125: =PriceBook!$E$23 -> 199 | D125: USD per month | E125: quoted | F125: S44 in evidence/source-register.md; Langfuse pricing page, fetched 2026-09-20 | G125: 46285 | H125: A | I125: AI program lead (fictional) | J125: 46285
A126: PB.U_LANGFUSE_OVER | B126: Overage per 100k units | C126: =PriceBook!$E$24 -> 8 | D126: USD per 100k units | E126: quoted | F126: S44 in evidence/source-register.md; Langfuse pricing page, fetched 2026-09-20 | G126: 46285 | H126: A | I126: AI program lead (fictional) | J126: 46285
A128: Share of cost by evidence category (selected scenario)
A129: Dated primary prices (A) | C129: =Results!$E$43 -> 0.40853159
A130: Ranges with a warning (B*/C) | C130: =Results!$E$44 -> 0.25182312
A131: Starter values (D) | C131: =Results!$E$45 -> 0.33964529
A132: Enterprise-entered, off until entered | C132: =Results!$E$46 -> 0

Sheet Tests
A1: Acceptance tests
A2: The ten tests from spec/requirements-spec.md plus tests 11 and 12 (added in Phases 5 and 6), as live formulas. Supporting calculations are below the table.
A3: # | B3: Test | C3: Result | D3: What is compared
A4: 1 | B4: Allocations sum to the enterprise hub cost under every rule and shape | C4: =IF(COUNTIF(L22:L33,"OK")=12,"PASS","FAIL") -> PASS | D4: 12 combinations, difference under $0.005
A5: 2 | B5: Amortised one-time costs sum to the one-time total | C5: =IF(AND(Org!$B$5>=1,Org!$B$5<=60,ABS(B38-C38)<0.005),"PASS","FAIL") -> PASS | D5: One-time total versus the sum of monthly amortisation
A6: 3 | B6: Lines sum to layers, and layers sum to the total | C6: =IF(AND(ABS(Results!$J$33-SUM(Results!$J$36:$J$40))<0.01,ABS(Results!$J$33-(SUM(Results!$D$57:$H$57)+Results!$J$64))<0.01),"PASS","FAIL") -> PASS | D6: Total cost versus layers, and versus teams plus unallocated hub
A7: 4 | B7: Zero outcomes gives zero variable cost while fixed costs remain | C7: =IF(AND(SUM(B42:B46)<0.005,SUM(C42:C46)>0,B47>0),"PASS","FAIL") -> PASS | D7: Zero-outcome months exist, variable cost in them is 0, hub cost in month 1 is positive
A8: 5 | B8: Lever fixtures match hand calculations and the provider's published example, and Levers matches Calc_Base | C8: =IF(AND(SUMPRODUCT(ABS(Levers!$B$40:$E$40))<0.000000001,SUMPRODUCT(ABS(Levers!$B$16:$F$16))<0.000000001),"PASS","FAIL") -> PASS | D8: Two hand-calculated fixtures, two from Anthropic's published example, and every team's cost per outcome
A9: 6 | B9: Shape changes hub lines, not variable inference cost | C9: =IF(AND(ABS(B50-C50)<0.005,IF(Org!$B$18*Calc_Base!$B$166=1,TRUE,ABS(B51-C51)>0.005)),"PASS","FAIL") -> PASS | D9: Same variable cost; effective hub cost differs
A10: 7 | B10: Every input has label, source, date, grade; evidence shares sum to 100% | C10: =IF(AND(COUNTBLANK(Evidence!$E$4:$H$126)=0,COUNTBLANK(Evidence!$J$4:$J$126)=0,ABS(Results!$E$47-1)<0.000000001),"PASS","FAIL") -> PASS | D10: No blanks in the register; category shares total 100%
A11: 8 | B11: No price lacks an effective date and a status | C11: =IF(AND(SUMPRODUCT((PriceBook!$A$4:$A$203<>"")*(PriceBook!$K$4:$K$203=""))=0,SUMPRODUCT((PriceBook!$A$4:$A$203<>"")*(PriceBook!$M$4:$M$203=""))=0,SUMPRODUCT((PriceBook!$A$4:$A$203<>"")*(PriceBook!$E$4:$E$203=""))=0),"PASS","FAIL") -> PASS | D11: Effective-from, status and price all filled
A12: 9 | B12: Effective cost per active user equals seat price divided by active share | C12: =IF(AND(ABS(E55-D55)<0.000001,D56=1,ABS(B56-C56)<0.000001),"PASS","FAIL") -> PASS | D12: Fixture, and live Team 1 once the ramp is complete
A13: 10 | B13: Low-cost <= Base <= High-cost in every layer and in total | C13: =IF(COUNTIF(Scenarios!$E$4:$E$9,"OK")=6,"PASS","FAIL") -> PASS | D13: Five layers and the total
A14: 11 | B14: Outcome and active-user totals cover only the horizon (added in Phase 5) | C14: =IF(AND(ABS(Calc_Base!$C$12-SUMPRODUCT((Calc_Base!$E$4:$BL$4<=Org!$B$5)*Calc_Base!$E$12:$BL$12))<0.005,ABS(Calc_Base!$C$11-SUMPRODUCT((Calc_Base!$E$4:$BL$4<=Org!$B$5)*Calc_Base!$E$11:$BL$11))<0.005,ABS(Calc_Base!$C$39-SUMPRODUCT((Calc_Base!$E$4:$BL$4<=Org!$B$5)*Calc_Base!$E$39:$BL$39))<0.005,ABS(Calc_Base!$C$38-SUMPRODUCT((Calc_Base!$E$4:$BL$4<=Org!$B$5)*Calc_Base!$E$38:$BL$38))<0.005,ABS(Calc_Base!$C$66-SUMPRODUCT((Calc_Base!$E$4:$BL$4<=Org!$B$5)*Calc_Base!$E$66:$BL$66))<0.005,ABS(Calc_Base!$C$65-SUMPRODUCT((Calc_Base!$E$4:$BL$4<=Org!$B$5)*Calc_Base!$E$65:$BL$65))<0.005,ABS(Calc_Base!$C$93-SUMPRODUCT((Calc_Base!$E$4:$BL$4<=Org!$B$5)*Calc_Base!$E$93:$BL$93))<0.005,ABS(Calc_Base!$C$92-SUMPRODUCT((Calc_Base!$E$4:$BL$4<=Org!$B$5)*Calc_Base!$E$92:$BL$92))<0.005,ABS(Calc_Base!$C$120-SUMPRODUCT((Calc_Base!$E$4:$BL$4<=Org!$B$5)*Calc_Base!$E$120:$BL$120))<0.005,ABS(Calc_Base!$C$119-SUMPRODUCT((Calc_Base!$E$4:$BL$4<=Org!$B$5)*Calc_Base!$E$119:$BL$119))<0.005),"PASS","FAIL") -> PASS | D14: Each team's total equals the sum of its in-horizon months (a check that would have caught the 60-month total)
A15: 12 | B15: Every price ID used exists exactly once in the PriceBook (added in Phase 6) | C15: =IF(SUM(C59:G70)+SUM(C71:D71)+C72=0,"PASS","FAIL") -> PASS | D15: No mistyped, missing or duplicate ID; a missing ID would otherwise price silently at zero
B16: Overall | C16: =IF(COUNTIF(C4:C15,"PASS")=12,"ALL 12 PASS","CHECK: "&(12-COUNTIF(C4:C15,"PASS"))&" failing") -> ALL 12 PASS
A20: Support for test 1: allocation under every rule and shape (Base scenario)
A21: Shape | B21: Rule | C21: Team 1 | D21: Team 2 | E21: Team 3 | F21: Team 4 | G21: Team 5 | H21: Unallocated | I21: Sum | J21: Effective hub | K21: Difference | L21: OK
A22: Centralized | B22: Usage-proportional | C22: =Calc_Base!$B$165*Calc_Base!$B$162/(Calc_Base!$B$162+Calc_Base!$C$162+Calc_Base!$D$162+Calc_Base!$E$162+Calc_Base!$F$162) -> 1052885.2 | D22: =Calc_Base!$B$165*Calc_Base!$C$162/(Calc_Base!$B$162+Calc_Base!$C$162+Calc_Base!$D$162+Calc_Base!$E$162+Calc_Base!$F$162) -> 1285113.6 | E22: =Calc_Base!$B$165*Calc_Base!$D$162/(Calc_Base!$B$162+Calc_Base!$C$162+Calc_Base!$D$162+Calc_Base!$E$162+Calc_Base!$F$162) -> 378316.96 | F22: =Calc_Base!$B$165*Calc_Base!$E$162/(Calc_Base!$B$162+Calc_Base!$C$162+Calc_Base!$D$162+Calc_Base!$E$162+Calc_Base!$F$162) -> 117336.46 | G22: =Calc_Base!$B$165*Calc_Base!$F$162/(Calc_Base!$B$162+Calc_Base!$C$162+Calc_Base!$D$162+Calc_Base!$E$162+Calc_Base!$F$162) -> 701923.46 | H22: =0 -> 0 | I22: =SUM(C22:H22) -> 3535575.7 | J22: =Calc_Base!$B$165 -> 3535575.7 | K22: =I22-J22 -> 0 | L22: =IF(ABS(K22)<0.005,"OK","BAD") -> OK
A23: Centralized | B23: Headcount proxy | C23: =Calc_Base!$B$165*Calc_Base!$B$163/(Calc_Base!$B$163+Calc_Base!$C$163+Calc_Base!$D$163+Calc_Base!$E$163+Calc_Base!$F$163) -> 1890682.2 | D23: =Calc_Base!$B$165*Calc_Base!$C$163/(Calc_Base!$B$163+Calc_Base!$C$163+Calc_Base!$D$163+Calc_Base!$E$163+Calc_Base!$F$163) -> 252090.96 | E23: =Calc_Base!$B$165*Calc_Base!$D$163/(Calc_Base!$B$163+Calc_Base!$C$163+Calc_Base!$D$163+Calc_Base!$E$163+Calc_Base!$F$163) -> 37813.644 | F23: =Calc_Base!$B$165*Calc_Base!$E$163/(Calc_Base!$B$163+Calc_Base!$C$163+Calc_Base!$D$163+Calc_Base!$E$163+Calc_Base!$F$163) -> 94534.109 | G23: =Calc_Base!$B$165*Calc_Base!$F$163/(Calc_Base!$B$163+Calc_Base!$C$163+Calc_Base!$D$163+Calc_Base!$E$163+Calc_Base!$F$163) -> 1260454.8 | H23: =0 -> 0 | I23: =SUM(C23:H23) -> 3535575.7 | J23: =Calc_Base!$B$165 -> 3535575.7 | K23: =I23-J23 -> 0 | L23: =IF(ABS(K23)<0.005,"OK","BAD") -> OK
A24: Centralized | B24: Even split | C24: =IF(Org!$B$18=0,0,Calc_Base!$B$165*Teams!$C$5/Org!$B$18) -> 707115.14 | D24: =IF(Org!$B$18=0,0,Calc_Base!$B$165*Teams!$D$5/Org!$B$18) -> 707115.14 | E24: =IF(Org!$B$18=0,0,Calc_Base!$B$165*Teams!$E$5/Org!$B$18) -> 707115.14 | F24: =IF(Org!$B$18=0,0,Calc_Base!$B$165*Teams!$F$5/Org!$B$18) -> 707115.14 | G24: =IF(Org!$B$18=0,0,Calc_Base!$B$165*Teams!$G$5/Org!$B$18) -> 707115.14 | H24: =0 -> 0 | I24: =SUM(C24:H24) -> 3535575.7 | J24: =Calc_Base!$B$165 -> 3535575.7 | K24: =I24-J24 -> 0 | L24: =IF(ABS(K24)<0.005,"OK","BAD") -> OK
A25: Centralized | B25: Central budget | C25: =0 -> 0 | D25: =0 -> 0 | E25: =0 -> 0 | F25: =0 -> 0 | G25: =0 -> 0 | H25: =Calc_Base!$B$165 -> 3535575.7 | I25: =SUM(C25:H25) -> 3535575.7 | J25: =Calc_Base!$B$165 -> 3535575.7 | K25: =I25-J25 -> 0 | L25: =IF(ABS(K25)<0.005,"OK","BAD") -> OK
A26: Federated | B26: Usage-proportional | C26: =Calc_Base!$B$165*Calc_Base!$B$166*Teams!$C$5 -> 1767787.8 | D26: =Calc_Base!$B$165*Calc_Base!$B$166*Teams!$D$5 -> 1767787.8 | E26: =Calc_Base!$B$165*Calc_Base!$B$166*Teams!$E$5 -> 1767787.8 | F26: =Calc_Base!$B$165*Calc_Base!$B$166*Teams!$F$5 -> 1767787.8 | G26: =Calc_Base!$B$165*Calc_Base!$B$166*Teams!$G$5 -> 1767787.8 | H26: =0 -> 0 | I26: =SUM(C26:H26) -> 8838939.2 | J26: =Calc_Base!$B$165*Org!$B$18*Calc_Base!$B$166 -> 8838939.2 | K26: =I26-J26 -> 0 | L26: =IF(ABS(K26)<0.005,"OK","BAD") -> OK
A27: Federated | B27: Headcount proxy | C27: =Calc_Base!$B$165*Calc_Base!$B$166*Teams!$C$5 -> 1767787.8 | D27: =Calc_Base!$B$165*Calc_Base!$B$166*Teams!$D$5 -> 1767787.8 | E27: =Calc_Base!$B$165*Calc_Base!$B$166*Teams!$E$5 -> 1767787.8 | F27: =Calc_Base!$B$165*Calc_Base!$B$166*Teams!$F$5 -> 1767787.8 | G27: =Calc_Base!$B$165*Calc_Base!$B$166*Teams!$G$5 -> 1767787.8 | H27: =0 -> 0 | I27: =SUM(C27:H27) -> 8838939.2 | J27: =Calc_Base!$B$165*Org!$B$18*Calc_Base!$B$166 -> 8838939.2 | K27: =I27-J27 -> 0 | L27: =IF(ABS(K27)<0.005,"OK","BAD") -> OK
A28: Federated | B28: Even split | C28: =Calc_Base!$B$165*Calc_Base!$B$166*Teams!$C$5 -> 1767787.8 | D28: =Calc_Base!$B$165*Calc_Base!$B$166*Teams!$D$5 -> 1767787.8 | E28: =Calc_Base!$B$165*Calc_Base!$B$166*Teams!$E$5 -> 1767787.8 | F28: =Calc_Base!$B$165*Calc_Base!$B$166*Teams!$F$5 -> 1767787.8 | G28: =Calc_Base!$B$165*Calc_Base!$B$166*Teams!$G$5 -> 1767787.8 | H28: =0 -> 0 | I28: =SUM(C28:H28) -> 8838939.2 | J28: =Calc_Base!$B$165*Org!$B$18*Calc_Base!$B$166 -> 8838939.2 | K28: =I28-J28 -> 0 | L28: =IF(ABS(K28)<0.005,"OK","BAD") -> OK
A29: Federated | B29: Central budget | C29: =Calc_Base!$B$165*Calc_Base!$B$166*Teams!$C$5 -> 1767787.8 | D29: =Calc_Base!$B$165*Calc_Base!$B$166*Teams!$D$5 -> 1767787.8 | E29: =Calc_Base!$B$165*Calc_Base!$B$166*Teams!$E$5 -> 1767787.8 | F29: =Calc_Base!$B$165*Calc_Base!$B$166*Teams!$F$5 -> 1767787.8 | G29: =Calc_Base!$B$165*Calc_Base!$B$166*Teams!$G$5 -> 1767787.8 | H29: =0 -> 0 | I29: =SUM(C29:H29) -> 8838939.2 | J29: =Calc_Base!$B$165*Org!$B$18*Calc_Base!$B$166 -> 8838939.2 | K29: =I29-J29 -> 0 | L29: =IF(ABS(K29)<0.005,"OK","BAD") -> OK
A30: Hub-and-spoke | B30: Usage-proportional | C30: =Calc_Base!$B$165*Calc_Base!$B$162/(Calc_Base!$B$162+Calc_Base!$C$162+Calc_Base!$D$162+Calc_Base!$E$162+Calc_Base!$F$162) -> 1052885.2 | D30: =Calc_Base!$B$165*Calc_Base!$C$162/(Calc_Base!$B$162+Calc_Base!$C$162+Calc_Base!$D$162+Calc_Base!$E$162+Calc_Base!$F$162) -> 1285113.6 | E30: =Calc_Base!$B$165*Calc_Base!$D$162/(Calc_Base!$B$162+Calc_Base!$C$162+Calc_Base!$D$162+Calc_Base!$E$162+Calc_Base!$F$162) -> 378316.96 | F30: =Calc_Base!$B$165*Calc_Base!$E$162/(Calc_Base!$B$162+Calc_Base!$C$162+Calc_Base!$D$162+Calc_Base!$E$162+Calc_Base!$F$162) -> 117336.46 | G30: =Calc_Base!$B$165*Calc_Base!$F$162/(Calc_Base!$B$162+Calc_Base!$C$162+Calc_Base!$D$162+Calc_Base!$E$162+Calc_Base!$F$162) -> 701923.46 | H30: =0 -> 0 | I30: =SUM(C30:H30) -> 3535575.7 | J30: =Calc_Base!$B$165 -> 3535575.7 | K30: =I30-J30 -> 0 | L30: =IF(ABS(K30)<0.005,"OK","BAD") -> OK
A31: Hub-and-spoke | B31: Headcount proxy | C31: =Calc_Base!$B$165*Calc_Base!$B$163/(Calc_Base!$B$163+Calc_Base!$C$163+Calc_Base!$D$163+Calc_Base!$E$163+Calc_Base!$F$163) -> 1890682.2 | D31: =Calc_Base!$B$165*Calc_Base!$C$163/(Calc_Base!$B$163+Calc_Base!$C$163+Calc_Base!$D$163+Calc_Base!$E$163+Calc_Base!$F$163) -> 252090.96 | E31: =Calc_Base!$B$165*Calc_Base!$D$163/(Calc_Base!$B$163+Calc_Base!$C$163+Calc_Base!$D$163+Calc_Base!$E$163+Calc_Base!$F$163) -> 37813.644 | F31: =Calc_Base!$B$165*Calc_Base!$E$163/(Calc_Base!$B$163+Calc_Base!$C$163+Calc_Base!$D$163+Calc_Base!$E$163+Calc_Base!$F$163) -> 94534.109 | G31: =Calc_Base!$B$165*Calc_Base!$F$163/(Calc_Base!$B$163+Calc_Base!$C$163+Calc_Base!$D$163+Calc_Base!$E$163+Calc_Base!$F$163) -> 1260454.8 | H31: =0 -> 0 | I31: =SUM(C31:H31) -> 3535575.7 | J31: =Calc_Base!$B$165 -> 3535575.7 | K31: =I31-J31 -> 0 | L31: =IF(ABS(K31)<0.005,"OK","BAD") -> OK
A32: Hub-and-spoke | B32: Even split | C32: =IF(Org!$B$18=0,0,Calc_Base!$B$165*Teams!$C$5/Org!$B$18) -> 707115.14 | D32: =IF(Org!$B$18=0,0,Calc_Base!$B$165*Teams!$D$5/Org!$B$18) -> 707115.14 | E32: =IF(Org!$B$18=0,0,Calc_Base!$B$165*Teams!$E$5/Org!$B$18) -> 707115.14 | F32: =IF(Org!$B$18=0,0,Calc_Base!$B$165*Teams!$F$5/Org!$B$18) -> 707115.14 | G32: =IF(Org!$B$18=0,0,Calc_Base!$B$165*Teams!$G$5/Org!$B$18) -> 707115.14 | H32: =0 -> 0 | I32: =SUM(C32:H32) -> 3535575.7 | J32: =Calc_Base!$B$165 -> 3535575.7 | K32: =I32-J32 -> 0 | L32: =IF(ABS(K32)<0.005,"OK","BAD") -> OK
A33: Hub-and-spoke | B33: Central budget | C33: =0 -> 0 | D33: =0 -> 0 | E33: =0 -> 0 | F33: =0 -> 0 | G33: =0 -> 0 | H33: =Calc_Base!$B$165 -> 3535575.7 | I33: =SUM(C33:H33) -> 3535575.7 | J33: =Calc_Base!$B$165 -> 3535575.7 | K33: =I33-J33 -> 0 | L33: =IF(ABS(K33)<0.005,"OK","BAD") -> OK
A35: Support for test 2: amortisation of one-time costs by month
A36: Month | B36: 1 | C36: 2 | D36: 3 | E36: 4 | F36: 5 | G36: 6 | H36: 7 | I36: 8 | J36: 9 | K36: 10 | L36: 11 | M36: 12 | N36: 13 | O36: 14 | P36: 15 | Q36: 16 | R36: 17 | S36: 18 | T36: 19 | U36: 20 | V36: 21 | W36: 22 | X36: 23 | Y36: 24 | Z36: 25 | AA36: 26 | AB36: 27 | AC36: 28 | AD36: 29 | AE36: 30 | AF36: 31 | AG36: 32 | AH36: 33 | AI36: 34 | AJ36: 35 | AK36: 36 | AL36: 37 | AM36: 38 | AN36: 39 | AO36: 40 | AP36: 41 | AQ36: 42 | AR36: 43 | AS36: 44 | AT36: 45 | AU36: 46 | AV36: 47 | AW36: 48 | AX36: 49 | AY36: 50 | AZ36: 51 | BA36: 52 | BB36: 53 | BC36: 54 | BD36: 55 | BE36: 56 | BF36: 57 | BG36: 58 | BH36: 59 | BI36: 60
A37: Amortised cost | B37: =IF(B36<=Org!$B$5,(Calc_Base!$D$175+Calc_Base!$D$176)/Org!$B$5,0) -> 57875.658 | C37: =IF(C36<=Org!$B$5,(Calc_Base!$D$175+Calc_Base!$D$176)/Org!$B$5,0) -> 57875.658 | D37: =IF(D36<=Org!$B$5,(Calc_Base!$D$175+Calc_Base!$D$176)/Org!$B$5,0) -> 57875.658 | E37: =IF(E36<=Org!$B$5,(Calc_Base!$D$175+Calc_Base!$D$176)/Org!$B$5,0) -> 57875.658 | F37: =IF(F36<=Org!$B$5,(Calc_Base!$D$175+Calc_Base!$D$176)/Org!$B$5,0) -> 57875.658 | G37: =IF(G36<=Org!$B$5,(Calc_Base!$D$175+Calc_Base!$D$176)/Org!$B$5,0) -> 57875.658 | H37: =IF(H36<=Org!$B$5,(Calc_Base!$D$175+Calc_Base!$D$176)/Org!$B$5,0) -> 57875.658 | I37: =IF(I36<=Org!$B$5,(Calc_Base!$D$175+Calc_Base!$D$176)/Org!$B$5,0) -> 57875.658 | ... BI37: =IF(BI36<=Org!$B$5,(Calc_Base!$D$175+Calc_Base!$D$176)/Org!$B$5,0) -> 0
A38: One-time total, and sum of amortisation | B38: =(Calc_Base!$D$175+Calc_Base!$D$176) -> 2083523.7 | C38: =SUM(B37:BI37) -> 2083523.7
A40: Support for test 4: variable cost in months with zero outcomes (Base)
A41: Team | B41: Variable cost in zero-outcome months | C41: Zero-outcome months in horizon
A42: =Teams!$C$4 -> Corporate knowledge assistant (conservative calibration) | B42: =SUMPRODUCT((Calc_Base!$E$12:$BL$12=0)*(Calc_Base!$E$14:$BL$14+Calc_Base!$E$15:$BL$15+Calc_Base!$E$16:$BL$16+Calc_Base!$E$22:$BL$22)) -> 0 | C42: =SUMPRODUCT((Calc_Base!$E$12:$BL$12=0)*(Calc_Base!$E$5:$BL$5=1)) -> 0
A43: =Teams!$D$4 -> Engineering assistant | B43: =SUMPRODUCT((Calc_Base!$E$39:$BL$39=0)*(Calc_Base!$E$41:$BL$41+Calc_Base!$E$42:$BL$42+Calc_Base!$E$43:$BL$43+Calc_Base!$E$49:$BL$49)) -> 0 | C43: =SUMPRODUCT((Calc_Base!$E$39:$BL$39=0)*(Calc_Base!$E$5:$BL$5=1)) -> 0
A44: =Teams!$E$4 -> Customer service agent | B44: =SUMPRODUCT((Calc_Base!$E$66:$BL$66=0)*(Calc_Base!$E$68:$BL$68+Calc_Base!$E$69:$BL$69+Calc_Base!$E$70:$BL$70+Calc_Base!$E$76:$BL$76)) -> 0 | C44: =SUMPRODUCT((Calc_Base!$E$66:$BL$66=0)*(Calc_Base!$E$5:$BL$5=1)) -> 1
A45: =Teams!$F$4 -> Regulated document review | B45: =SUMPRODUCT((Calc_Base!$E$93:$BL$93=0)*(Calc_Base!$E$95:$BL$95+Calc_Base!$E$96:$BL$96+Calc_Base!$E$97:$BL$97+Calc_Base!$E$103:$BL$103)) -> 0 | C45: =SUMPRODUCT((Calc_Base!$E$93:$BL$93=0)*(Calc_Base!$E$5:$BL$5=1)) -> 2
A46: =Teams!$G$4 -> Sales assistant (published-range calibration) | B46: =SUMPRODUCT((Calc_Base!$E$120:$BL$120=0)*(Calc_Base!$E$122:$BL$122+Calc_Base!$E$123:$BL$123+Calc_Base!$E$124:$BL$124+Calc_Base!$E$130:$BL$130)) -> 0 | C46: =SUMPRODUCT((Calc_Base!$E$120:$BL$120=0)*(Calc_Base!$E$5:$BL$5=1)) -> 0
A47: Hub cost in month 1 (fixed cost that remains) | B47: =Calc_Base!$E$158 -> 91515.8
A49: Support for test 6: shape changes the hub lines, not the variable inference cost
A50: Variable inference cost (tokens, vendor, tools), both shapes | B50: =Calc_Base!$C$14+Calc_Base!$C$15+Calc_Base!$C$16+Calc_Base!$C$41+Calc_Base!$C$42+Calc_Base!$C$43+Calc_Base!$C$68+Calc_Base!$C$69+Calc_Base!$C$70+Calc_Base!$C$95+Calc_Base!$C$96+Calc_Base!$C$97+Calc_Base!$C$122+Calc_Base!$C$123+Calc_Base!$C$124 -> 2092931 | C50: =Calc_Base!$C$14+Calc_Base!$C$15+Calc_Base!$C$16+Calc_Base!$C$41+Calc_Base!$C$42+Calc_Base!$C$43+Calc_Base!$C$68+Calc_Base!$C$69+Calc_Base!$C$70+Calc_Base!$C$95+Calc_Base!$C$96+Calc_Base!$C$97+Calc_Base!$C$122+Calc_Base!$C$123+Calc_Base!$C$124 -> 2092931
A51: Effective hub cost: Centralized, Federated | B51: =Calc_Base!$B$165 -> 3535575.7 | C51: =Calc_Base!$B$165*Org!$B$18*Calc_Base!$B$166 -> 8838939.2
A52: The build script also flips the shape in the workbook, recalculates and compares with the reference model (build/verify.py).
A54: Support for test 9: seat price divided by active share
A55: Fixture: seat 30, active share 50%, expected 60 | B55: 30 | C55: 0.5 | D55: 60 | E55: =B55/C55 -> 60
A56: Live, Team 1 at the last horizon month: seat cost / active users, and blended seat / plateau share | B56: =IF(INDEX(Calc_Base!$E$11:$BL$11,Org!$B$5)=0,0,INDEX(Calc_Base!$E$13:$BL$13,Org!$B$5)/INDEX(Calc_Base!$E$11:$BL$11,Org!$B$5)) -> 46.666667 | C56: =Teams!$C$66/Teams!$C$19 -> 46.666667 | D56: =INDEX(Calc_Base!$E$9:$BL$9,Org!$B$5) -> 1
A58: Support for test 12: every price ID used by a team or the hub exists exactly once in the PriceBook (0 = fine)
A59: Seat price (price book ID) | C59: =IF(Teams!$C$9="",0,IF(COUNTIF(PriceBook!$A$4:$A$203,Teams!$C$9)=1,0,1)) -> 0 | D59: =IF(Teams!$D$9="",0,IF(COUNTIF(PriceBook!$A$4:$A$203,Teams!$D$9)=1,0,1)) -> 0 | E59: =IF(Teams!$E$9="",0,IF(COUNTIF(PriceBook!$A$4:$A$203,Teams!$E$9)=1,0,1)) -> 0 | F59: =IF(Teams!$F$9="",0,IF(COUNTIF(PriceBook!$A$4:$A$203,Teams!$F$9)=1,0,1)) -> 0 | G59: =IF(Teams!$G$9="",0,IF(COUNTIF(PriceBook!$A$4:$A$203,Teams!$G$9)=1,0,1)) -> 0
A60: Premium seat price (price book ID) | C60: =IF(Teams!$C$10="",0,IF(COUNTIF(PriceBook!$A$4:$A$203,Teams!$C$10)=1,0,1)) -> 0 | D60: =IF(Teams!$D$10="",0,IF(COUNTIF(PriceBook!$A$4:$A$203,Teams!$D$10)=1,0,1)) -> 0 | E60: =IF(Teams!$E$10="",0,IF(COUNTIF(PriceBook!$A$4:$A$203,Teams!$E$10)=1,0,1)) -> 0 | F60: =IF(Teams!$F$10="",0,IF(COUNTIF(PriceBook!$A$4:$A$203,Teams!$F$10)=1,0,1)) -> 0 | G60: =IF(Teams!$G$10="",0,IF(COUNTIF(PriceBook!$A$4:$A$203,Teams!$G$10)=1,0,1)) -> 0
A61: Vendor per-outcome price (price book ID, or none) | C61: =IF(Teams!$C$15="",0,IF(COUNTIF(PriceBook!$A$4:$A$203,Teams!$C$15)=1,0,1)) -> 0 | D61: =IF(Teams!$D$15="",0,IF(COUNTIF(PriceBook!$A$4:$A$203,Teams!$D$15)=1,0,1)) -> 0 | E61: =IF(Teams!$E$15="",0,IF(COUNTIF(PriceBook!$A$4:$A$203,Teams!$E$15)=1,0,1)) -> 0 | F61: =IF(Teams!$F$15="",0,IF(COUNTIF(PriceBook!$A$4:$A$203,Teams!$F$15)=1,0,1)) -> 0 | G61: =IF(Teams!$G$15="",0,IF(COUNTIF(PriceBook!$A$4:$A$203,Teams!$G$15)=1,0,1)) -> 0
A62: Main model (price book ID) | C62: =IF(Teams!$C$26="",0,IF(COUNTIF(PriceBook!$A$4:$A$203,Teams!$C$26)=1,0,1)) -> 0 | D62: =IF(Teams!$D$26="",0,IF(COUNTIF(PriceBook!$A$4:$A$203,Teams!$D$26)=1,0,1)) -> 0 | E62: =IF(Teams!$E$26="",0,IF(COUNTIF(PriceBook!$A$4:$A$203,Teams!$E$26)=1,0,1)) -> 0 | F62: =IF(Teams!$F$26="",0,IF(COUNTIF(PriceBook!$A$4:$A$203,Teams!$F$26)=1,0,1)) -> 0 | G62: =IF(Teams!$G$26="",0,IF(COUNTIF(PriceBook!$A$4:$A$203,Teams!$G$26)=1,0,1)) -> 0
A63: Cheaper model (price book ID) | C63: =IF(Teams!$C$27="",0,IF(COUNTIF(PriceBook!$A$4:$A$203,Teams!$C$27)=1,0,1)) -> 0 | D63: =IF(Teams!$D$27="",0,IF(COUNTIF(PriceBook!$A$4:$A$203,Teams!$D$27)=1,0,1)) -> 0 | E63: =IF(Teams!$E$27="",0,IF(COUNTIF(PriceBook!$A$4:$A$203,Teams!$E$27)=1,0,1)) -> 0 | F63: =IF(Teams!$F$27="",0,IF(COUNTIF(PriceBook!$A$4:$A$203,Teams!$F$27)=1,0,1)) -> 0 | G63: =IF(Teams!$G$27="",0,IF(COUNTIF(PriceBook!$A$4:$A$203,Teams!$G$27)=1,0,1)) -> 0
A64: Tool price (price book ID) | C64: =IF(Teams!$C$38="",0,IF(COUNTIF(PriceBook!$A$4:$A$203,Teams!$C$38)=1,0,1)) -> 0 | D64: =IF(Teams!$D$38="",0,IF(COUNTIF(PriceBook!$A$4:$A$203,Teams!$D$38)=1,0,1)) -> 0 | E64: =IF(Teams!$E$38="",0,IF(COUNTIF(PriceBook!$A$4:$A$203,Teams!$E$38)=1,0,1)) -> 0 | F64: =IF(Teams!$F$38="",0,IF(COUNTIF(PriceBook!$A$4:$A$203,Teams!$F$38)=1,0,1)) -> 0 | G64: =IF(Teams!$G$38="",0,IF(COUNTIF(PriceBook!$A$4:$A$203,Teams!$G$38)=1,0,1)) -> 0
A65: Guardrail price (price book ID) | C65: =IF(Teams!$C$40="",0,IF(COUNTIF(PriceBook!$A$4:$A$203,Teams!$C$40)=1,0,1)) -> 0 | D65: =IF(Teams!$D$40="",0,IF(COUNTIF(PriceBook!$A$4:$A$203,Teams!$D$40)=1,0,1)) -> 0 | E65: =IF(Teams!$E$40="",0,IF(COUNTIF(PriceBook!$A$4:$A$203,Teams!$E$40)=1,0,1)) -> 0 | F65: =IF(Teams!$F$40="",0,IF(COUNTIF(PriceBook!$A$4:$A$203,Teams!$F$40)=1,0,1)) -> 0 | G65: =IF(Teams!$G$40="",0,IF(COUNTIF(PriceBook!$A$4:$A$203,Teams!$G$40)=1,0,1)) -> 0
A66: Parsing price (price book ID) | C66: =IF(Teams!$C$46="",0,IF(COUNTIF(PriceBook!$A$4:$A$203,Teams!$C$46)=1,0,1)) -> 0 | D66: =IF(Teams!$D$46="",0,IF(COUNTIF(PriceBook!$A$4:$A$203,Teams!$D$46)=1,0,1)) -> 0 | E66: =IF(Teams!$E$46="",0,IF(COUNTIF(PriceBook!$A$4:$A$203,Teams!$E$46)=1,0,1)) -> 0 | F66: =IF(Teams!$F$46="",0,IF(COUNTIF(PriceBook!$A$4:$A$203,Teams!$F$46)=1,0,1)) -> 0 | G66: =IF(Teams!$G$46="",0,IF(COUNTIF(PriceBook!$A$4:$A$203,Teams!$G$46)=1,0,1)) -> 0
A67: Embedding price (price book ID) | C67: =IF(Teams!$C$48="",0,IF(COUNTIF(PriceBook!$A$4:$A$203,Teams!$C$48)=1,0,1)) -> 0 | D67: =IF(Teams!$D$48="",0,IF(COUNTIF(PriceBook!$A$4:$A$203,Teams!$D$48)=1,0,1)) -> 0 | E67: =IF(Teams!$E$48="",0,IF(COUNTIF(PriceBook!$A$4:$A$203,Teams!$E$48)=1,0,1)) -> 0 | F67: =IF(Teams!$F$48="",0,IF(COUNTIF(PriceBook!$A$4:$A$203,Teams!$F$48)=1,0,1)) -> 0 | G67: =IF(Teams!$G$48="",0,IF(COUNTIF(PriceBook!$A$4:$A$203,Teams!$G$48)=1,0,1)) -> 0
A68: Index plan minimum (price book ID) | C68: =IF(Teams!$C$52="",0,IF(COUNTIF(PriceBook!$A$4:$A$203,Teams!$C$52)=1,0,1)) -> 0 | D68: =IF(Teams!$D$52="",0,IF(COUNTIF(PriceBook!$A$4:$A$203,Teams!$D$52)=1,0,1)) -> 0 | E68: =IF(Teams!$E$52="",0,IF(COUNTIF(PriceBook!$A$4:$A$203,Teams!$E$52)=1,0,1)) -> 0 | F68: =IF(Teams!$F$52="",0,IF(COUNTIF(PriceBook!$A$4:$A$203,Teams!$F$52)=1,0,1)) -> 0 | G68: =IF(Teams!$G$52="",0,IF(COUNTIF(PriceBook!$A$4:$A$203,Teams!$G$52)=1,0,1)) -> 0
A69: Storage price (price book ID) | C69: =IF(Teams!$C$53="",0,IF(COUNTIF(PriceBook!$A$4:$A$203,Teams!$C$53)=1,0,1)) -> 0 | D69: =IF(Teams!$D$53="",0,IF(COUNTIF(PriceBook!$A$4:$A$203,Teams!$D$53)=1,0,1)) -> 0 | E69: =IF(Teams!$E$53="",0,IF(COUNTIF(PriceBook!$A$4:$A$203,Teams!$E$53)=1,0,1)) -> 0 | F69: =IF(Teams!$F$53="",0,IF(COUNTIF(PriceBook!$A$4:$A$203,Teams!$F$53)=1,0,1)) -> 0 | G69: =IF(Teams!$G$53="",0,IF(COUNTIF(PriceBook!$A$4:$A$203,Teams!$G$53)=1,0,1)) -> 0
A70: Read price (price book ID) | C70: =IF(Teams!$C$54="",0,IF(COUNTIF(PriceBook!$A$4:$A$203,Teams!$C$54)=1,0,1)) -> 0 | D70: =IF(Teams!$D$54="",0,IF(COUNTIF(PriceBook!$A$4:$A$203,Teams!$D$54)=1,0,1)) -> 0 | E70: =IF(Teams!$E$54="",0,IF(COUNTIF(PriceBook!$A$4:$A$203,Teams!$E$54)=1,0,1)) -> 0 | F70: =IF(Teams!$F$54="",0,IF(COUNTIF(PriceBook!$A$4:$A$203,Teams!$F$54)=1,0,1)) -> 0 | G70: =IF(Teams!$G$54="",0,IF(COUNTIF(PriceBook!$A$4:$A$203,Teams!$G$54)=1,0,1)) -> 0
A71: Hub IDs (monitoring plan, overage) | C71: =IF(COUNTIF(PriceBook!$A$4:$A$203,"PL_LANGFUSE_PRO")=1,0,1) -> 0 | D71: =IF(COUNTIF(PriceBook!$A$4:$A$203,"U_LANGFUSE_OVER")=1,0,1) -> 0
A72: Duplicate IDs in the PriceBook | C72: =SUMPRODUCT((PriceBook!$A$4:$A$203<>"")*(COUNTIF(PriceBook!$A$4:$A$203,PriceBook!$A$4:$A$203)>1)) -> 0

Sheet Calc_Low
A1: Calc: Low-cost scenario
A2: Monthly grid. Month 0 holds one-time costs; months 1 to 60 are masked by the horizon. All values are formulas.
A4: Month | B4: Tag | C4: Total | D4: 0 | E4: =D4+1 -> 1 | F4: =E4+1 -> 2 | G4: =F4+1 -> 3 | H4: =G4+1 -> 4 | I4: =H4+1 -> 5 | J4: =I4+1 -> 6 | K4: =J4+1 -> 7 | L4: =K4+1 -> 8 | ... BL4: =BK4+1 -> 60
A5: In horizon (1/0) | E5: =IF(E$4<=Org!$B$5,1,0) -> 1 | F5: =IF(F$4<=Org!$B$5,1,0) -> 1 | G5: =IF(G$4<=Org!$B$5,1,0) -> 1 | H5: =IF(H$4<=Org!$B$5,1,0) -> 1 | I5: =IF(I$4<=Org!$B$5,1,0) -> 1 | J5: =IF(J$4<=Org!$B$5,1,0) -> 1 | K5: =IF(K$4<=Org!$B$5,1,0) -> 1 | L5: =IF(L$4<=Org!$B$5,1,0) -> 1 | ... BL5: =IF(BL$4<=Org!$B$5,1,0) -> 0
A8: =Teams!$C$4 -> Corporate knowledge assistant (conservative calibration) | B8: Token cost per outcome: | C8: =(Teams!$C$29*(1-Teams!$C$31)*Params!$D$39*Params!$D$21*IF(Teams!$C$36="Yes",Params!$D$22,1)*Teams!$C$68*Teams!$C$70+Teams!$C$30*(1-Teams!$C$31)*Params!$D$39*Params!$D$21*IF(Teams!$C$36="Yes",Params!$D$22,1)*Teams!$C$69)/1000000*Teams!$C$71*Teams!$C$35 -> 0.00585795
A9: Ramp factor | E9: =IF(E$4<Teams!$C$80,0,IF(Teams!$C$22="S",MIN(1,(E$4-Teams!$C$80+1)/Teams!$C$21)^2*(3-2*MIN(1,(E$4-Teams!$C$80+1)/Teams!$C$21)),MIN(1,(E$4-Teams!$C$80+1)/Teams!$C$21))) -> 0.074074074 | F9: =IF(F$4<Teams!$C$80,0,IF(Teams!$C$22="S",MIN(1,(F$4-Teams!$C$80+1)/Teams!$C$21)^2*(3-2*MIN(1,(F$4-Teams!$C$80+1)/Teams!$C$21)),MIN(1,(F$4-Teams!$C$80+1)/Teams!$C$21))) -> 0.25925926 | G9: =IF(G$4<Teams!$C$80,0,IF(Teams!$C$22="S",MIN(1,(G$4-Teams!$C$80+1)/Teams!$C$21)^2*(3-2*MIN(1,(G$4-Teams!$C$80+1)/Teams!$C$21)),MIN(1,(G$4-Teams!$C$80+1)/Teams!$C$21))) -> 0.5 | H9: =IF(H$4<Teams!$C$80,0,IF(Teams!$C$22="S",MIN(1,(H$4-Teams!$C$80+1)/Teams!$C$21)^2*(3-2*MIN(1,(H$4-Teams!$C$80+1)/Teams!$C$21)),MIN(1,(H$4-Teams!$C$80+1)/Teams!$C$21))) -> 0.74074074 | I9: =IF(I$4<Teams!$C$80,0,IF(Teams!$C$22="S",MIN(1,(I$4-Teams!$C$80+1)/Teams!$C$21)^2*(3-2*MIN(1,(I$4-Teams!$C$80+1)/Teams!$C$21)),MIN(1,(I$4-Teams!$C$80+1)/Teams!$C$21))) -> 0.92592593 | J9: =IF(J$4<Teams!$C$80,0,IF(Teams!$C$22="S",MIN(1,(J$4-Teams!$C$80+1)/Teams!$C$21)^2*(3-2*MIN(1,(J$4-Teams!$C$80+1)/Teams!$C$21)),MIN(1,(J$4-Teams!$C$80+1)/Teams!$C$21))) -> 1 | K9: =IF(K$4<Teams!$C$80,0,IF(Teams!$C$22="S",MIN(1,(K$4-Teams!$C$80+1)/Teams!$C$21)^2*(3-2*MIN(1,(K$4-Teams!$C$80+1)/Teams!$C$21)),MIN(1,(K$4-Teams!$C$80+1)/Teams!$C$21))) -> 1 | L9: =IF(L$4<Teams!$C$80,0,IF(Teams!$C$22="S",MIN(1,(L$4-Teams!$C$80+1)/Teams!$C$21)^2*(3-2*MIN(1,(L$4-Teams!$C$80+1)/Teams!$C$21)),MIN(1,(L$4-Teams!$C$80+1)/Teams!$C$21))) -> 1 | ... BL9: =IF(BL$4<Teams!$C$80,0,IF(Teams!$C$22="S",MIN(1,(BL$4-Teams!$C$80+1)/Teams!$C$21)^2*(3-2*MIN(1,(BL$4-Teams!$C$80+1)/Teams!$C$21)),MIN(1,(BL$4-Teams!$C$80+1)/Teams!$C$21))) -> 1
A10: Licensed users | E10: =IF(E$4>=Teams!$C$80,Teams!$C$18,0) -> 3000 | F10: =IF(F$4>=Teams!$C$80,Teams!$C$18,0) -> 3000 | G10: =IF(G$4>=Teams!$C$80,Teams!$C$18,0) -> 3000 | H10: =IF(H$4>=Teams!$C$80,Teams!$C$18,0) -> 3000 | I10: =IF(I$4>=Teams!$C$80,Teams!$C$18,0) -> 3000 | J10: =IF(J$4>=Teams!$C$80,Teams!$C$18,0) -> 3000 | K10: =IF(K$4>=Teams!$C$80,Teams!$C$18,0) -> 3000 | L10: =IF(L$4>=Teams!$C$80,Teams!$C$18,0) -> 3000 | ... BL10: =IF(BL$4>=Teams!$C$80,Teams!$C$18,0) -> 3000
A11: Active users | C11: =SUMPRODUCT(E11:BL11,E$5:BL$5) -> 60300 | E11: =E10*Teams!$C$19*E9 -> 133.33333 | F11: =F10*Teams!$C$19*F9 -> 466.66667 | G11: =G10*Teams!$C$19*G9 -> 900 | H11: =H10*Teams!$C$19*H9 -> 1333.3333 | I11: =I10*Teams!$C$19*I9 -> 1666.6667 | J11: =J10*Teams!$C$19*J9 -> 1800 | K11: =K10*Teams!$C$19*K9 -> 1800 | L11: =L10*Teams!$C$19*L9 -> 1800 | ... BL11: =BL10*Teams!$C$19*BL9 -> 1800
A12: Outcomes | C12: =SUMPRODUCT(E12:BL12,E$5:BL$5) -> 3618000 | E12: =IF(Teams!$C$23="per user",E11*Teams!$C$24,Teams!$C$25*E9) -> 8000 | F12: =IF(Teams!$C$23="per user",F11*Teams!$C$24,Teams!$C$25*F9) -> 28000 | G12: =IF(Teams!$C$23="per user",G11*Teams!$C$24,Teams!$C$25*G9) -> 54000 | H12: =IF(Teams!$C$23="per user",H11*Teams!$C$24,Teams!$C$25*H9) -> 80000 | I12: =IF(Teams!$C$23="per user",I11*Teams!$C$24,Teams!$C$25*I9) -> 100000 | J12: =IF(Teams!$C$23="per user",J11*Teams!$C$24,Teams!$C$25*J9) -> 108000 | K12: =IF(Teams!$C$23="per user",K11*Teams!$C$24,Teams!$C$25*K9) -> 108000 | L12: =IF(Teams!$C$23="per user",L11*Teams!$C$24,Teams!$C$25*L9) -> 108000 | ... BL12: =IF(Teams!$C$23="per user",BL11*Teams!$C$24,Teams!$C$25*BL9) -> 108000
A13: Seats (CL-21) | B13: A | C13: =SUM(D13:BL13) -> 3024000 | E13: =E$5*Teams!$C$60*E10*Teams!$C$66 -> 84000 | F13: =F$5*Teams!$C$60*F10*Teams!$C$66 -> 84000 | G13: =G$5*Teams!$C$60*G10*Teams!$C$66 -> 84000 | H13: =H$5*Teams!$C$60*H10*Teams!$C$66 -> 84000 | I13: =I$5*Teams!$C$60*I10*Teams!$C$66 -> 84000 | J13: =J$5*Teams!$C$60*J10*Teams!$C$66 -> 84000 | K13: =K$5*Teams!$C$60*K10*Teams!$C$66 -> 84000 | L13: =L$5*Teams!$C$60*L10*Teams!$C$66 -> 84000 | ... BL13: =BL$5*Teams!$C$60*BL10*Teams!$C$66 -> 0
A14: Model tokens incl. retries and agent steps (CL-16, CL-17) | B14: A | C14: =SUM(D14:BL14) -> 0 | E14: =E$5*IF(Teams!$C$61=1,E11*((1-Teams!$C$13)*MAX(0,Teams!$C$72*$C$8-Teams!$C$12)+Teams!$C$13*MAX(0,Teams!$C$73*$C$8-Teams!$C$12)),IF(Teams!$C$62=1,E12*$C$8,0)) -> 0 | F14: =F$5*IF(Teams!$C$61=1,F11*((1-Teams!$C$13)*MAX(0,Teams!$C$72*$C$8-Teams!$C$12)+Teams!$C$13*MAX(0,Teams!$C$73*$C$8-Teams!$C$12)),IF(Teams!$C$62=1,F12*$C$8,0)) -> 0 | G14: =G$5*IF(Teams!$C$61=1,G11*((1-Teams!$C$13)*MAX(0,Teams!$C$72*$C$8-Teams!$C$12)+Teams!$C$13*MAX(0,Teams!$C$73*$C$8-Teams!$C$12)),IF(Teams!$C$62=1,G12*$C$8,0)) -> 0 | H14: =H$5*IF(Teams!$C$61=1,H11*((1-Teams!$C$13)*MAX(0,Teams!$C$72*$C$8-Teams!$C$12)+Teams!$C$13*MAX(0,Teams!$C$73*$C$8-Teams!$C$12)),IF(Teams!$C$62=1,H12*$C$8,0)) -> 0 | I14: =I$5*IF(Teams!$C$61=1,I11*((1-Teams!$C$13)*MAX(0,Teams!$C$72*$C$8-Teams!$C$12)+Teams!$C$13*MAX(0,Teams!$C$73*$C$8-Teams!$C$12)),IF(Teams!$C$62=1,I12*$C$8,0)) -> 0 | J14: =J$5*IF(Teams!$C$61=1,J11*((1-Teams!$C$13)*MAX(0,Teams!$C$72*$C$8-Teams!$C$12)+Teams!$C$13*MAX(0,Teams!$C$73*$C$8-Teams!$C$12)),IF(Teams!$C$62=1,J12*$C$8,0)) -> 0 | K14: =K$5*IF(Teams!$C$61=1,K11*((1-Teams!$C$13)*MAX(0,Teams!$C$72*$C$8-Teams!$C$12)+Teams!$C$13*MAX(0,Teams!$C$73*$C$8-Teams!$C$12)),IF(Teams!$C$62=1,K12*$C$8,0)) -> 0 | L14: =L$5*IF(Teams!$C$61=1,L11*((1-Teams!$C$13)*MAX(0,Teams!$C$72*$C$8-Teams!$C$12)+Teams!$C$13*MAX(0,Teams!$C$73*$C$8-Teams!$C$12)),IF(Teams!$C$62=1,L12*$C$8,0)) -> 0 | ... BL14: =BL$5*IF(Teams!$C$61=1,BL11*((1-Teams!$C$13)*MAX(0,Teams!$C$72*$C$8-Teams!$C$12)+Teams!$C$13*MAX(0,Teams!$C$73*$C$8-Teams!$C$12)),IF(Teams!$C$62=1,BL12*$C$8,0)) -> 0
A15: Vendor per-outcome price (CL-22) | B15: A | C15: =SUM(D15:BL15) -> 0 | E15: =E$5*Teams!$C$63*E12*Teams!$C$67 -> 0 | F15: =F$5*Teams!$C$63*F12*Teams!$C$67 -> 0 | G15: =G$5*Teams!$C$63*G12*Teams!$C$67 -> 0 | H15: =H$5*Teams!$C$63*H12*Teams!$C$67 -> 0 | I15: =I$5*Teams!$C$63*I12*Teams!$C$67 -> 0 | J15: =J$5*Teams!$C$63*J12*Teams!$C$67 -> 0 | K15: =K$5*Teams!$C$63*K12*Teams!$C$67 -> 0 | L15: =L$5*Teams!$C$63*L12*Teams!$C$67 -> 0 | ... BL15: =BL$5*Teams!$C$63*BL12*Teams!$C$67 -> 0
A16: Tool and guardrail calls (CL-18, CL-19) | B16: A | C16: =SUM(D16:BL16) -> 0 | E16: =E$5*Teams!$C$65*E12*Teams!$C$74 -> 0 | F16: =F$5*Teams!$C$65*F12*Teams!$C$74 -> 0 | G16: =G$5*Teams!$C$65*G12*Teams!$C$74 -> 0 | H16: =H$5*Teams!$C$65*H12*Teams!$C$74 -> 0 | I16: =I$5*Teams!$C$65*I12*Teams!$C$74 -> 0 | J16: =J$5*Teams!$C$65*J12*Teams!$C$74 -> 0 | K16: =K$5*Teams!$C$65*K12*Teams!$C$74 -> 0 | L16: =L$5*Teams!$C$65*L12*Teams!$C$74 -> 0 | ... BL16: =BL$5*Teams!$C$65*BL12*Teams!$C$74 -> 0
A17: Committed capacity (CL-15) | B17: E | C17: =SUM(D17:BL17) -> 0 | E17: =E$5*Teams!$C$64*Teams!$C$16*IF(E$4>=Teams!$C$80,1,0) -> 0 | F17: =F$5*Teams!$C$64*Teams!$C$16*IF(F$4>=Teams!$C$80,1,0) -> 0 | G17: =G$5*Teams!$C$64*Teams!$C$16*IF(G$4>=Teams!$C$80,1,0) -> 0 | H17: =H$5*Teams!$C$64*Teams!$C$16*IF(H$4>=Teams!$C$80,1,0) -> 0 | I17: =I$5*Teams!$C$64*Teams!$C$16*IF(I$4>=Teams!$C$80,1,0) -> 0 | J17: =J$5*Teams!$C$64*Teams!$C$16*IF(J$4>=Teams!$C$80,1,0) -> 0 | K17: =K$5*Teams!$C$64*Teams!$C$16*IF(K$4>=Teams!$C$80,1,0) -> 0 | L17: =L$5*Teams!$C$64*Teams!$C$16*IF(L$4>=Teams!$C$80,1,0) -> 0 | ... BL17: =BL$5*Teams!$C$64*Teams!$C$16*IF(BL$4>=Teams!$C$80,1,0) -> 0
A18: Parsing, embeddings, index, retrieval (CL-05 to CL-08) | B18: A | C18: =SUM(D18:BL18) -> 2210.184 | E18: =E$5*IF(AND(E$4>=Teams!$C$80,Teams!$C$49=1),Teams!$C$44*Params!$D$10*Teams!$C$45*Teams!$C$75+Teams!$C$44*Params!$D$10*Teams!$C$47*Teams!$C$76/1000000+Teams!$C$77+Teams!$C$50*Teams!$C$78+E12*Teams!$C$51*Teams!$C$79/1000000,0) -> 58.434 | F18: =F$5*IF(AND(F$4>=Teams!$C$80,Teams!$C$49=1),Teams!$C$44*Params!$D$10*Teams!$C$45*Teams!$C$75+Teams!$C$44*Params!$D$10*Teams!$C$47*Teams!$C$76/1000000+Teams!$C$77+Teams!$C$50*Teams!$C$78+F12*Teams!$C$51*Teams!$C$79/1000000,0) -> 59.074 | G18: =G$5*IF(AND(G$4>=Teams!$C$80,Teams!$C$49=1),Teams!$C$44*Params!$D$10*Teams!$C$45*Teams!$C$75+Teams!$C$44*Params!$D$10*Teams!$C$47*Teams!$C$76/1000000+Teams!$C$77+Teams!$C$50*Teams!$C$78+G12*Teams!$C$51*Teams!$C$79/1000000,0) -> 59.906 | H18: =H$5*IF(AND(H$4>=Teams!$C$80,Teams!$C$49=1),Teams!$C$44*Params!$D$10*Teams!$C$45*Teams!$C$75+Teams!$C$44*Params!$D$10*Teams!$C$47*Teams!$C$76/1000000+Teams!$C$77+Teams!$C$50*Teams!$C$78+H12*Teams!$C$51*Teams!$C$79/1000000,0) -> 60.738 | I18: =I$5*IF(AND(I$4>=Teams!$C$80,Teams!$C$49=1),Teams!$C$44*Params!$D$10*Teams!$C$45*Teams!$C$75+Teams!$C$44*Params!$D$10*Teams!$C$47*Teams!$C$76/1000000+Teams!$C$77+Teams!$C$50*Teams!$C$78+I12*Teams!$C$51*Teams!$C$79/1000000,0) -> 61.378 | J18: =J$5*IF(AND(J$4>=Teams!$C$80,Teams!$C$49=1),Teams!$C$44*Params!$D$10*Teams!$C$45*Teams!$C$75+Teams!$C$44*Params!$D$10*Teams!$C$47*Teams!$C$76/1000000+Teams!$C$77+Teams!$C$50*Teams!$C$78+J12*Teams!$C$51*Teams!$C$79/1000000,0) -> 61.634 | K18: =K$5*IF(AND(K$4>=Teams!$C$80,Teams!$C$49=1),Teams!$C$44*Params!$D$10*Teams!$C$45*Teams!$C$75+Teams!$C$44*Params!$D$10*Teams!$C$47*Teams!$C$76/1000000+Teams!$C$77+Teams!$C$50*Teams!$C$78+K12*Teams!$C$51*Teams!$C$79/1000000,0) -> 61.634 | L18: =L$5*IF(AND(L$4>=Teams!$C$80,Teams!$C$49=1),Teams!$C$44*Params!$D$10*Teams!$C$45*Teams!$C$75+Teams!$C$44*Params!$D$10*Teams!$C$47*Teams!$C$76/1000000+Teams!$C$77+Teams!$C$50*Teams!$C$78+L12*Teams!$C$51*Teams!$C$79/1000000,0) -> 61.634 | ... BL18: =BL$5*IF(AND(BL$4>=Teams!$C$80,Teams!$C$49=1),Teams!$C$44*Params!$D$10*Teams!$C$45*Teams!$C$75+Teams!$C$44*Params!$D$10*Teams!$C$47*Teams!$C$76/1000000+Teams!$C$77+Teams!$C$50*Teams!$C$78+BL12*Teams!$C$51*Teams!$C$79/1000000,0) -> 0
A19: Connector upkeep (CL-03) | B19: S | C19: =SUM(D19:BL19) -> 3600 | E19: =E$5*IF(E$4>=Teams!$C$80,Teams!$C$43*Params!$D$6*Org!$B$10*Params!$D$7/12,0) -> 100 | F19: =F$5*IF(F$4>=Teams!$C$80,Teams!$C$43*Params!$D$6*Org!$B$10*Params!$D$7/12,0) -> 100 | G19: =G$5*IF(G$4>=Teams!$C$80,Teams!$C$43*Params!$D$6*Org!$B$10*Params!$D$7/12,0) -> 100 | H19: =H$5*IF(H$4>=Teams!$C$80,Teams!$C$43*Params!$D$6*Org!$B$10*Params!$D$7/12,0) -> 100 | I19: =I$5*IF(I$4>=Teams!$C$80,Teams!$C$43*Params!$D$6*Org!$B$10*Params!$D$7/12,0) -> 100 | J19: =J$5*IF(J$4>=Teams!$C$80,Teams!$C$43*Params!$D$6*Org!$B$10*Params!$D$7/12,0) -> 100 | K19: =K$5*IF(K$4>=Teams!$C$80,Teams!$C$43*Params!$D$6*Org!$B$10*Params!$D$7/12,0) -> 100 | L19: =L$5*IF(L$4>=Teams!$C$80,Teams!$C$43*Params!$D$6*Org!$B$10*Params!$D$7/12,0) -> 100 | ... BL19: =BL$5*IF(BL$4>=Teams!$C$80,Teams!$C$43*Params!$D$6*Org!$B$10*Params!$D$7/12,0) -> 0
A20: Quality review, maintenance, support (CL-25, CL-27, CL-28) | B20: S | C20: =SUM(D20:BL20) -> 31875 | E20: =E$5*IF(E$4>=Teams!$C$80,Params!$D$23*Params!$D$24/60*(Org!$B$10/Org!$B$11)+Params!$D$27/12*Params!$D$13*Org!$B$10+E11/1000*Params!$D$28*Params!$D$29*(Org!$B$10/Org!$B$11),0) -> 500 | F20: =F$5*IF(F$4>=Teams!$C$80,Params!$D$23*Params!$D$24/60*(Org!$B$10/Org!$B$11)+Params!$D$27/12*Params!$D$13*Org!$B$10+F11/1000*Params!$D$28*Params!$D$29*(Org!$B$10/Org!$B$11),0) -> 583.33333 | G20: =G$5*IF(G$4>=Teams!$C$80,Params!$D$23*Params!$D$24/60*(Org!$B$10/Org!$B$11)+Params!$D$27/12*Params!$D$13*Org!$B$10+G11/1000*Params!$D$28*Params!$D$29*(Org!$B$10/Org!$B$11),0) -> 691.66667 | H20: =H$5*IF(H$4>=Teams!$C$80,Params!$D$23*Params!$D$24/60*(Org!$B$10/Org!$B$11)+Params!$D$27/12*Params!$D$13*Org!$B$10+H11/1000*Params!$D$28*Params!$D$29*(Org!$B$10/Org!$B$11),0) -> 800 | I20: =I$5*IF(I$4>=Teams!$C$80,Params!$D$23*Params!$D$24/60*(Org!$B$10/Org!$B$11)+Params!$D$27/12*Params!$D$13*Org!$B$10+I11/1000*Params!$D$28*Params!$D$29*(Org!$B$10/Org!$B$11),0) -> 883.33333 | J20: =J$5*IF(J$4>=Teams!$C$80,Params!$D$23*Params!$D$24/60*(Org!$B$10/Org!$B$11)+Params!$D$27/12*Params!$D$13*Org!$B$10+J11/1000*Params!$D$28*Params!$D$29*(Org!$B$10/Org!$B$11),0) -> 916.66667 | K20: =K$5*IF(K$4>=Teams!$C$80,Params!$D$23*Params!$D$24/60*(Org!$B$10/Org!$B$11)+Params!$D$27/12*Params!$D$13*Org!$B$10+K11/1000*Params!$D$28*Params!$D$29*(Org!$B$10/Org!$B$11),0) -> 916.66667 | L20: =L$5*IF(L$4>=Teams!$C$80,Params!$D$23*Params!$D$24/60*(Org!$B$10/Org!$B$11)+Params!$D$27/12*Params!$D$13*Org!$B$10+L11/1000*Params!$D$28*Params!$D$29*(Org!$B$10/Org!$B$11),0) -> 916.66667 | ... BL20: =BL$5*IF(BL$4>=Teams!$C$80,Params!$D$23*Params!$D$24/60*(Org!$B$10/Org!$B$11)+Params!$D$27/12*Params!$D$13*Org!$B$10+BL11/1000*Params!$D$28*Params!$D$29*(Org!$B$10/Org!$B$11),0) -> 0
A21: Model migration events (CL-26) | B21: R | C21: =SUM(D21:BL21) -> 1760 | E21: =E$5*IF(AND(E$4>Teams!$C$80,MOD(E$4-Teams!$C$80,MAX(1,ROUND(Params!$D$25,0)))=0),(Params!$D$26+Params!$D$17*Params!$D$16)*Org!$B$10,0) -> 0 | F21: =F$5*IF(AND(F$4>Teams!$C$80,MOD(F$4-Teams!$C$80,MAX(1,ROUND(Params!$D$25,0)))=0),(Params!$D$26+Params!$D$17*Params!$D$16)*Org!$B$10,0) -> 0 | G21: =G$5*IF(AND(G$4>Teams!$C$80,MOD(G$4-Teams!$C$80,MAX(1,ROUND(Params!$D$25,0)))=0),(Params!$D$26+Params!$D$17*Params!$D$16)*Org!$B$10,0) -> 0 | H21: =H$5*IF(AND(H$4>Teams!$C$80,MOD(H$4-Teams!$C$80,MAX(1,ROUND(Params!$D$25,0)))=0),(Params!$D$26+Params!$D$17*Params!$D$16)*Org!$B$10,0) -> 0 | I21: =I$5*IF(AND(I$4>Teams!$C$80,MOD(I$4-Teams!$C$80,MAX(1,ROUND(Params!$D$25,0)))=0),(Params!$D$26+Params!$D$17*Params!$D$16)*Org!$B$10,0) -> 0 | J21: =J$5*IF(AND(J$4>Teams!$C$80,MOD(J$4-Teams!$C$80,MAX(1,ROUND(Params!$D$25,0)))=0),(Params!$D$26+Params!$D$17*Params!$D$16)*Org!$B$10,0) -> 0 | K21: =K$5*IF(AND(K$4>Teams!$C$80,MOD(K$4-Teams!$C$80,MAX(1,ROUND(Params!$D$25,0)))=0),(Params!$D$26+Params!$D$17*Params!$D$16)*Org!$B$10,0) -> 0 | L21: =L$5*IF(AND(L$4>Teams!$C$80,MOD(L$4-Teams!$C$80,MAX(1,ROUND(Params!$D$25,0)))=0),(Params!$D$26+Params!$D$17*Params!$D$16)*Org!$B$10,0) -> 0 | ... BL21: =BL$5*IF(AND(BL$4>Teams!$C$80,MOD(BL$4-Teams!$C$80,MAX(1,ROUND(Params!$D$25,0)))=0),(Params!$D$26+Params!$D$17*Params!$D$16)*Org!$B$10,0) -> 0
A22: Human review of output (CL-34) | B22: R | C22: =SUM(D22:BL22) -> 141373.35 | E22: =E$5*E12*MIN(1,Teams!$C$41*Params!$D$35)*Params!$D$36/60*Teams!$C$42 -> 312.6 | F22: =F$5*F12*MIN(1,Teams!$C$41*Params!$D$35)*Params!$D$36/60*Teams!$C$42 -> 1094.1 | G22: =G$5*G12*MIN(1,Teams!$C$41*Params!$D$35)*Params!$D$36/60*Teams!$C$42 -> 2110.05 | H22: =H$5*H12*MIN(1,Teams!$C$41*Params!$D$35)*Params!$D$36/60*Teams!$C$42 -> 3126 | I22: =I$5*I12*MIN(1,Teams!$C$41*Params!$D$35)*Params!$D$36/60*Teams!$C$42 -> 3907.5 | J22: =J$5*J12*MIN(1,Teams!$C$41*Params!$D$35)*Params!$D$36/60*Teams!$C$42 -> 4220.1 | K22: =K$5*K12*MIN(1,Teams!$C$41*Params!$D$35)*Params!$D$36/60*Teams!$C$42 -> 4220.1 | L22: =L$5*L12*MIN(1,Teams!$C$41*Params!$D$35)*Params!$D$36/60*Teams!$C$42 -> 4220.1 | ... BL22: =BL$5*BL12*MIN(1,Teams!$C$41*Params!$D$35)*Params!$D$36/60*Teams!$C$42 -> 0
A23: Change champions (CL-35) | B23: S | C23: =SUM(D23:BL23) -> 132000 | E23: =E$5*IF(E$4>=Teams!$C$80,E10/1000*IF(E$4-Teams!$C$80<6,Params!$D$37,Params!$D$38)*Org!$B$10*Org!$B$12/12,0) -> 11000 | F23: =F$5*IF(F$4>=Teams!$C$80,F10/1000*IF(F$4-Teams!$C$80<6,Params!$D$37,Params!$D$38)*Org!$B$10*Org!$B$12/12,0) -> 11000 | G23: =G$5*IF(G$4>=Teams!$C$80,G10/1000*IF(G$4-Teams!$C$80<6,Params!$D$37,Params!$D$38)*Org!$B$10*Org!$B$12/12,0) -> 11000 | H23: =H$5*IF(H$4>=Teams!$C$80,H10/1000*IF(H$4-Teams!$C$80<6,Params!$D$37,Params!$D$38)*Org!$B$10*Org!$B$12/12,0) -> 11000 | I23: =I$5*IF(I$4>=Teams!$C$80,I10/1000*IF(I$4-Teams!$C$80<6,Params!$D$37,Params!$D$38)*Org!$B$10*Org!$B$12/12,0) -> 11000 | J23: =J$5*IF(J$4>=Teams!$C$80,J10/1000*IF(J$4-Teams!$C$80<6,Params!$D$37,Params!$D$38)*Org!$B$10*Org!$B$12/12,0) -> 11000 | K23: =K$5*IF(K$4>=Teams!$C$80,K10/1000*IF(K$4-Teams!$C$80<6,Params!$D$37,Params!$D$38)*Org!$B$10*Org!$B$12/12,0) -> 2200 | L23: =L$5*IF(L$4>=Teams!$C$80,L10/1000*IF(L$4-Teams!$C$80<6,Params!$D$37,Params!$D$38)*Org!$B$10*Org!$B$12/12,0) -> 2200 | ... BL23: =BL$5*IF(BL$4>=Teams!$C$80,BL10/1000*IF(BL$4-Teams!$C$80<6,Params!$D$37,Params!$D$38)*Org!$B$10*Org!$B$12/12,0) -> 0
A24: One-time: assess, clean, connect (CL-01 to CL-03) | B24: S | C24: =SUM(D24:BL24) -> 15200 | D24: =Teams!$C$5*((Teams!$C$43*Params!$D$4+Teams!$C$44/100000*Params!$D$5+Teams!$C$43*Params!$D$6)*Org!$B$10) -> 15200
A25: One-time: initial parse and embed (CL-05, CL-06) | B25: A | C25: =SUM(D25:BL25) -> 157.8 | D25: =Teams!$C$5*(Teams!$C$49*(Teams!$C$44*Teams!$C$45*Teams!$C$75+Teams!$C$44*Teams!$C$47*Teams!$C$76/1000000)) -> 157.8
A26: One-time: integrate, evaluation harness (CL-10, CL-12) | B26: S | C26: =SUM(D26:BL26) -> 18400 | D26: =Teams!$C$5*((Params!$D$13+Params!$D$16)*Org!$B$10) -> 18400
A27: One-time: training (CL-33) | B27: S | C27: =SUM(D27:BL27) -> 360000 | D27: =Teams!$C$5*(Teams!$C$18*Teams!$C$19*Params!$D$34*(Org!$B$10/Org!$B$11)) -> 360000
A28: Benefit | C28: =SUM(D28:BL28) -> 2544720.3 | E28: =E$5*E12*Teams!$C$55/60*Teams!$C$56*INDEX(Params!$D$41:$F$41,Org!$B$17)*Teams!$C$57 -> 5626.8 | F28: =F$5*F12*Teams!$C$55/60*Teams!$C$56*INDEX(Params!$D$41:$F$41,Org!$B$17)*Teams!$C$57 -> 19693.8 | G28: =G$5*G12*Teams!$C$55/60*Teams!$C$56*INDEX(Params!$D$41:$F$41,Org!$B$17)*Teams!$C$57 -> 37980.9 | H28: =H$5*H12*Teams!$C$55/60*Teams!$C$56*INDEX(Params!$D$41:$F$41,Org!$B$17)*Teams!$C$57 -> 56268 | I28: =I$5*I12*Teams!$C$55/60*Teams!$C$56*INDEX(Params!$D$41:$F$41,Org!$B$17)*Teams!$C$57 -> 70335 | J28: =J$5*J12*Teams!$C$55/60*Teams!$C$56*INDEX(Params!$D$41:$F$41,Org!$B$17)*Teams!$C$57 -> 75961.8 | K28: =K$5*K12*Teams!$C$55/60*Teams!$C$56*INDEX(Params!$D$41:$F$41,Org!$B$17)*Teams!$C$57 -> 75961.8 | L28: =L$5*L12*Teams!$C$55/60*Teams!$C$56*INDEX(Params!$D$41:$F$41,Org!$B$17)*Teams!$C$57 -> 75961.8 | ... BL28: =BL$5*BL12*Teams!$C$55/60*Teams!$C$56*INDEX(Params!$D$41:$F$41,Org!$B$17)*Teams!$C$57 -> 0
A29: Direct cost | C29: =SUM(D29:BL29) -> 3730576.3 | D29: =SUM(D13:D27) -> 393757.8 | E29: =SUM(E13:E27) -> 95971.034 | F29: =SUM(F13:F27) -> 96836.507 | G29: =SUM(G13:G27) -> 97961.623 | H29: =SUM(H13:H27) -> 99086.738 | I29: =SUM(I13:I27) -> 99952.211 | J29: =SUM(J13:J27) -> 100298.4 | K29: =SUM(K13:K27) -> 91498.401 | ... BL29: =SUM(BL13:BL27) -> 0
A30: Allocated hub cost | C30: =SUM(D30:BL30) -> 595861.5 | D30: =$B$169*D158 -> 34068.021 | E30: =$B$169*E158 -> 15570.575 | F30: =$B$169*F158 -> 15578.71 | G30: =$B$169*G158 -> 15588.722 | H30: =$B$169*H158 -> 15599.215 | I30: =$B$169*I158 -> 15604.777 | J30: =$B$169*J158 -> 15607.62 | K30: =$B$169*K158 -> 15608.129 | ... BL30: =$B$169*BL158 -> 0
A31: Net cash | C31: =SUM(D31:BL31) -> -1781717.5 | D31: =D28-D29-D30 -> -427825.82 | E31: =E28-E29-E30 -> -105914.81 | F31: =F28-F29-F30 -> -92721.417 | G31: =G28-G29-G30 -> -75569.445 | H31: =H28-H29-H30 -> -58417.953 | I31: =I28-I29-I30 -> -45221.988 | J31: =J28-J29-J30 -> -39944.22 | K31: =K28-K29-K30 -> -31144.729 | ... BL31: =BL28-BL29-BL30 -> 0
A32: Cumulative net cash | D32: =D31 -> -427825.82 | E32: =D32+E31 -> -533740.63 | F32: =E32+F31 -> -626462.05 | G32: =F32+G31 -> -702031.49 | H32: =G32+H31 -> -760449.44 | I32: =H32+I31 -> -805671.43 | J32: =I32+J31 -> -845615.65 | K32: =J32+K31 -> -876760.38 | L32: =K32+L31 -> -907905.11 | ... BL32: =BK32+BL31 -> -1781717.5
A33: Payback flag (month) | C33: =IF(COUNT(E33:BL33)=0,"None",MIN(E33:BL33)) -> None | E33: =IF(AND(E$4<=Org!$B$5,E32>=0),E$4,"") | F33: =IF(AND(F$4<=Org!$B$5,F32>=0),F$4,"") | G33: =IF(AND(G$4<=Org!$B$5,G32>=0),G$4,"") | H33: =IF(AND(H$4<=Org!$B$5,H32>=0),H$4,"") | I33: =IF(AND(I$4<=Org!$B$5,I32>=0),I$4,"") | J33: =IF(AND(J$4<=Org!$B$5,J32>=0),J$4,"") | K33: =IF(AND(K$4<=Org!$B$5,K32>=0),K$4,"") | L33: =IF(AND(L$4<=Org!$B$5,L32>=0),L$4,"") | ... BL33: =IF(AND(BL$4<=Org!$B$5,BL32>=0),BL$4,"")
A35: =Teams!$D$4 -> Engineering assistant | B35: Token cost per outcome: | C35: =(Teams!$D$29*(1-Teams!$D$31)*Params!$D$39*Params!$D$21*IF(Teams!$D$36="Yes",Params!$D$22,1)*Teams!$D$68*Teams!$D$70+Teams!$D$30*(1-Teams!$D$31)*Params!$D$39*Params!$D$21*IF(Teams!$D$36="Yes",Params!$D$22,1)*Teams!$D$69)/1000000*Teams!$D$71*Teams!$D$35 -> 0.05469282
A36: Ramp factor | E36: =IF(E$4<Teams!$D$80,0,IF(Teams!$D$22="S",MIN(1,(E$4-Teams!$D$80+1)/Teams!$D$21)^2*(3-2*MIN(1,(E$4-Teams!$D$80+1)/Teams!$D$21)),MIN(1,(E$4-Teams!$D$80+1)/Teams!$D$21))) -> 0.25 | F36: =IF(F$4<Teams!$D$80,0,IF(Teams!$D$22="S",MIN(1,(F$4-Teams!$D$80+1)/Teams!$D$21)^2*(3-2*MIN(1,(F$4-Teams!$D$80+1)/Teams!$D$21)),MIN(1,(F$4-Teams!$D$80+1)/Teams!$D$21))) -> 0.5 | G36: =IF(G$4<Teams!$D$80,0,IF(Teams!$D$22="S",MIN(1,(G$4-Teams!$D$80+1)/Teams!$D$21)^2*(3-2*MIN(1,(G$4-Teams!$D$80+1)/Teams!$D$21)),MIN(1,(G$4-Teams!$D$80+1)/Teams!$D$21))) -> 0.75 | H36: =IF(H$4<Teams!$D$80,0,IF(Teams!$D$22="S",MIN(1,(H$4-Teams!$D$80+1)/Teams!$D$21)^2*(3-2*MIN(1,(H$4-Teams!$D$80+1)/Teams!$D$21)),MIN(1,(H$4-Teams!$D$80+1)/Teams!$D$21))) -> 1 | I36: =IF(I$4<Teams!$D$80,0,IF(Teams!$D$22="S",MIN(1,(I$4-Teams!$D$80+1)/Teams!$D$21)^2*(3-2*MIN(1,(I$4-Teams!$D$80+1)/Teams!$D$21)),MIN(1,(I$4-Teams!$D$80+1)/Teams!$D$21))) -> 1 | J36: =IF(J$4<Teams!$D$80,0,IF(Teams!$D$22="S",MIN(1,(J$4-Teams!$D$80+1)/Teams!$D$21)^2*(3-2*MIN(1,(J$4-Teams!$D$80+1)/Teams!$D$21)),MIN(1,(J$4-Teams!$D$80+1)/Teams!$D$21))) -> 1 | K36: =IF(K$4<Teams!$D$80,0,IF(Teams!$D$22="S",MIN(1,(K$4-Teams!$D$80+1)/Teams!$D$21)^2*(3-2*MIN(1,(K$4-Teams!$D$80+1)/Teams!$D$21)),MIN(1,(K$4-Teams!$D$80+1)/Teams!$D$21))) -> 1 | L36: =IF(L$4<Teams!$D$80,0,IF(Teams!$D$22="S",MIN(1,(L$4-Teams!$D$80+1)/Teams!$D$21)^2*(3-2*MIN(1,(L$4-Teams!$D$80+1)/Teams!$D$21)),MIN(1,(L$4-Teams!$D$80+1)/Teams!$D$21))) -> 1 | ... BL36: =IF(BL$4<Teams!$D$80,0,IF(Teams!$D$22="S",MIN(1,(BL$4-Teams!$D$80+1)/Teams!$D$21)^2*(3-2*MIN(1,(BL$4-Teams!$D$80+1)/Teams!$D$21)),MIN(1,(BL$4-Teams!$D$80+1)/Teams!$D$21))) -> 1
A37: Licensed users | E37: =IF(E$4>=Teams!$D$80,Teams!$D$18,0) -> 400 | F37: =IF(F$4>=Teams!$D$80,Teams!$D$18,0) -> 400 | G37: =IF(G$4>=Teams!$D$80,Teams!$D$18,0) -> 400 | H37: =IF(H$4>=Teams!$D$80,Teams!$D$18,0) -> 400 | I37: =IF(I$4>=Teams!$D$80,Teams!$D$18,0) -> 400 | J37: =IF(J$4>=Teams!$D$80,Teams!$D$18,0) -> 400 | K37: =IF(K$4>=Teams!$D$80,Teams!$D$18,0) -> 400 | L37: =IF(L$4>=Teams!$D$80,Teams!$D$18,0) -> 400 | ... BL37: =IF(BL$4>=Teams!$D$80,Teams!$D$18,0) -> 400
A38: Active users | C38: =SUMPRODUCT(E38:BL38,E$5:BL$5) -> 11040 | E38: =E37*Teams!$D$19*E36 -> 80 | F38: =F37*Teams!$D$19*F36 -> 160 | G38: =G37*Teams!$D$19*G36 -> 240 | H38: =H37*Teams!$D$19*H36 -> 320 | I38: =I37*Teams!$D$19*I36 -> 320 | J38: =J37*Teams!$D$19*J36 -> 320 | K38: =K37*Teams!$D$19*K36 -> 320 | L38: =L37*Teams!$D$19*L36 -> 320 | ... BL38: =BL37*Teams!$D$19*BL36 -> 320
A39: Outcomes | C39: =SUMPRODUCT(E39:BL39,E$5:BL$5) -> 4416000 | E39: =IF(Teams!$D$23="per user",E38*Teams!$D$24,Teams!$D$25*E36) -> 32000 | F39: =IF(Teams!$D$23="per user",F38*Teams!$D$24,Teams!$D$25*F36) -> 64000 | G39: =IF(Teams!$D$23="per user",G38*Teams!$D$24,Teams!$D$25*G36) -> 96000 | H39: =IF(Teams!$D$23="per user",H38*Teams!$D$24,Teams!$D$25*H36) -> 128000 | I39: =IF(Teams!$D$23="per user",I38*Teams!$D$24,Teams!$D$25*I36) -> 128000 | J39: =IF(Teams!$D$23="per user",J38*Teams!$D$24,Teams!$D$25*J36) -> 128000 | K39: =IF(Teams!$D$23="per user",K38*Teams!$D$24,Teams!$D$25*K36) -> 128000 | L39: =IF(Teams!$D$23="per user",L38*Teams!$D$24,Teams!$D$25*L36) -> 128000 | ... BL39: =IF(Teams!$D$23="per user",BL38*Teams!$D$24,Teams!$D$25*BL36) -> 128000
A40: Seats (CL-21) | B40: A | C40: =SUM(D40:BL40) -> 288000 | E40: =E$5*Teams!$D$60*E37*Teams!$D$66 -> 8000 | F40: =F$5*Teams!$D$60*F37*Teams!$D$66 -> 8000 | G40: =G$5*Teams!$D$60*G37*Teams!$D$66 -> 8000 | H40: =H$5*Teams!$D$60*H37*Teams!$D$66 -> 8000 | I40: =I$5*Teams!$D$60*I37*Teams!$D$66 -> 8000 | J40: =J$5*Teams!$D$60*J37*Teams!$D$66 -> 8000 | K40: =K$5*Teams!$D$60*K37*Teams!$D$66 -> 8000 | L40: =L$5*Teams!$D$60*L37*Teams!$D$66 -> 8000 | ... BL40: =BL$5*Teams!$D$60*BL37*Teams!$D$66 -> 0
A41: Model tokens incl. retries and agent steps (CL-16, CL-17) | B41: A | C41: =SUM(D41:BL41) -> 241523.49 | E41: =E$5*IF(Teams!$D$61=1,E38*((1-Teams!$D$13)*MAX(0,Teams!$D$72*$C$35-Teams!$D$12)+Teams!$D$13*MAX(0,Teams!$D$73*$C$35-Teams!$D$12)),IF(Teams!$D$62=1,E39*$C$35,0)) -> 1750.1702 | F41: =F$5*IF(Teams!$D$61=1,F38*((1-Teams!$D$13)*MAX(0,Teams!$D$72*$C$35-Teams!$D$12)+Teams!$D$13*MAX(0,Teams!$D$73*$C$35-Teams!$D$12)),IF(Teams!$D$62=1,F39*$C$35,0)) -> 3500.3405 | G41: =G$5*IF(Teams!$D$61=1,G38*((1-Teams!$D$13)*MAX(0,Teams!$D$72*$C$35-Teams!$D$12)+Teams!$D$13*MAX(0,Teams!$D$73*$C$35-Teams!$D$12)),IF(Teams!$D$62=1,G39*$C$35,0)) -> 5250.5107 | H41: =H$5*IF(Teams!$D$61=1,H38*((1-Teams!$D$13)*MAX(0,Teams!$D$72*$C$35-Teams!$D$12)+Teams!$D$13*MAX(0,Teams!$D$73*$C$35-Teams!$D$12)),IF(Teams!$D$62=1,H39*$C$35,0)) -> 7000.681 | I41: =I$5*IF(Teams!$D$61=1,I38*((1-Teams!$D$13)*MAX(0,Teams!$D$72*$C$35-Teams!$D$12)+Teams!$D$13*MAX(0,Teams!$D$73*$C$35-Teams!$D$12)),IF(Teams!$D$62=1,I39*$C$35,0)) -> 7000.681 | J41: =J$5*IF(Teams!$D$61=1,J38*((1-Teams!$D$13)*MAX(0,Teams!$D$72*$C$35-Teams!$D$12)+Teams!$D$13*MAX(0,Teams!$D$73*$C$35-Teams!$D$12)),IF(Teams!$D$62=1,J39*$C$35,0)) -> 7000.681 | K41: =K$5*IF(Teams!$D$61=1,K38*((1-Teams!$D$13)*MAX(0,Teams!$D$72*$C$35-Teams!$D$12)+Teams!$D$13*MAX(0,Teams!$D$73*$C$35-Teams!$D$12)),IF(Teams!$D$62=1,K39*$C$35,0)) -> 7000.681 | L41: =L$5*IF(Teams!$D$61=1,L38*((1-Teams!$D$13)*MAX(0,Teams!$D$72*$C$35-Teams!$D$12)+Teams!$D$13*MAX(0,Teams!$D$73*$C$35-Teams!$D$12)),IF(Teams!$D$62=1,L39*$C$35,0)) -> 7000.681 | ... BL41: =BL$5*IF(Teams!$D$61=1,BL38*((1-Teams!$D$13)*MAX(0,Teams!$D$72*$C$35-Teams!$D$12)+Teams!$D$13*MAX(0,Teams!$D$73*$C$35-Teams!$D$12)),IF(Teams!$D$62=1,BL39*$C$35,0)) -> 0
A42: Vendor per-outcome price (CL-22) | B42: A | C42: =SUM(D42:BL42) -> 0 | E42: =E$5*Teams!$D$63*E39*Teams!$D$67 -> 0 | F42: =F$5*Teams!$D$63*F39*Teams!$D$67 -> 0 | G42: =G$5*Teams!$D$63*G39*Teams!$D$67 -> 0 | H42: =H$5*Teams!$D$63*H39*Teams!$D$67 -> 0 | I42: =I$5*Teams!$D$63*I39*Teams!$D$67 -> 0 | J42: =J$5*Teams!$D$63*J39*Teams!$D$67 -> 0 | K42: =K$5*Teams!$D$63*K39*Teams!$D$67 -> 0 | L42: =L$5*Teams!$D$63*L39*Teams!$D$67 -> 0 | ... BL42: =BL$5*Teams!$D$63*BL39*Teams!$D$67 -> 0
A43: Tool and guardrail calls (CL-18, CL-19) | B43: A | C43: =SUM(D43:BL43) -> 0 | E43: =E$5*Teams!$D$65*E39*Teams!$D$74 -> 0 | F43: =F$5*Teams!$D$65*F39*Teams!$D$74 -> 0 | G43: =G$5*Teams!$D$65*G39*Teams!$D$74 -> 0 | H43: =H$5*Teams!$D$65*H39*Teams!$D$74 -> 0 | I43: =I$5*Teams!$D$65*I39*Teams!$D$74 -> 0 | J43: =J$5*Teams!$D$65*J39*Teams!$D$74 -> 0 | K43: =K$5*Teams!$D$65*K39*Teams!$D$74 -> 0 | L43: =L$5*Teams!$D$65*L39*Teams!$D$74 -> 0 | ... BL43: =BL$5*Teams!$D$65*BL39*Teams!$D$74 -> 0
A44: Committed capacity (CL-15) | B44: E | C44: =SUM(D44:BL44) -> 0 | E44: =E$5*Teams!$D$64*Teams!$D$16*IF(E$4>=Teams!$D$80,1,0) -> 0 | F44: =F$5*Teams!$D$64*Teams!$D$16*IF(F$4>=Teams!$D$80,1,0) -> 0 | G44: =G$5*Teams!$D$64*Teams!$D$16*IF(G$4>=Teams!$D$80,1,0) -> 0 | H44: =H$5*Teams!$D$64*Teams!$D$16*IF(H$4>=Teams!$D$80,1,0) -> 0 | I44: =I$5*Teams!$D$64*Teams!$D$16*IF(I$4>=Teams!$D$80,1,0) -> 0 | J44: =J$5*Teams!$D$64*Teams!$D$16*IF(J$4>=Teams!$D$80,1,0) -> 0 | K44: =K$5*Teams!$D$64*Teams!$D$16*IF(K$4>=Teams!$D$80,1,0) -> 0 | L44: =L$5*Teams!$D$64*Teams!$D$16*IF(L$4>=Teams!$D$80,1,0) -> 0 | ... BL44: =BL$5*Teams!$D$64*Teams!$D$16*IF(BL$4>=Teams!$D$80,1,0) -> 0
A45: Parsing, embeddings, index, retrieval (CL-05 to CL-08) | B45: A | C45: =SUM(D45:BL45) -> 2718.84 | E45: =E$5*IF(AND(E$4>=Teams!$D$80,Teams!$D$49=1),Teams!$D$44*Params!$D$10*Teams!$D$45*Teams!$D$75+Teams!$D$44*Params!$D$10*Teams!$D$47*Teams!$D$76/1000000+Teams!$D$77+Teams!$D$50*Teams!$D$78+E39*Teams!$D$51*Teams!$D$79/1000000,0) -> 68.27 | F45: =F$5*IF(AND(F$4>=Teams!$D$80,Teams!$D$49=1),Teams!$D$44*Params!$D$10*Teams!$D$45*Teams!$D$75+Teams!$D$44*Params!$D$10*Teams!$D$47*Teams!$D$76/1000000+Teams!$D$77+Teams!$D$50*Teams!$D$78+F39*Teams!$D$51*Teams!$D$79/1000000,0) -> 70.83 | G45: =G$5*IF(AND(G$4>=Teams!$D$80,Teams!$D$49=1),Teams!$D$44*Params!$D$10*Teams!$D$45*Teams!$D$75+Teams!$D$44*Params!$D$10*Teams!$D$47*Teams!$D$76/1000000+Teams!$D$77+Teams!$D$50*Teams!$D$78+G39*Teams!$D$51*Teams!$D$79/1000000,0) -> 73.39 | H45: =H$5*IF(AND(H$4>=Teams!$D$80,Teams!$D$49=1),Teams!$D$44*Params!$D$10*Teams!$D$45*Teams!$D$75+Teams!$D$44*Params!$D$10*Teams!$D$47*Teams!$D$76/1000000+Teams!$D$77+Teams!$D$50*Teams!$D$78+H39*Teams!$D$51*Teams!$D$79/1000000,0) -> 75.95 | I45: =I$5*IF(AND(I$4>=Teams!$D$80,Teams!$D$49=1),Teams!$D$44*Params!$D$10*Teams!$D$45*Teams!$D$75+Teams!$D$44*Params!$D$10*Teams!$D$47*Teams!$D$76/1000000+Teams!$D$77+Teams!$D$50*Teams!$D$78+I39*Teams!$D$51*Teams!$D$79/1000000,0) -> 75.95 | J45: =J$5*IF(AND(J$4>=Teams!$D$80,Teams!$D$49=1),Teams!$D$44*Params!$D$10*Teams!$D$45*Teams!$D$75+Teams!$D$44*Params!$D$10*Teams!$D$47*Teams!$D$76/1000000+Teams!$D$77+Teams!$D$50*Teams!$D$78+J39*Teams!$D$51*Teams!$D$79/1000000,0) -> 75.95 | K45: =K$5*IF(AND(K$4>=Teams!$D$80,Teams!$D$49=1),Teams!$D$44*Params!$D$10*Teams!$D$45*Teams!$D$75+Teams!$D$44*Params!$D$10*Teams!$D$47*Teams!$D$76/1000000+Teams!$D$77+Teams!$D$50*Teams!$D$78+K39*Teams!$D$51*Teams!$D$79/1000000,0) -> 75.95 | L45: =L$5*IF(AND(L$4>=Teams!$D$80,Teams!$D$49=1),Teams!$D$44*Params!$D$10*Teams!$D$45*Teams!$D$75+Teams!$D$44*Params!$D$10*Teams!$D$47*Teams!$D$76/1000000+Teams!$D$77+Teams!$D$50*Teams!$D$78+L39*Teams!$D$51*Teams!$D$79/1000000,0) -> 75.95 | ... BL45: =BL$5*IF(AND(BL$4>=Teams!$D$80,Teams!$D$49=1),Teams!$D$44*Params!$D$10*Teams!$D$45*Teams!$D$75+Teams!$D$44*Params!$D$10*Teams!$D$47*Teams!$D$76/1000000+Teams!$D$77+Teams!$D$50*Teams!$D$78+BL39*Teams!$D$51*Teams!$D$79/1000000,0) -> 0
A46: Connector upkeep (CL-03) | B46: S | C46: =SUM(D46:BL46) -> 2400 | E46: =E$5*IF(E$4>=Teams!$D$80,Teams!$D$43*Params!$D$6*Org!$B$10*Params!$D$7/12,0) -> 66.666667 | F46: =F$5*IF(F$4>=Teams!$D$80,Teams!$D$43*Params!$D$6*Org!$B$10*Params!$D$7/12,0) -> 66.666667 | G46: =G$5*IF(G$4>=Teams!$D$80,Teams!$D$43*Params!$D$6*Org!$B$10*Params!$D$7/12,0) -> 66.666667 | H46: =H$5*IF(H$4>=Teams!$D$80,Teams!$D$43*Params!$D$6*Org!$B$10*Params!$D$7/12,0) -> 66.666667 | I46: =I$5*IF(I$4>=Teams!$D$80,Teams!$D$43*Params!$D$6*Org!$B$10*Params!$D$7/12,0) -> 66.666667 | J46: =J$5*IF(J$4>=Teams!$D$80,Teams!$D$43*Params!$D$6*Org!$B$10*Params!$D$7/12,0) -> 66.666667 | K46: =K$5*IF(K$4>=Teams!$D$80,Teams!$D$43*Params!$D$6*Org!$B$10*Params!$D$7/12,0) -> 66.666667 | L46: =L$5*IF(L$4>=Teams!$D$80,Teams!$D$43*Params!$D$6*Org!$B$10*Params!$D$7/12,0) -> 66.666667 | ... BL46: =BL$5*IF(BL$4>=Teams!$D$80,Teams!$D$43*Params!$D$6*Org!$B$10*Params!$D$7/12,0) -> 0
A47: Quality review, maintenance, support (CL-25, CL-27, CL-28) | B47: S | C47: =SUM(D47:BL47) -> 19560 | E47: =E$5*IF(E$4>=Teams!$D$80,Params!$D$23*Params!$D$24/60*(Org!$B$10/Org!$B$11)+Params!$D$27/12*Params!$D$13*Org!$B$10+E38/1000*Params!$D$28*Params!$D$29*(Org!$B$10/Org!$B$11),0) -> 486.66667 | F47: =F$5*IF(F$4>=Teams!$D$80,Params!$D$23*Params!$D$24/60*(Org!$B$10/Org!$B$11)+Params!$D$27/12*Params!$D$13*Org!$B$10+F38/1000*Params!$D$28*Params!$D$29*(Org!$B$10/Org!$B$11),0) -> 506.66667 | G47: =G$5*IF(G$4>=Teams!$D$80,Params!$D$23*Params!$D$24/60*(Org!$B$10/Org!$B$11)+Params!$D$27/12*Params!$D$13*Org!$B$10+G38/1000*Params!$D$28*Params!$D$29*(Org!$B$10/Org!$B$11),0) -> 526.66667 | H47: =H$5*IF(H$4>=Teams!$D$80,Params!$D$23*Params!$D$24/60*(Org!$B$10/Org!$B$11)+Params!$D$27/12*Params!$D$13*Org!$B$10+H38/1000*Params!$D$28*Params!$D$29*(Org!$B$10/Org!$B$11),0) -> 546.66667 | I47: =I$5*IF(I$4>=Teams!$D$80,Params!$D$23*Params!$D$24/60*(Org!$B$10/Org!$B$11)+Params!$D$27/12*Params!$D$13*Org!$B$10+I38/1000*Params!$D$28*Params!$D$29*(Org!$B$10/Org!$B$11),0) -> 546.66667 | J47: =J$5*IF(J$4>=Teams!$D$80,Params!$D$23*Params!$D$24/60*(Org!$B$10/Org!$B$11)+Params!$D$27/12*Params!$D$13*Org!$B$10+J38/1000*Params!$D$28*Params!$D$29*(Org!$B$10/Org!$B$11),0) -> 546.66667 | K47: =K$5*IF(K$4>=Teams!$D$80,Params!$D$23*Params!$D$24/60*(Org!$B$10/Org!$B$11)+Params!$D$27/12*Params!$D$13*Org!$B$10+K38/1000*Params!$D$28*Params!$D$29*(Org!$B$10/Org!$B$11),0) -> 546.66667 | L47: =L$5*IF(L$4>=Teams!$D$80,Params!$D$23*Params!$D$24/60*(Org!$B$10/Org!$B$11)+Params!$D$27/12*Params!$D$13*Org!$B$10+L38/1000*Params!$D$28*Params!$D$29*(Org!$B$10/Org!$B$11),0) -> 546.66667 | ... BL47: =BL$5*IF(BL$4>=Teams!$D$80,Params!$D$23*Params!$D$24/60*(Org!$B$10/Org!$B$11)+Params!$D$27/12*Params!$D$13*Org!$B$10+BL38/1000*Params!$D$28*Params!$D$29*(Org!$B$10/Org!$B$11),0) -> 0
A48: Model migration events (CL-26) | B48: R | C48: =SUM(D48:BL48) -> 1760 | E48: =E$5*IF(AND(E$4>Teams!$D$80,MOD(E$4-Teams!$D$80,MAX(1,ROUND(Params!$D$25,0)))=0),(Params!$D$26+Params!$D$17*Params!$D$16)*Org!$B$10,0) -> 0 | F48: =F$5*IF(AND(F$4>Teams!$D$80,MOD(F$4-Teams!$D$80,MAX(1,ROUND(Params!$D$25,0)))=0),(Params!$D$26+Params!$D$17*Params!$D$16)*Org!$B$10,0) -> 0 | G48: =G$5*IF(AND(G$4>Teams!$D$80,MOD(G$4-Teams!$D$80,MAX(1,ROUND(Params!$D$25,0)))=0),(Params!$D$26+Params!$D$17*Params!$D$16)*Org!$B$10,0) -> 0 | H48: =H$5*IF(AND(H$4>Teams!$D$80,MOD(H$4-Teams!$D$80,MAX(1,ROUND(Params!$D$25,0)))=0),(Params!$D$26+Params!$D$17*Params!$D$16)*Org!$B$10,0) -> 0 | I48: =I$5*IF(AND(I$4>Teams!$D$80,MOD(I$4-Teams!$D$80,MAX(1,ROUND(Params!$D$25,0)))=0),(Params!$D$26+Params!$D$17*Params!$D$16)*Org!$B$10,0) -> 0 | J48: =J$5*IF(AND(J$4>Teams!$D$80,MOD(J$4-Teams!$D$80,MAX(1,ROUND(Params!$D$25,0)))=0),(Params!$D$26+Params!$D$17*Params!$D$16)*Org!$B$10,0) -> 0 | K48: =K$5*IF(AND(K$4>Teams!$D$80,MOD(K$4-Teams!$D$80,MAX(1,ROUND(Params!$D$25,0)))=0),(Params!$D$26+Params!$D$17*Params!$D$16)*Org!$B$10,0) -> 0 | L48: =L$5*IF(AND(L$4>Teams!$D$80,MOD(L$4-Teams!$D$80,MAX(1,ROUND(Params!$D$25,0)))=0),(Params!$D$26+Params!$D$17*Params!$D$16)*Org!$B$10,0) -> 0 | ... BL48: =BL$5*IF(AND(BL$4>Teams!$D$80,MOD(BL$4-Teams!$D$80,MAX(1,ROUND(Params!$D$25,0)))=0),(Params!$D$26+Params!$D$17*Params!$D$16)*Org!$B$10,0) -> 0
A49: Human review of output (CL-34) | B49: R | C49: =SUM(D49:BL49) -> 690220.8 | E49: =E$5*E39*MIN(1,Teams!$D$41*Params!$D$35)*Params!$D$36/60*Teams!$D$42 -> 5001.6 | F49: =F$5*F39*MIN(1,Teams!$D$41*Params!$D$35)*Params!$D$36/60*Teams!$D$42 -> 10003.2 | G49: =G$5*G39*MIN(1,Teams!$D$41*Params!$D$35)*Params!$D$36/60*Teams!$D$42 -> 15004.8 | H49: =H$5*H39*MIN(1,Teams!$D$41*Params!$D$35)*Params!$D$36/60*Teams!$D$42 -> 20006.4 | I49: =I$5*I39*MIN(1,Teams!$D$41*Params!$D$35)*Params!$D$36/60*Teams!$D$42 -> 20006.4 | J49: =J$5*J39*MIN(1,Teams!$D$41*Params!$D$35)*Params!$D$36/60*Teams!$D$42 -> 20006.4 | K49: =K$5*K39*MIN(1,Teams!$D$41*Params!$D$35)*Params!$D$36/60*Teams!$D$42 -> 20006.4 | L49: =L$5*L39*MIN(1,Teams!$D$41*Params!$D$35)*Params!$D$36/60*Teams!$D$42 -> 20006.4 | ... BL49: =BL$5*BL39*MIN(1,Teams!$D$41*Params!$D$35)*Params!$D$36/60*Teams!$D$42 -> 0
A50: Change champions (CL-35) | B50: S | C50: =SUM(D50:BL50) -> 17600 | E50: =E$5*IF(E$4>=Teams!$D$80,E37/1000*IF(E$4-Teams!$D$80<6,Params!$D$37,Params!$D$38)*Org!$B$10*Org!$B$12/12,0) -> 1466.6667 | F50: =F$5*IF(F$4>=Teams!$D$80,F37/1000*IF(F$4-Teams!$D$80<6,Params!$D$37,Params!$D$38)*Org!$B$10*Org!$B$12/12,0) -> 1466.6667 | G50: =G$5*IF(G$4>=Teams!$D$80,G37/1000*IF(G$4-Teams!$D$80<6,Params!$D$37,Params!$D$38)*Org!$B$10*Org!$B$12/12,0) -> 1466.6667 | H50: =H$5*IF(H$4>=Teams!$D$80,H37/1000*IF(H$4-Teams!$D$80<6,Params!$D$37,Params!$D$38)*Org!$B$10*Org!$B$12/12,0) -> 1466.6667 | I50: =I$5*IF(I$4>=Teams!$D$80,I37/1000*IF(I$4-Teams!$D$80<6,Params!$D$37,Params!$D$38)*Org!$B$10*Org!$B$12/12,0) -> 1466.6667 | J50: =J$5*IF(J$4>=Teams!$D$80,J37/1000*IF(J$4-Teams!$D$80<6,Params!$D$37,Params!$D$38)*Org!$B$10*Org!$B$12/12,0) -> 1466.6667 | K50: =K$5*IF(K$4>=Teams!$D$80,K37/1000*IF(K$4-Teams!$D$80<6,Params!$D$37,Params!$D$38)*Org!$B$10*Org!$B$12/12,0) -> 293.33333 | L50: =L$5*IF(L$4>=Teams!$D$80,L37/1000*IF(L$4-Teams!$D$80<6,Params!$D$37,Params!$D$38)*Org!$B$10*Org!$B$12/12,0) -> 293.33333 | ... BL50: =BL$5*IF(BL$4>=Teams!$D$80,BL37/1000*IF(BL$4-Teams!$D$80<6,Params!$D$37,Params!$D$38)*Org!$B$10*Org!$B$12/12,0) -> 0
A51: One-time: assess, clean, connect (CL-01 to CL-03) | B51: S | C51: =SUM(D51:BL51) -> 11600 | D51: =Teams!$D$5*((Teams!$D$43*Params!$D$4+Teams!$D$44/100000*Params!$D$5+Teams!$D$43*Params!$D$6)*Org!$B$10) -> 11600
A52: One-time: initial parse and embed (CL-05, CL-06) | B52: A | C52: =SUM(D52:BL52) -> 251 | D52: =Teams!$D$5*(Teams!$D$49*(Teams!$D$44*Teams!$D$45*Teams!$D$75+Teams!$D$44*Teams!$D$47*Teams!$D$76/1000000)) -> 251
A53: One-time: integrate, evaluation harness (CL-10, CL-12) | B53: S | C53: =SUM(D53:BL53) -> 18400 | D53: =Teams!$D$5*((Params!$D$13+Params!$D$16)*Org!$B$10) -> 18400
A54: One-time: training (CL-33) | B54: S | C54: =SUM(D54:BL54) -> 64000 | D54: =Teams!$D$5*(Teams!$D$18*Teams!$D$19*Params!$D$34*(Org!$B$10/Org!$B$11)) -> 64000
A55: Benefit | C55: =SUM(D55:BL55) -> 13763200 | E55: =E$5*E39*Teams!$D$55/60*Teams!$D$56*INDEX(Params!$D$41:$F$41,Org!$B$17)*Teams!$D$57 -> 99733.333 | F55: =F$5*F39*Teams!$D$55/60*Teams!$D$56*INDEX(Params!$D$41:$F$41,Org!$B$17)*Teams!$D$57 -> 199466.67 | G55: =G$5*G39*Teams!$D$55/60*Teams!$D$56*INDEX(Params!$D$41:$F$41,Org!$B$17)*Teams!$D$57 -> 299200 | H55: =H$5*H39*Teams!$D$55/60*Teams!$D$56*INDEX(Params!$D$41:$F$41,Org!$B$17)*Teams!$D$57 -> 398933.33 | I55: =I$5*I39*Teams!$D$55/60*Teams!$D$56*INDEX(Params!$D$41:$F$41,Org!$B$17)*Teams!$D$57 -> 398933.33 | J55: =J$5*J39*Teams!$D$55/60*Teams!$D$56*INDEX(Params!$D$41:$F$41,Org!$B$17)*Teams!$D$57 -> 398933.33 | K55: =K$5*K39*Teams!$D$55/60*Teams!$D$56*INDEX(Params!$D$41:$F$41,Org!$B$17)*Teams!$D$57 -> 398933.33 | L55: =L$5*L39*Teams!$D$55/60*Teams!$D$56*INDEX(Params!$D$41:$F$41,Org!$B$17)*Teams!$D$57 -> 398933.33 | ... BL55: =BL$5*BL39*Teams!$D$55/60*Teams!$D$56*INDEX(Params!$D$41:$F$41,Org!$B$17)*Teams!$D$57 -> 0
A56: Direct cost | C56: =SUM(D56:BL56) -> 1358034.1 | D56: =SUM(D40:D54) -> 94251 | E56: =SUM(E40:E54) -> 16840.04 | F56: =SUM(F40:F54) -> 23614.37 | G56: =SUM(G40:G54) -> 30388.701 | H56: =SUM(H40:H54) -> 37163.031 | I56: =SUM(I40:I54) -> 37163.031 | J56: =SUM(J40:J54) -> 37163.031 | K56: =SUM(K40:K54) -> 35989.698 | ... BL56: =SUM(BL40:BL54) -> 0
A57: Allocated hub cost | C57: =SUM(D57:BL57) -> 727287.01 | D57: =$C$169*D158 -> 41582.195 | E57: =$C$169*E158 -> 19004.88 | F57: =$C$169*F158 -> 19014.81 | G57: =$C$169*G158 -> 19027.031 | H57: =$C$169*H158 -> 19039.838 | I57: =$C$169*I158 -> 19046.627 | J57: =$C$169*J158 -> 19050.096 | K57: =$C$169*K158 -> 19050.718 | ... BL57: =$C$169*BL158 -> 0
A58: Net cash | C58: =SUM(D58:BL58) -> 11677879 | D58: =D55-D56-D57 -> -135833.19 | E58: =E55-E56-E57 -> 63888.413 | F58: =F55-F56-F57 -> 156837.49 | G58: =G55-G56-G57 -> 249784.27 | H58: =H55-H56-H57 -> 342730.46 | I58: =I55-I56-I57 -> 342723.68 | J58: =J55-J56-J57 -> 342720.21 | K58: =K55-K56-K57 -> 343892.92 | ... BL58: =BL55-BL56-BL57 -> 0
A59: Cumulative net cash | D59: =D58 -> -135833.19 | E59: =D59+E58 -> -71944.782 | F59: =E59+F58 -> 84892.704 | G59: =F59+G58 -> 334676.97 | H59: =G59+H58 -> 677407.44 | I59: =H59+I58 -> 1020131.1 | J59: =I59+J58 -> 1362851.3 | K59: =J59+K58 -> 1706744.2 | L59: =K59+L58 -> 2050637.2 | ... BL59: =BK59+BL58 -> 11677879
A60: Payback flag (month) | C60: =IF(COUNT(E60:BL60)=0,"None",MIN(E60:BL60)) -> 2 | E60: =IF(AND(E$4<=Org!$B$5,E59>=0),E$4,"") | F60: =IF(AND(F$4<=Org!$B$5,F59>=0),F$4,"") -> 2 | G60: =IF(AND(G$4<=Org!$B$5,G59>=0),G$4,"") -> 3 | H60: =IF(AND(H$4<=Org!$B$5,H59>=0),H$4,"") -> 4 | I60: =IF(AND(I$4<=Org!$B$5,I59>=0),I$4,"") -> 5 | J60: =IF(AND(J$4<=Org!$B$5,J59>=0),J$4,"") -> 6 | K60: =IF(AND(K$4<=Org!$B$5,K59>=0),K$4,"") -> 7 | L60: =IF(AND(L$4<=Org!$B$5,L59>=0),L$4,"") -> 8 | ... BL60: =IF(AND(BL$4<=Org!$B$5,BL59>=0),BL$4,"")
A62: =Teams!$E$4 -> Customer service agent | B62: Token cost per outcome: | C62: =(Teams!$E$29*(1-Teams!$E$31)*Params!$D$39*Params!$D$21*IF(Teams!$E$36="Yes",Params!$D$22,1)*Teams!$E$68*Teams!$E$70+Teams!$E$30*(1-Teams!$E$31)*Params!$D$39*Params!$D$21*IF(Teams!$E$36="Yes",Params!$D$22,1)*Teams!$E$69)/1000000*Teams!$E$71*Teams!$E$35 -> 0
A63: Ramp factor | E63: =IF(E$4<Teams!$E$80,0,IF(Teams!$E$22="S",MIN(1,(E$4-Teams!$E$80+1)/Teams!$E$21)^2*(3-2*MIN(1,(E$4-Teams!$E$80+1)/Teams!$E$21)),MIN(1,(E$4-Teams!$E$80+1)/Teams!$E$21))) -> 0 | F63: =IF(F$4<Teams!$E$80,0,IF(Teams!$E$22="S",MIN(1,(F$4-Teams!$E$80+1)/Teams!$E$21)^2*(3-2*MIN(1,(F$4-Teams!$E$80+1)/Teams!$E$21)),MIN(1,(F$4-Teams!$E$80+1)/Teams!$E$21))) -> 0.074074074 | G63: =IF(G$4<Teams!$E$80,0,IF(Teams!$E$22="S",MIN(1,(G$4-Teams!$E$80+1)/Teams!$E$21)^2*(3-2*MIN(1,(G$4-Teams!$E$80+1)/Teams!$E$21)),MIN(1,(G$4-Teams!$E$80+1)/Teams!$E$21))) -> 0.25925926 | H63: =IF(H$4<Teams!$E$80,0,IF(Teams!$E$22="S",MIN(1,(H$4-Teams!$E$80+1)/Teams!$E$21)^2*(3-2*MIN(1,(H$4-Teams!$E$80+1)/Teams!$E$21)),MIN(1,(H$4-Teams!$E$80+1)/Teams!$E$21))) -> 0.5 | I63: =IF(I$4<Teams!$E$80,0,IF(Teams!$E$22="S",MIN(1,(I$4-Teams!$E$80+1)/Teams!$E$21)^2*(3-2*MIN(1,(I$4-Teams!$E$80+1)/Teams!$E$21)),MIN(1,(I$4-Teams!$E$80+1)/Teams!$E$21))) -> 0.74074074 | J63: =IF(J$4<Teams!$E$80,0,IF(Teams!$E$22="S",MIN(1,(J$4-Teams!$E$80+1)/Teams!$E$21)^2*(3-2*MIN(1,(J$4-Teams!$E$80+1)/Teams!$E$21)),MIN(1,(J$4-Teams!$E$80+1)/Teams!$E$21))) -> 0.92592593 | K63: =IF(K$4<Teams!$E$80,0,IF(Teams!$E$22="S",MIN(1,(K$4-Teams!$E$80+1)/Teams!$E$21)^2*(3-2*MIN(1,(K$4-Teams!$E$80+1)/Teams!$E$21)),MIN(1,(K$4-Teams!$E$80+1)/Teams!$E$21))) -> 1 | L63: =IF(L$4<Teams!$E$80,0,IF(Teams!$E$22="S",MIN(1,(L$4-Teams!$E$80+1)/Teams!$E$21)^2*(3-2*MIN(1,(L$4-Teams!$E$80+1)/Teams!$E$21)),MIN(1,(L$4-Teams!$E$80+1)/Teams!$E$21))) -> 1 | ... BL63: =IF(BL$4<Teams!$E$80,0,IF(Teams!$E$22="S",MIN(1,(BL$4-Teams!$E$80+1)/Teams!$E$21)^2*(3-2*MIN(1,(BL$4-Teams!$E$80+1)/Teams!$E$21)),MIN(1,(BL$4-Teams!$E$80+1)/Teams!$E$21))) -> 1
A64: Licensed users | E64: =IF(E$4>=Teams!$E$80,Teams!$E$18,0) -> 0 | F64: =IF(F$4>=Teams!$E$80,Teams!$E$18,0) -> 60 | G64: =IF(G$4>=Teams!$E$80,Teams!$E$18,0) -> 60 | H64: =IF(H$4>=Teams!$E$80,Teams!$E$18,0) -> 60 | I64: =IF(I$4>=Teams!$E$80,Teams!$E$18,0) -> 60 | J64: =IF(J$4>=Teams!$E$80,Teams!$E$18,0) -> 60 | K64: =IF(K$4>=Teams!$E$80,Teams!$E$18,0) -> 60 | L64: =IF(L$4>=Teams!$E$80,Teams!$E$18,0) -> 60 | ... BL64: =IF(BL$4>=Teams!$E$80,Teams!$E$18,0) -> 60
A65: Active users | C65: =SUMPRODUCT(E65:BL65,E$5:BL$5) -> 1657.5 | E65: =E64*Teams!$E$19*E63 -> 0 | F65: =F64*Teams!$E$19*F63 -> 3.7777778 | G65: =G64*Teams!$E$19*G63 -> 13.222222 | H65: =H64*Teams!$E$19*H63 -> 25.5 | I65: =I64*Teams!$E$19*I63 -> 37.777778 | J65: =J64*Teams!$E$19*J63 -> 47.222222 | K65: =K64*Teams!$E$19*K63 -> 51 | L65: =L64*Teams!$E$19*L63 -> 51 | ... BL65: =BL64*Teams!$E$19*BL63 -> 51
A66: Outcomes | C66: =SUMPRODUCT(E66:BL66,E$5:BL$5) -> 1300000 | E66: =IF(Teams!$E$23="per user",E65*Teams!$E$24,Teams!$E$25*E63) -> 0 | F66: =IF(Teams!$E$23="per user",F65*Teams!$E$24,Teams!$E$25*F63) -> 2962.963 | G66: =IF(Teams!$E$23="per user",G65*Teams!$E$24,Teams!$E$25*G63) -> 10370.37 | H66: =IF(Teams!$E$23="per user",H65*Teams!$E$24,Teams!$E$25*H63) -> 20000 | I66: =IF(Teams!$E$23="per user",I65*Teams!$E$24,Teams!$E$25*I63) -> 29629.63 | J66: =IF(Teams!$E$23="per user",J65*Teams!$E$24,Teams!$E$25*J63) -> 37037.037 | K66: =IF(Teams!$E$23="per user",K65*Teams!$E$24,Teams!$E$25*K63) -> 40000 | L66: =IF(Teams!$E$23="per user",L65*Teams!$E$24,Teams!$E$25*L63) -> 40000 | ... BL66: =IF(Teams!$E$23="per user",BL65*Teams!$E$24,Teams!$E$25*BL63) -> 40000
A67: Seats (CL-21) | B67: A | C67: =SUM(D67:BL67) -> 0 | E67: =E$5*Teams!$E$60*E64*Teams!$E$66 -> 0 | F67: =F$5*Teams!$E$60*F64*Teams!$E$66 -> 0 | G67: =G$5*Teams!$E$60*G64*Teams!$E$66 -> 0 | H67: =H$5*Teams!$E$60*H64*Teams!$E$66 -> 0 | I67: =I$5*Teams!$E$60*I64*Teams!$E$66 -> 0 | J67: =J$5*Teams!$E$60*J64*Teams!$E$66 -> 0 | K67: =K$5*Teams!$E$60*K64*Teams!$E$66 -> 0 | L67: =L$5*Teams!$E$60*L64*Teams!$E$66 -> 0 | ... BL67: =BL$5*Teams!$E$60*BL64*Teams!$E$66 -> 0
A68: Model tokens incl. retries and agent steps (CL-16, CL-17) | B68: A | C68: =SUM(D68:BL68) -> 0 | E68: =E$5*IF(Teams!$E$61=1,E65*((1-Teams!$E$13)*MAX(0,Teams!$E$72*$C$62-Teams!$E$12)+Teams!$E$13*MAX(0,Teams!$E$73*$C$62-Teams!$E$12)),IF(Teams!$E$62=1,E66*$C$62,0)) -> 0 | F68: =F$5*IF(Teams!$E$61=1,F65*((1-Teams!$E$13)*MAX(0,Teams!$E$72*$C$62-Teams!$E$12)+Teams!$E$13*MAX(0,Teams!$E$73*$C$62-Teams!$E$12)),IF(Teams!$E$62=1,F66*$C$62,0)) -> 0 | G68: =G$5*IF(Teams!$E$61=1,G65*((1-Teams!$E$13)*MAX(0,Teams!$E$72*$C$62-Teams!$E$12)+Teams!$E$13*MAX(0,Teams!$E$73*$C$62-Teams!$E$12)),IF(Teams!$E$62=1,G66*$C$62,0)) -> 0 | H68: =H$5*IF(Teams!$E$61=1,H65*((1-Teams!$E$13)*MAX(0,Teams!$E$72*$C$62-Teams!$E$12)+Teams!$E$13*MAX(0,Teams!$E$73*$C$62-Teams!$E$12)),IF(Teams!$E$62=1,H66*$C$62,0)) -> 0 | I68: =I$5*IF(Teams!$E$61=1,I65*((1-Teams!$E$13)*MAX(0,Teams!$E$72*$C$62-Teams!$E$12)+Teams!$E$13*MAX(0,Teams!$E$73*$C$62-Teams!$E$12)),IF(Teams!$E$62=1,I66*$C$62,0)) -> 0 | J68: =J$5*IF(Teams!$E$61=1,J65*((1-Teams!$E$13)*MAX(0,Teams!$E$72*$C$62-Teams!$E$12)+Teams!$E$13*MAX(0,Teams!$E$73*$C$62-Teams!$E$12)),IF(Teams!$E$62=1,J66*$C$62,0)) -> 0 | K68: =K$5*IF(Teams!$E$61=1,K65*((1-Teams!$E$13)*MAX(0,Teams!$E$72*$C$62-Teams!$E$12)+Teams!$E$13*MAX(0,Teams!$E$73*$C$62-Teams!$E$12)),IF(Teams!$E$62=1,K66*$C$62,0)) -> 0 | L68: =L$5*IF(Teams!$E$61=1,L65*((1-Teams!$E$13)*MAX(0,Teams!$E$72*$C$62-Teams!$E$12)+Teams!$E$13*MAX(0,Teams!$E$73*$C$62-Teams!$E$12)),IF(Teams!$E$62=1,L66*$C$62,0)) -> 0 | ... BL68: =BL$5*IF(Teams!$E$61=1,BL65*((1-Teams!$E$13)*MAX(0,Teams!$E$72*$C$62-Teams!$E$12)+Teams!$E$13*MAX(0,Teams!$E$73*$C$62-Teams!$E$12)),IF(Teams!$E$62=1,BL66*$C$62,0)) -> 0
A69: Vendor per-outcome price (CL-22) | B69: A | C69: =SUM(D69:BL69) -> 1287000 | E69: =E$5*Teams!$E$63*E66*Teams!$E$67 -> 0 | F69: =F$5*Teams!$E$63*F66*Teams!$E$67 -> 2933.3333 | G69: =G$5*Teams!$E$63*G66*Teams!$E$67 -> 10266.667 | H69: =H$5*Teams!$E$63*H66*Teams!$E$67 -> 19800 | I69: =I$5*Teams!$E$63*I66*Teams!$E$67 -> 29333.333 | J69: =J$5*Teams!$E$63*J66*Teams!$E$67 -> 36666.667 | K69: =K$5*Teams!$E$63*K66*Teams!$E$67 -> 39600 | L69: =L$5*Teams!$E$63*L66*Teams!$E$67 -> 39600 | ... BL69: =BL$5*Teams!$E$63*BL66*Teams!$E$67 -> 0
A70: Tool and guardrail calls (CL-18, CL-19) | B70: A | C70: =SUM(D70:BL70) -> 0 | E70: =E$5*Teams!$E$65*E66*Teams!$E$74 -> 0 | F70: =F$5*Teams!$E$65*F66*Teams!$E$74 -> 0 | G70: =G$5*Teams!$E$65*G66*Teams!$E$74 -> 0 | H70: =H$5*Teams!$E$65*H66*Teams!$E$74 -> 0 | I70: =I$5*Teams!$E$65*I66*Teams!$E$74 -> 0 | J70: =J$5*Teams!$E$65*J66*Teams!$E$74 -> 0 | K70: =K$5*Teams!$E$65*K66*Teams!$E$74 -> 0 | L70: =L$5*Teams!$E$65*L66*Teams!$E$74 -> 0 | ... BL70: =BL$5*Teams!$E$65*BL66*Teams!$E$74 -> 0
A71: Committed capacity (CL-15) | B71: E | C71: =SUM(D71:BL71) -> 0 | E71: =E$5*Teams!$E$64*Teams!$E$16*IF(E$4>=Teams!$E$80,1,0) -> 0 | F71: =F$5*Teams!$E$64*Teams!$E$16*IF(F$4>=Teams!$E$80,1,0) -> 0 | G71: =G$5*Teams!$E$64*Teams!$E$16*IF(G$4>=Teams!$E$80,1,0) -> 0 | H71: =H$5*Teams!$E$64*Teams!$E$16*IF(H$4>=Teams!$E$80,1,0) -> 0 | I71: =I$5*Teams!$E$64*Teams!$E$16*IF(I$4>=Teams!$E$80,1,0) -> 0 | J71: =J$5*Teams!$E$64*Teams!$E$16*IF(J$4>=Teams!$E$80,1,0) -> 0 | K71: =K$5*Teams!$E$64*Teams!$E$16*IF(K$4>=Teams!$E$80,1,0) -> 0 | L71: =L$5*Teams!$E$64*Teams!$E$16*IF(L$4>=Teams!$E$80,1,0) -> 0 | ... BL71: =BL$5*Teams!$E$64*Teams!$E$16*IF(BL$4>=Teams!$E$80,1,0) -> 0
A72: Parsing, embeddings, index, retrieval (CL-05 to CL-08) | B72: A | C72: =SUM(D72:BL72) -> 0 | E72: =E$5*IF(AND(E$4>=Teams!$E$80,Teams!$E$49=1),Teams!$E$44*Params!$D$10*Teams!$E$45*Teams!$E$75+Teams!$E$44*Params!$D$10*Teams!$E$47*Teams!$E$76/1000000+Teams!$E$77+Teams!$E$50*Teams!$E$78+E66*Teams!$E$51*Teams!$E$79/1000000,0) -> 0 | F72: =F$5*IF(AND(F$4>=Teams!$E$80,Teams!$E$49=1),Teams!$E$44*Params!$D$10*Teams!$E$45*Teams!$E$75+Teams!$E$44*Params!$D$10*Teams!$E$47*Teams!$E$76/1000000+Teams!$E$77+Teams!$E$50*Teams!$E$78+F66*Teams!$E$51*Teams!$E$79/1000000,0) -> 0 | G72: =G$5*IF(AND(G$4>=Teams!$E$80,Teams!$E$49=1),Teams!$E$44*Params!$D$10*Teams!$E$45*Teams!$E$75+Teams!$E$44*Params!$D$10*Teams!$E$47*Teams!$E$76/1000000+Teams!$E$77+Teams!$E$50*Teams!$E$78+G66*Teams!$E$51*Teams!$E$79/1000000,0) -> 0 | H72: =H$5*IF(AND(H$4>=Teams!$E$80,Teams!$E$49=1),Teams!$E$44*Params!$D$10*Teams!$E$45*Teams!$E$75+Teams!$E$44*Params!$D$10*Teams!$E$47*Teams!$E$76/1000000+Teams!$E$77+Teams!$E$50*Teams!$E$78+H66*Teams!$E$51*Teams!$E$79/1000000,0) -> 0 | I72: =I$5*IF(AND(I$4>=Teams!$E$80,Teams!$E$49=1),Teams!$E$44*Params!$D$10*Teams!$E$45*Teams!$E$75+Teams!$E$44*Params!$D$10*Teams!$E$47*Teams!$E$76/1000000+Teams!$E$77+Teams!$E$50*Teams!$E$78+I66*Teams!$E$51*Teams!$E$79/1000000,0) -> 0 | J72: =J$5*IF(AND(J$4>=Teams!$E$80,Teams!$E$49=1),Teams!$E$44*Params!$D$10*Teams!$E$45*Teams!$E$75+Teams!$E$44*Params!$D$10*Teams!$E$47*Teams!$E$76/1000000+Teams!$E$77+Teams!$E$50*Teams!$E$78+J66*Teams!$E$51*Teams!$E$79/1000000,0) -> 0 | K72: =K$5*IF(AND(K$4>=Teams!$E$80,Teams!$E$49=1),Teams!$E$44*Params!$D$10*Teams!$E$45*Teams!$E$75+Teams!$E$44*Params!$D$10*Teams!$E$47*Teams!$E$76/1000000+Teams!$E$77+Teams!$E$50*Teams!$E$78+K66*Teams!$E$51*Teams!$E$79/1000000,0) -> 0 | L72: =L$5*IF(AND(L$4>=Teams!$E$80,Teams!$E$49=1),Teams!$E$44*Params!$D$10*Teams!$E$45*Teams!$E$75+Teams!$E$44*Params!$D$10*Teams!$E$47*Teams!$E$76/1000000+Teams!$E$77+Teams!$E$50*Teams!$E$78+L66*Teams!$E$51*Teams!$E$79/1000000,0) -> 0 | ... BL72: =BL$5*IF(AND(BL$4>=Teams!$E$80,Teams!$E$49=1),Teams!$E$44*Params!$D$10*Teams!$E$45*Teams!$E$75+Teams!$E$44*Params!$D$10*Teams!$E$47*Teams!$E$76/1000000+Teams!$E$77+Teams!$E$50*Teams!$E$78+BL66*Teams!$E$51*Teams!$E$79/1000000,0) -> 0
A73: Connector upkeep (CL-03) | B73: S | C73: =SUM(D73:BL73) -> 3500 | E73: =E$5*IF(E$4>=Teams!$E$80,Teams!$E$43*Params!$D$6*Org!$B$10*Params!$D$7/12,0) -> 0 | F73: =F$5*IF(F$4>=Teams!$E$80,Teams!$E$43*Params!$D$6*Org!$B$10*Params!$D$7/12,0) -> 100 | G73: =G$5*IF(G$4>=Teams!$E$80,Teams!$E$43*Params!$D$6*Org!$B$10*Params!$D$7/12,0) -> 100 | H73: =H$5*IF(H$4>=Teams!$E$80,Teams!$E$43*Params!$D$6*Org!$B$10*Params!$D$7/12,0) -> 100 | I73: =I$5*IF(I$4>=Teams!$E$80,Teams!$E$43*Params!$D$6*Org!$B$10*Params!$D$7/12,0) -> 100 | J73: =J$5*IF(J$4>=Teams!$E$80,Teams!$E$43*Params!$D$6*Org!$B$10*Params!$D$7/12,0) -> 100 | K73: =K$5*IF(K$4>=Teams!$E$80,Teams!$E$43*Params!$D$6*Org!$B$10*Params!$D$7/12,0) -> 100 | L73: =L$5*IF(L$4>=Teams!$E$80,Teams!$E$43*Params!$D$6*Org!$B$10*Params!$D$7/12,0) -> 100 | ... BL73: =BL$5*IF(BL$4>=Teams!$E$80,Teams!$E$43*Params!$D$6*Org!$B$10*Params!$D$7/12,0) -> 0
A74: Quality review, maintenance, support (CL-25, CL-27, CL-28) | B74: S | C74: =SUM(D74:BL74) -> 16747.708 | E74: =E$5*IF(E$4>=Teams!$E$80,Params!$D$23*Params!$D$24/60*(Org!$B$10/Org!$B$11)+Params!$D$27/12*Params!$D$13*Org!$B$10+E65/1000*Params!$D$28*Params!$D$29*(Org!$B$10/Org!$B$11),0) -> 0 | F74: =F$5*IF(F$4>=Teams!$E$80,Params!$D$23*Params!$D$24/60*(Org!$B$10/Org!$B$11)+Params!$D$27/12*Params!$D$13*Org!$B$10+F65/1000*Params!$D$28*Params!$D$29*(Org!$B$10/Org!$B$11),0) -> 467.61111 | G74: =G$5*IF(G$4>=Teams!$E$80,Params!$D$23*Params!$D$24/60*(Org!$B$10/Org!$B$11)+Params!$D$27/12*Params!$D$13*Org!$B$10+G65/1000*Params!$D$28*Params!$D$29*(Org!$B$10/Org!$B$11),0) -> 469.97222 | H74: =H$5*IF(H$4>=Teams!$E$80,Params!$D$23*Params!$D$24/60*(Org!$B$10/Org!$B$11)+Params!$D$27/12*Params!$D$13*Org!$B$10+H65/1000*Params!$D$28*Params!$D$29*(Org!$B$10/Org!$B$11),0) -> 473.04167 | I74: =I$5*IF(I$4>=Teams!$E$80,Params!$D$23*Params!$D$24/60*(Org!$B$10/Org!$B$11)+Params!$D$27/12*Params!$D$13*Org!$B$10+I65/1000*Params!$D$28*Params!$D$29*(Org!$B$10/Org!$B$11),0) -> 476.11111 | J74: =J$5*IF(J$4>=Teams!$E$80,Params!$D$23*Params!$D$24/60*(Org!$B$10/Org!$B$11)+Params!$D$27/12*Params!$D$13*Org!$B$10+J65/1000*Params!$D$28*Params!$D$29*(Org!$B$10/Org!$B$11),0) -> 478.47222 | K74: =K$5*IF(K$4>=Teams!$E$80,Params!$D$23*Params!$D$24/60*(Org!$B$10/Org!$B$11)+Params!$D$27/12*Params!$D$13*Org!$B$10+K65/1000*Params!$D$28*Params!$D$29*(Org!$B$10/Org!$B$11),0) -> 479.41667 | L74: =L$5*IF(L$4>=Teams!$E$80,Params!$D$23*Params!$D$24/60*(Org!$B$10/Org!$B$11)+Params!$D$27/12*Params!$D$13*Org!$B$10+L65/1000*Params!$D$28*Params!$D$29*(Org!$B$10/Org!$B$11),0) -> 479.41667 | ... BL74: =BL$5*IF(BL$4>=Teams!$E$80,Params!$D$23*Params!$D$24/60*(Org!$B$10/Org!$B$11)+Params!$D$27/12*Params!$D$13*Org!$B$10+BL65/1000*Params!$D$28*Params!$D$29*(Org!$B$10/Org!$B$11),0) -> 0
A75: Model migration events (CL-26) | B75: R | C75: =SUM(D75:BL75) -> 1760 | E75: =E$5*IF(AND(E$4>Teams!$E$80,MOD(E$4-Teams!$E$80,MAX(1,ROUND(Params!$D$25,0)))=0),(Params!$D$26+Params!$D$17*Params!$D$16)*Org!$B$10,0) -> 0 | F75: =F$5*IF(AND(F$4>Teams!$E$80,MOD(F$4-Teams!$E$80,MAX(1,ROUND(Params!$D$25,0)))=0),(Params!$D$26+Params!$D$17*Params!$D$16)*Org!$B$10,0) -> 0 | G75: =G$5*IF(AND(G$4>Teams!$E$80,MOD(G$4-Teams!$E$80,MAX(1,ROUND(Params!$D$25,0)))=0),(Params!$D$26+Params!$D$17*Params!$D$16)*Org!$B$10,0) -> 0 | H75: =H$5*IF(AND(H$4>Teams!$E$80,MOD(H$4-Teams!$E$80,MAX(1,ROUND(Params!$D$25,0)))=0),(Params!$D$26+Params!$D$17*Params!$D$16)*Org!$B$10,0) -> 0 | I75: =I$5*IF(AND(I$4>Teams!$E$80,MOD(I$4-Teams!$E$80,MAX(1,ROUND(Params!$D$25,0)))=0),(Params!$D$26+Params!$D$17*Params!$D$16)*Org!$B$10,0) -> 0 | J75: =J$5*IF(AND(J$4>Teams!$E$80,MOD(J$4-Teams!$E$80,MAX(1,ROUND(Params!$D$25,0)))=0),(Params!$D$26+Params!$D$17*Params!$D$16)*Org!$B$10,0) -> 0 | K75: =K$5*IF(AND(K$4>Teams!$E$80,MOD(K$4-Teams!$E$80,MAX(1,ROUND(Params!$D$25,0)))=0),(Params!$D$26+Params!$D$17*Params!$D$16)*Org!$B$10,0) -> 0 | L75: =L$5*IF(AND(L$4>Teams!$E$80,MOD(L$4-Teams!$E$80,MAX(1,ROUND(Params!$D$25,0)))=0),(Params!$D$26+Params!$D$17*Params!$D$16)*Org!$B$10,0) -> 0 | ... BL75: =BL$5*IF(AND(BL$4>Teams!$E$80,MOD(BL$4-Teams!$E$80,MAX(1,ROUND(Params!$D$25,0)))=0),(Params!$D$26+Params!$D$17*Params!$D$16)*Org!$B$10,0) -> 0
A76: Human review of output (CL-34) | B76: R | C76: =SUM(D76:BL76) -> 101595 | E76: =E$5*E66*MIN(1,Teams!$E$41*Params!$D$35)*Params!$D$36/60*Teams!$E$42 -> 0 | F76: =F$5*F66*MIN(1,Teams!$E$41*Params!$D$35)*Params!$D$36/60*Teams!$E$42 -> 231.55556 | G76: =G$5*G66*MIN(1,Teams!$E$41*Params!$D$35)*Params!$D$36/60*Teams!$E$42 -> 810.44444 | H76: =H$5*H66*MIN(1,Teams!$E$41*Params!$D$35)*Params!$D$36/60*Teams!$E$42 -> 1563 | I76: =I$5*I66*MIN(1,Teams!$E$41*Params!$D$35)*Params!$D$36/60*Teams!$E$42 -> 2315.5556 | J76: =J$5*J66*MIN(1,Teams!$E$41*Params!$D$35)*Params!$D$36/60*Teams!$E$42 -> 2894.4444 | K76: =K$5*K66*MIN(1,Teams!$E$41*Params!$D$35)*Params!$D$36/60*Teams!$E$42 -> 3126 | L76: =L$5*L66*MIN(1,Teams!$E$41*Params!$D$35)*Params!$D$36/60*Teams!$E$42 -> 3126 | ... BL76: =BL$5*BL66*MIN(1,Teams!$E$41*Params!$D$35)*Params!$D$36/60*Teams!$E$42 -> 0
A77: Change champions (CL-35) | B77: S | C77: =SUM(D77:BL77) -> 2596 | E77: =E$5*IF(E$4>=Teams!$E$80,E64/1000*IF(E$4-Teams!$E$80<6,Params!$D$37,Params!$D$38)*Org!$B$10*Org!$B$12/12,0) -> 0 | F77: =F$5*IF(F$4>=Teams!$E$80,F64/1000*IF(F$4-Teams!$E$80<6,Params!$D$37,Params!$D$38)*Org!$B$10*Org!$B$12/12,0) -> 220 | G77: =G$5*IF(G$4>=Teams!$E$80,G64/1000*IF(G$4-Teams!$E$80<6,Params!$D$37,Params!$D$38)*Org!$B$10*Org!$B$12/12,0) -> 220 | H77: =H$5*IF(H$4>=Teams!$E$80,H64/1000*IF(H$4-Teams!$E$80<6,Params!$D$37,Params!$D$38)*Org!$B$10*Org!$B$12/12,0) -> 220 | I77: =I$5*IF(I$4>=Teams!$E$80,I64/1000*IF(I$4-Teams!$E$80<6,Params!$D$37,Params!$D$38)*Org!$B$10*Org!$B$12/12,0) -> 220 | J77: =J$5*IF(J$4>=Teams!$E$80,J64/1000*IF(J$4-Teams!$E$80<6,Params!$D$37,Params!$D$38)*Org!$B$10*Org!$B$12/12,0) -> 220 | K77: =K$5*IF(K$4>=Teams!$E$80,K64/1000*IF(K$4-Teams!$E$80<6,Params!$D$37,Params!$D$38)*Org!$B$10*Org!$B$12/12,0) -> 220 | L77: =L$5*IF(L$4>=Teams!$E$80,L64/1000*IF(L$4-Teams!$E$80<6,Params!$D$37,Params!$D$38)*Org!$B$10*Org!$B$12/12,0) -> 44 | ... BL77: =BL$5*IF(BL$4>=Teams!$E$80,BL64/1000*IF(BL$4-Teams!$E$80<6,Params!$D$37,Params!$D$38)*Org!$B$10*Org!$B$12/12,0) -> 0
A78: One-time: assess, clean, connect (CL-01 to CL-03) | B78: S | C78: =SUM(D78:BL78) -> 14720 | D78: =Teams!$E$5*((Teams!$E$43*Params!$D$4+Teams!$E$44/100000*Params!$D$5+Teams!$E$43*Params!$D$6)*Org!$B$10) -> 14720
A79: One-time: initial parse and embed (CL-05, CL-06) | B79: A | C79: =SUM(D79:BL79) -> 0 | D79: =Teams!$E$5*(Teams!$E$49*(Teams!$E$44*Teams!$E$45*Teams!$E$75+Teams!$E$44*Teams!$E$47*Teams!$E$76/1000000)) -> 0
A80: One-time: integrate, evaluation harness (CL-10, CL-12) | B80: S | C80: =SUM(D80:BL80) -> 18400 | D80: =Teams!$E$5*((Params!$D$13+Params!$D$16)*Org!$B$10) -> 18400
A81: One-time: training (CL-33) | B81: S | C81: =SUM(D81:BL81) -> 10200 | D81: =Teams!$E$5*(Teams!$E$18*Teams!$E$19*Params!$D$34*(Org!$B$10/Org!$B$11)) -> 10200
A82: Benefit | C82: =SUM(D82:BL82) -> 2590672.5 | E82: =E$5*E66*Teams!$E$55/60*Teams!$E$56*INDEX(Params!$D$41:$F$41,Org!$B$17)*Teams!$E$57 -> 0 | F82: =F$5*F66*Teams!$E$55/60*Teams!$E$56*INDEX(Params!$D$41:$F$41,Org!$B$17)*Teams!$E$57 -> 5904.6667 | G82: =G$5*G66*Teams!$E$55/60*Teams!$E$56*INDEX(Params!$D$41:$F$41,Org!$B$17)*Teams!$E$57 -> 20666.333 | H82: =H$5*H66*Teams!$E$55/60*Teams!$E$56*INDEX(Params!$D$41:$F$41,Org!$B$17)*Teams!$E$57 -> 39856.5 | I82: =I$5*I66*Teams!$E$55/60*Teams!$E$56*INDEX(Params!$D$41:$F$41,Org!$B$17)*Teams!$E$57 -> 59046.667 | J82: =J$5*J66*Teams!$E$55/60*Teams!$E$56*INDEX(Params!$D$41:$F$41,Org!$B$17)*Teams!$E$57 -> 73808.333 | K82: =K$5*K66*Teams!$E$55/60*Teams!$E$56*INDEX(Params!$D$41:$F$41,Org!$B$17)*Teams!$E$57 -> 79713 | L82: =L$5*L66*Teams!$E$55/60*Teams!$E$56*INDEX(Params!$D$41:$F$41,Org!$B$17)*Teams!$E$57 -> 79713 | ... BL82: =BL$5*BL66*Teams!$E$55/60*Teams!$E$56*INDEX(Params!$D$41:$F$41,Org!$B$17)*Teams!$E$57 -> 0
A83: Direct cost | C83: =SUM(D83:BL83) -> 1456518.7 | D83: =SUM(D67:D81) -> 43320 | E83: =SUM(E67:E81) -> 0 | F83: =SUM(F67:F81) -> 3952.5 | G83: =SUM(G67:G81) -> 11867.083 | H83: =SUM(H67:H81) -> 22156.042 | I83: =SUM(I67:I81) -> 32445 | J83: =SUM(J67:J81) -> 40359.583 | K83: =SUM(K67:K81) -> 43525.417 | ... BL83: =SUM(BL67:BL81) -> 0
A84: Allocated hub cost | C84: =SUM(D84:BL84) -> 214101.7 | D84: =$D$169*D158 -> 12241.135 | E84: =$D$169*E158 -> 5594.7338 | F84: =$D$169*F158 -> 5597.657 | G84: =$D$169*G158 -> 5601.2545 | H84: =$D$169*H158 -> 5605.0247 | I84: =$D$169*I158 -> 5607.0232 | J84: =$D$169*J158 -> 5608.0447 | K84: =$D$169*K158 -> 5608.2276 | ... BL84: =$D$169*BL158 -> 0
A85: Net cash | C85: =SUM(D85:BL85) -> 920052.09 | D85: =D82-D83-D84 -> -55561.135 | E85: =E82-E83-E84 -> -5594.7338 | F85: =F82-F83-F84 -> -3645.4903 | G85: =G82-G83-G84 -> 3197.9955 | H85: =H82-H83-H84 -> 12095.434 | I85: =I82-I83-I84 -> 20994.643 | J85: =J82-J83-J84 -> 27840.705 | K85: =K82-K83-K84 -> 30579.356 | ... BL85: =BL82-BL83-BL84 -> 0
A86: Cumulative net cash | D86: =D85 -> -55561.135 | E86: =D86+E85 -> -61155.869 | F86: =E86+F85 -> -64801.359 | G86: =F86+G85 -> -61603.364 | H86: =G86+H85 -> -49507.93 | I86: =H86+I85 -> -28513.287 | J86: =I86+J85 -> -672.58141 | K86: =J86+K85 -> 29906.774 | L86: =K86+L85 -> 60662.13 | ... BL86: =BK86+BL85 -> 920052.09
A87: Payback flag (month) | C87: =IF(COUNT(E87:BL87)=0,"None",MIN(E87:BL87)) -> 7 | E87: =IF(AND(E$4<=Org!$B$5,E86>=0),E$4,"") | F87: =IF(AND(F$4<=Org!$B$5,F86>=0),F$4,"") | G87: =IF(AND(G$4<=Org!$B$5,G86>=0),G$4,"") | H87: =IF(AND(H$4<=Org!$B$5,H86>=0),H$4,"") | I87: =IF(AND(I$4<=Org!$B$5,I86>=0),I$4,"") | J87: =IF(AND(J$4<=Org!$B$5,J86>=0),J$4,"") | K87: =IF(AND(K$4<=Org!$B$5,K86>=0),K$4,"") -> 7 | L87: =IF(AND(L$4<=Org!$B$5,L86>=0),L$4,"") -> 8 | ... BL87: =IF(AND(BL$4<=Org!$B$5,BL86>=0),BL$4,"")
A89: =Teams!$F$4 -> Regulated document review | B89: Token cost per outcome: | C89: =(Teams!$F$29*(1-Teams!$F$31)*Params!$D$39*Params!$D$21*IF(Teams!$F$36="Yes",Params!$D$22,1)*Teams!$F$68*Teams!$F$70+Teams!$F$30*(1-Teams!$F$31)*Params!$D$39*Params!$D$21*IF(Teams!$F$36="Yes",Params!$D$22,1)*Teams!$F$69)/1000000*Teams!$F$71*Teams!$F$35 -> 0.067404645
A90: Ramp factor | E90: =IF(E$4<Teams!$F$80,0,IF(Teams!$F$22="S",MIN(1,(E$4-Teams!$F$80+1)/Teams!$F$21)^2*(3-2*MIN(1,(E$4-Teams!$F$80+1)/Teams!$F$21)),MIN(1,(E$4-Teams!$F$80+1)/Teams!$F$21))) -> 0 | F90: =IF(F$4<Teams!$F$80,0,IF(Teams!$F$22="S",MIN(1,(F$4-Teams!$F$80+1)/Teams!$F$21)^2*(3-2*MIN(1,(F$4-Teams!$F$80+1)/Teams!$F$21)),MIN(1,(F$4-Teams!$F$80+1)/Teams!$F$21))) -> 0 | G90: =IF(G$4<Teams!$F$80,0,IF(Teams!$F$22="S",MIN(1,(G$4-Teams!$F$80+1)/Teams!$F$21)^2*(3-2*MIN(1,(G$4-Teams!$F$80+1)/Teams!$F$21)),MIN(1,(G$4-Teams!$F$80+1)/Teams!$F$21))) -> 0.104 | H90: =IF(H$4<Teams!$F$80,0,IF(Teams!$F$22="S",MIN(1,(H$4-Teams!$F$80+1)/Teams!$F$21)^2*(3-2*MIN(1,(H$4-Teams!$F$80+1)/Teams!$F$21)),MIN(1,(H$4-Teams!$F$80+1)/Teams!$F$21))) -> 0.352 | I90: =IF(I$4<Teams!$F$80,0,IF(Teams!$F$22="S",MIN(1,(I$4-Teams!$F$80+1)/Teams!$F$21)^2*(3-2*MIN(1,(I$4-Teams!$F$80+1)/Teams!$F$21)),MIN(1,(I$4-Teams!$F$80+1)/Teams!$F$21))) -> 0.648 | J90: =IF(J$4<Teams!$F$80,0,IF(Teams!$F$22="S",MIN(1,(J$4-Teams!$F$80+1)/Teams!$F$21)^2*(3-2*MIN(1,(J$4-Teams!$F$80+1)/Teams!$F$21)),MIN(1,(J$4-Teams!$F$80+1)/Teams!$F$21))) -> 0.896 | K90: =IF(K$4<Teams!$F$80,0,IF(Teams!$F$22="S",MIN(1,(K$4-Teams!$F$80+1)/Teams!$F$21)^2*(3-2*MIN(1,(K$4-Teams!$F$80+1)/Teams!$F$21)),MIN(1,(K$4-Teams!$F$80+1)/Teams!$F$21))) -> 1 | L90: =IF(L$4<Teams!$F$80,0,IF(Teams!$F$22="S",MIN(1,(L$4-Teams!$F$80+1)/Teams!$F$21)^2*(3-2*MIN(1,(L$4-Teams!$F$80+1)/Teams!$F$21)),MIN(1,(L$4-Teams!$F$80+1)/Teams!$F$21))) -> 1 | ... BL90: =IF(BL$4<Teams!$F$80,0,IF(Teams!$F$22="S",MIN(1,(BL$4-Teams!$F$80+1)/Teams!$F$21)^2*(3-2*MIN(1,(BL$4-Teams!$F$80+1)/Teams!$F$21)),MIN(1,(BL$4-Teams!$F$80+1)/Teams!$F$21))) -> 1
A91: Licensed users | E91: =IF(E$4>=Teams!$F$80,Teams!$F$18,0) -> 0 | F91: =IF(F$4>=Teams!$F$80,Teams!$F$18,0) -> 0 | G91: =IF(G$4>=Teams!$F$80,Teams!$F$18,0) -> 150 | H91: =IF(H$4>=Teams!$F$80,Teams!$F$18,0) -> 150 | I91: =IF(I$4>=Teams!$F$80,Teams!$F$18,0) -> 150 | J91: =IF(J$4>=Teams!$F$80,Teams!$F$18,0) -> 150 | K91: =IF(K$4>=Teams!$F$80,Teams!$F$18,0) -> 150 | L91: =IF(L$4>=Teams!$F$80,Teams!$F$18,0) -> 150 | ... BL91: =IF(BL$4>=Teams!$F$80,Teams!$F$18,0) -> 150
A92: Active users | C92: =SUMPRODUCT(E92:BL92,E$5:BL$5) -> 3360 | E92: =E91*Teams!$F$19*E90 -> 0 | F92: =F91*Teams!$F$19*F90 -> 0 | G92: =G91*Teams!$F$19*G90 -> 10.92 | H92: =H91*Teams!$F$19*H90 -> 36.96 | I92: =I91*Teams!$F$19*I90 -> 68.04 | J92: =J91*Teams!$F$19*J90 -> 94.08 | K92: =K91*Teams!$F$19*K90 -> 105 | L92: =L91*Teams!$F$19*L90 -> 105 | ... BL92: =BL91*Teams!$F$19*BL90 -> 105
A93: Outcomes | C93: =SUMPRODUCT(E93:BL93,E$5:BL$5) -> 403200 | E93: =IF(Teams!$F$23="per user",E92*Teams!$F$24,Teams!$F$25*E90) -> 0 | F93: =IF(Teams!$F$23="per user",F92*Teams!$F$24,Teams!$F$25*F90) -> 0 | G93: =IF(Teams!$F$23="per user",G92*Teams!$F$24,Teams!$F$25*G90) -> 1310.4 | H93: =IF(Teams!$F$23="per user",H92*Teams!$F$24,Teams!$F$25*H90) -> 4435.2 | I93: =IF(Teams!$F$23="per user",I92*Teams!$F$24,Teams!$F$25*I90) -> 8164.8 | J93: =IF(Teams!$F$23="per user",J92*Teams!$F$24,Teams!$F$25*J90) -> 11289.6 | K93: =IF(Teams!$F$23="per user",K92*Teams!$F$24,Teams!$F$25*K90) -> 12600 | L93: =IF(Teams!$F$23="per user",L92*Teams!$F$24,Teams!$F$25*L90) -> 12600 | ... BL93: =IF(Teams!$F$23="per user",BL92*Teams!$F$24,Teams!$F$25*BL90) -> 12600
A94: Seats (CL-21) | B94: A | C94: =SUM(D94:BL94) -> 0 | E94: =E$5*Teams!$F$60*E91*Teams!$F$66 -> 0 | F94: =F$5*Teams!$F$60*F91*Teams!$F$66 -> 0 | G94: =G$5*Teams!$F$60*G91*Teams!$F$66 -> 0 | H94: =H$5*Teams!$F$60*H91*Teams!$F$66 -> 0 | I94: =I$5*Teams!$F$60*I91*Teams!$F$66 -> 0 | J94: =J$5*Teams!$F$60*J91*Teams!$F$66 -> 0 | K94: =K$5*Teams!$F$60*K91*Teams!$F$66 -> 0 | L94: =L$5*Teams!$F$60*L91*Teams!$F$66 -> 0 | ... BL94: =BL$5*Teams!$F$60*BL91*Teams!$F$66 -> 0
A95: Model tokens incl. retries and agent steps (CL-16, CL-17) | B95: A | C95: =SUM(D95:BL95) -> 27177.553 | E95: =E$5*IF(Teams!$F$61=1,E92*((1-Teams!$F$13)*MAX(0,Teams!$F$72*$C$89-Teams!$F$12)+Teams!$F$13*MAX(0,Teams!$F$73*$C$89-Teams!$F$12)),IF(Teams!$F$62=1,E93*$C$89,0)) -> 0 | F95: =F$5*IF(Teams!$F$61=1,F92*((1-Teams!$F$13)*MAX(0,Teams!$F$72*$C$89-Teams!$F$12)+Teams!$F$13*MAX(0,Teams!$F$73*$C$89-Teams!$F$12)),IF(Teams!$F$62=1,F93*$C$89,0)) -> 0 | G95: =G$5*IF(Teams!$F$61=1,G92*((1-Teams!$F$13)*MAX(0,Teams!$F$72*$C$89-Teams!$F$12)+Teams!$F$13*MAX(0,Teams!$F$73*$C$89-Teams!$F$12)),IF(Teams!$F$62=1,G93*$C$89,0)) -> 88.327047 | H95: =H$5*IF(Teams!$F$61=1,H92*((1-Teams!$F$13)*MAX(0,Teams!$F$72*$C$89-Teams!$F$12)+Teams!$F$13*MAX(0,Teams!$F$73*$C$89-Teams!$F$12)),IF(Teams!$F$62=1,H93*$C$89,0)) -> 298.95308 | I95: =I$5*IF(Teams!$F$61=1,I92*((1-Teams!$F$13)*MAX(0,Teams!$F$72*$C$89-Teams!$F$12)+Teams!$F$13*MAX(0,Teams!$F$73*$C$89-Teams!$F$12)),IF(Teams!$F$62=1,I93*$C$89,0)) -> 550.34545 | J95: =J$5*IF(Teams!$F$61=1,J92*((1-Teams!$F$13)*MAX(0,Teams!$F$72*$C$89-Teams!$F$12)+Teams!$F$13*MAX(0,Teams!$F$73*$C$89-Teams!$F$12)),IF(Teams!$F$62=1,J93*$C$89,0)) -> 760.97148 | K95: =K$5*IF(Teams!$F$61=1,K92*((1-Teams!$F$13)*MAX(0,Teams!$F$72*$C$89-Teams!$F$12)+Teams!$F$13*MAX(0,Teams!$F$73*$C$89-Teams!$F$12)),IF(Teams!$F$62=1,K93*$C$89,0)) -> 849.29853 | L95: =L$5*IF(Teams!$F$61=1,L92*((1-Teams!$F$13)*MAX(0,Teams!$F$72*$C$89-Teams!$F$12)+Teams!$F$13*MAX(0,Teams!$F$73*$C$89-Teams!$F$12)),IF(Teams!$F$62=1,L93*$C$89,0)) -> 849.29853 | ... BL95: =BL$5*IF(Teams!$F$61=1,BL92*((1-Teams!$F$13)*MAX(0,Teams!$F$72*$C$89-Teams!$F$12)+Teams!$F$13*MAX(0,Teams!$F$73*$C$89-Teams!$F$12)),IF(Teams!$F$62=1,BL93*$C$89,0)) -> 0
A96: Vendor per-outcome price (CL-22) | B96: A | C96: =SUM(D96:BL96) -> 0 | E96: =E$5*Teams!$F$63*E93*Teams!$F$67 -> 0 | F96: =F$5*Teams!$F$63*F93*Teams!$F$67 -> 0 | G96: =G$5*Teams!$F$63*G93*Teams!$F$67 -> 0 | H96: =H$5*Teams!$F$63*H93*Teams!$F$67 -> 0 | I96: =I$5*Teams!$F$63*I93*Teams!$F$67 -> 0 | J96: =J$5*Teams!$F$63*J93*Teams!$F$67 -> 0 | K96: =K$5*Teams!$F$63*K93*Teams!$F$67 -> 0 | L96: =L$5*Teams!$F$63*L93*Teams!$F$67 -> 0 | ... BL96: =BL$5*Teams!$F$63*BL93*Teams!$F$67 -> 0
A97: Tool and guardrail calls (CL-18, CL-19) | B97: A | C97: =SUM(D97:BL97) -> 7620.48 | E97: =E$5*Teams!$F$65*E93*Teams!$F$74 -> 0 | F97: =F$5*Teams!$F$65*F93*Teams!$F$74 -> 0 | G97: =G$5*Teams!$F$65*G93*Teams!$F$74 -> 24.76656 | H97: =H$5*Teams!$F$65*H93*Teams!$F$74 -> 83.82528 | I97: =I$5*Teams!$F$65*I93*Teams!$F$74 -> 154.31472 | J97: =J$5*Teams!$F$65*J93*Teams!$F$74 -> 213.37344 | K97: =K$5*Teams!$F$65*K93*Teams!$F$74 -> 238.14 | L97: =L$5*Teams!$F$65*L93*Teams!$F$74 -> 238.14 | ... BL97: =BL$5*Teams!$F$65*BL93*Teams!$F$74 -> 0
A98: Committed capacity (CL-15) | B98: E | C98: =SUM(D98:BL98) -> 0 | E98: =E$5*Teams!$F$64*Teams!$F$16*IF(E$4>=Teams!$F$80,1,0) -> 0 | F98: =F$5*Teams!$F$64*Teams!$F$16*IF(F$4>=Teams!$F$80,1,0) -> 0 | G98: =G$5*Teams!$F$64*Teams!$F$16*IF(G$4>=Teams!$F$80,1,0) -> 0 | H98: =H$5*Teams!$F$64*Teams!$F$16*IF(H$4>=Teams!$F$80,1,0) -> 0 | I98: =I$5*Teams!$F$64*Teams!$F$16*IF(I$4>=Teams!$F$80,1,0) -> 0 | J98: =J$5*Teams!$F$64*Teams!$F$16*IF(J$4>=Teams!$F$80,1,0) -> 0 | K98: =K$5*Teams!$F$64*Teams!$F$16*IF(K$4>=Teams!$F$80,1,0) -> 0 | L98: =L$5*Teams!$F$64*Teams!$F$16*IF(L$4>=Teams!$F$80,1,0) -> 0 | ... BL98: =BL$5*Teams!$F$64*Teams!$F$16*IF(BL$4>=Teams!$F$80,1,0) -> 0
